Workbook

Sheet RESUMO
A1: Levantamento paramétrico - demandas de MP, Justiça e TCM (SEINFRA Ilhéus)
A2: PROVISORIO - aguarda aprovacao
A3: Estimativa preliminar paramétrica, não vinculante, para planejamento orçamentário. Preços SINAPI-BA 08/2026, não desonerado. Data: 13/10/2026. Levantamentos MP (pacote de 12/10) e Justiça (pacote de 13/10), sem dupla contagem.
A5: Nº | B5: Grupo-objeto | C5: Objeto | D5: Origem | E5: Levantamento | F5: Categoria | G5: Fonte das quantidades | H5: Mínimo (R$) | I5: Provável (R$) | J5: Máximo (R$) | K5: Aba
A6: 1 | B6: MPBA_001.9.102305.2021 | C6: Proteção e estabilização do prédio da Sociedade União Protetora dos Artífices e Operários (Centro) | D6: MPBA | E6: MP | F6: outro | G6: demanda-tipo (medidas do próprio documento) | H6: ='01_MPBA_001.9.102305.2021'!J62 -> 20375.387 | I6: ='01_MPBA_001.9.102305.2021'!K62 -> 31196.762 | J6: ='01_MPBA_001.9.102305.2021'!L62 -> 554590.52 | K6: 01_MPBA_001.9.102305.2021
A7: 2 | B7: MPBA_001.9.190096.2025 | C7: Conclusão de unidades escolares paralisadas (Recomendação MPBA 02/2025) | D7: MPBA | E7: MP | F7: escola/creche | G7: demanda-tipo (unidades não listadas) | H7: ='02_MPBA_001.9.190096.2025'!J55 -> 330852.01 | I7: ='02_MPBA_001.9.190096.2025'!K55 -> 781244.32 | J7: ='02_MPBA_001.9.190096.2025'!L55 -> 1609322.7 | K7: 02_MPBA_001.9.190096.2025
A8: 3 | B8: MPBA_001.9.24192.2024 | C8: Requalificação da drenagem pluvial da Av. Soares Lopes | D8: MPBA | E8: MP | F8: drenagem | G8: documento (extensão de 1.600 m) | H8: ='03_MPBA_001.9.24192.2024'!J41 -> 2199510.9 | I8: ='03_MPBA_001.9.24192.2024'!K41 -> 2756333 | J8: ='03_MPBA_001.9.24192.2024'!L41 -> 4174865.2 | K8: 03_MPBA_001.9.24192.2024
A9: 4 | B9: MPBA_001.9.250850.2021 | C9: Banheiro com chuveiro e grade na sede do Conselho Municipal de Educação | D9: MPBA | E9: MP | F9: outro | G9: demanda-tipo (banheiro-tipo) | H9: ='04_MPBA_001.9.250850.2021'!J38 -> 8137.2392 | I9: ='04_MPBA_001.9.250850.2021'!K38 -> 10266.795 | J9: ='04_MPBA_001.9.250850.2021'!L38 -> 16216.156 | K9: 04_MPBA_001.9.250850.2021
A10: 5 | B10: MPBA_001.9.379764.2023 | C10: Valetão aberto pela EMBASA em via pública (local não identificado) | D10: MPBA | E10: MP | F10: drenagem | G10: demanda-tipo (local não identificado) | H10: ='05_MPBA_001.9.379764.2023'!J39 -> 63307.487 | I10: ='05_MPBA_001.9.379764.2023'!K39 -> 118557.42 | J10: ='05_MPBA_001.9.379764.2023'!L39 -> 351155.12 | K10: 05_MPBA_001.9.379764.2023
A11: 6 | B11: MPBA_001.9.52800.2024 | C11: Quadra poliesportiva do distrito de Banco do Pedro | D11: MPBA | E11: MP | F11: quadra/esporte | G11: documento (1 quadra) + demanda-tipo | H11: ='06_MPBA_001.9.52800.2024'!J72 -> 638222.78 | I11: ='06_MPBA_001.9.52800.2024'!K72 -> 855621.59 | J11: ='06_MPBA_001.9.52800.2024'!L72 -> 1166732.3 | K11: 06_MPBA_001.9.52800.2024
A12: 7 | B12: MPBA_003.9.153337.2023 | C12: Reforma do Instituto Municipal de Ensino Eusínio Lavigne – IME (Av. Canavieiras, Centro) | D12: MPBA | E12: MP | F12: escola/creche | G12: demanda-tipo (área a confirmar) | H12: ='07_MPBA_003.9.153337.2023'!J53 -> 297660.86 | I12: ='07_MPBA_003.9.153337.2023'!K53 -> 907542.49 | J12: ='07_MPBA_003.9.153337.2023'!L53 -> 2481754 | K12: 07_MPBA_003.9.153337.2023
A13: 8 | B13: MPBA_003.9.198543.2025 | C13: Drenagem da Rua Jardim Alice (Banco da Vitória) | D13: MPBA | E13: MP | F13: drenagem | G13: demanda-tipo (escopo a confirmar) | H13: ='08_MPBA_003.9.198543.2025'!J39 -> 160465.94 | I13: ='08_MPBA_003.9.198543.2025'!K39 -> 282387.84 | J13: ='08_MPBA_003.9.198543.2025'!L39 -> 694200.07 | K13: 08_MPBA_003.9.198543.2025
A14: 9 | B14: MPBA_003.9.476383.2022 | C14: Drenagem da Rua Praia Dourada | D14: MPBA | E14: MP | F14: drenagem | G14: demanda-tipo (rua-tipo) | H14: ='09_MPBA_003.9.476383.2022'!J52 -> 307680.85 | I14: ='09_MPBA_003.9.476383.2022'!K52 -> 659546.56 | J14: ='09_MPBA_003.9.476383.2022'!L52 -> 1748983.5 | K14: 09_MPBA_003.9.476383.2022
A15: 10 | B15: MPF_1.14.001.000105-2023 | C15: Contenção de encosta da Rua Alto do Socorro (Conquista) | D15: MPF | E15: MP | F15: encosta/contenção | G15: documento (1.368,32 m², Meta 13 do Novo PAC) | H15: ='10_MPF_.000105-2023'!J33 -> 1328465.1 | I15: ='10_MPF_.000105-2023'!K33 -> 2292498.3 | J15: ='10_MPF_.000105-2023'!L33 -> 4832014.3 | K15: 10_MPF_.000105-2023
A16: 11 | B16: MPF_1.14.001.000183-2023 | C16: 96 casas e parques lineares pós-chuvas de 2021 (Salobrinho, Banco da Vitória e Vila Cachoeira) | D16: MPF | E16: MP | F16: habitação | G16: documento (96 casas e 5 parques lineares) | H16: ='11_MPF_.000183-2023'!J57 -> 7461124.6 | I16: ='11_MPF_.000183-2023'!K57 -> 8393660.7 | J16: ='11_MPF_.000183-2023'!L57 -> 10752292 | K16: 11_MPF_.000183-2023
A17: 12 | B17: SN_MPF-OBRAS_FNDE_2023 | C17: Obras FNDE: Escola Vila Lídia, Quadra do Vilela e Creche Nossa Senhora da Vitória | D17: MPF | E17: MP | F17: escola/creche | G17: demanda-tipo (situação das obras não informada) | H17: =12_SN_MPF_FNDE_2023!J138 -> 1290541.4 | I17: =12_SN_MPF_FNDE_2023!K138 -> 2284651.8 | J17: =12_SN_MPF_FNDE_2023!L138 -> 3763734.4 | K17: 12_SN_MPF_FNDE_2023
A18: 13 | B18: MPT_000120.2022.05.001.7 | C18: Condições de trabalho e reforma do prédio do SAMU de Ilhéus | D18: MPT | E18: MP | F18: outro | G18: demanda-tipo (área a confirmar) | H18: ='13_MPT_000120.2022'!J52 -> 43249.122 | I18: ='13_MPT_000120.2022'!K52 -> 139248.08 | J18: ='13_MPT_000120.2022'!L52 -> 400710.8 | K18: 13_MPT_000120.2022
A19: 14 | B19: MPT_000252.2024.05.001.5 | C19: Condições do prédio do Arquivo Público Municipal | D19: MPT | E19: MP | F19: outro | G19: demanda-tipo (área a confirmar) | H19: ='14_MPT_000252.2024'!J53 -> 62764.169 | I19: ='14_MPT_000252.2024'!K53 -> 229637.2 | J19: ='14_MPT_000252.2024'!L53 -> 797089.81 | K19: 14_MPT_000252.2024
A20: 15 | B20: MPT_000282.2023.05.001.4 | C20: Condições estruturais da Clínica Municipal de Atendimento Especializado - CMAE (Av. Canavieiras) | D20: MPT | E20: MP | F20: outro | G20: demanda-tipo (área a confirmar) | H20: ='15_MPT_000282.2023'!J52 -> 62764.169 | I20: ='15_MPT_000282.2023'!K52 -> 207030.95 | J20: ='15_MPT_000282.2023'!L52 -> 598900.3 | K20: 15_MPT_000282.2023
A21: 16 | B21: MPT_000393.2023.05.001.6 | C21: Cozinhas e áreas de limpeza das escolas municipais (saúde e segurança do trabalho) | D21: MPT | E21: MP | F21: escola/creche | G21: demanda-tipo (unidades não listadas) | H21: ='16_MPT_000393.2023'!J34 -> 41628.819 | I21: ='16_MPT_000393.2023'!K34 -> 88512.429 | J21: ='16_MPT_000393.2023'!L34 -> 208379.65 | K21: 16_MPT_000393.2023
A22: 17 | B22: JUSTICA_0006323-71.2012.8.05.0103 | C22: Requalificação do Estádio Municipal Mário Pessoa (Cidade Nova) – TAC | D22: Justiça | E22: MP | F22: quadra/esporte | G22: demanda-tipo (itens do TAC) | H22: ='17_TJBA_0006323-71.2012'!J61 -> 280956.1 | I22: ='17_TJBA_0006323-71.2012'!K61 -> 579542.15 | J22: ='17_TJBA_0006323-71.2012'!L61 -> 1434218.3 | K22: 17_TJBA_0006323-71.2012
A23: 18 | B23: JUSTICA_8003152-18.2022.8.05.0103 | C23: Drenagem pluvial e alagamentos nas Ruas Castro Alves e Barão do Rio Branco (Pontal) | D23: Justiça | E23: MP | F23: drenagem | G23: demanda-tipo (duas ruas) | H23: ='18_TJBA_8003152-18.2022'!J39 -> 315078.63 | I23: ='18_TJBA_8003152-18.2022'!K39 -> 549169.41 | J23: ='18_TJBA_8003152-18.2022'!L39 -> 1380290.2 | K23: 18_TJBA_8003152-18.2022
A24: 19 | B24: JUSTICA_8005263-04.2024.8.05.0103 | C24: Drenagem e pavimentação da Rua Aracuã (Nossa Senhora das Vitórias) | D24: Justiça | E24: MP | F24: drenagem+pavimentação | G24: demanda-tipo (rua-tipo) | H24: ='19_TJBA_8005263-04.2024'!J52 -> 307680.85 | I24: ='19_TJBA_8005263-04.2024'!K52 -> 659546.56 | J24: ='19_TJBA_8005263-04.2024'!L52 -> 1748983.5 | K24: 19_TJBA_8005263-04.2024
A25: 20 | B25: JUSTICA_8005837-61.2023.8.05.0103 | C25: Abrigos de ônibus da Rodovia Jorge Amado (BR-415), perto do IFBA | D25: Justiça | E25: MP | F25: outro | G25: demanda-tipo (abrigo-tipo) | H25: ='20_TJBA_8005837-61.2023'!J28 -> 25781.309 | I25: ='20_TJBA_8005837-61.2023'!K28 -> 41112.737 | J25: ='20_TJBA_8005837-61.2023'!L28 -> 64526.214 | K25: 20_TJBA_8005837-61.2023
A26: 21 | B26: TCM_03973e23-CRECHE_TEOTONIO_VILELA | C26: Creche Municipal Padrão de 6 salas da Rua Genésio Santos (Teotônio Vilela) | D26: TCM | E26: MP | F26: escola/creche | G26: documento (6 salas) + demanda-tipo | H26: =21_TCM_03973e23!J55 -> 385923.81 | I26: =21_TCM_03973e23!K55 -> 781244.32 | J26: =21_TCM_03973e23!L55 -> 1448377.8 | K26: 21_TCM_03973e23
A27: 22 | B27: SN_COMPLEXO_ESPORTIVO_CAMPO_DO_RODAO | C27: Requalificação e ampliação do Complexo Esportivo Campo do Rodão (Teotônio Vilela) | D27: outro | E27: MP | F27: quadra/esporte | G27: demanda-tipo (campo-tipo) | H27: =22_SN_CAMPO_DO_RODAO!J63 -> 278660.29 | I27: =22_SN_CAMPO_DO_RODAO!K63 -> 426327.92 | J27: =22_SN_CAMPO_DO_RODAO!L63 -> 651156.79 | K27: 22_SN_CAMPO_DO_RODAO
A28: 23 | B28: JUSTICA_0001568-38.2011.8.05.0103 | C28: Infraestrutura básica do Loteamento Santa Cruz (cumprimento de sentença) | D28: Justiça | E28: Justiça | F28: drenagem+pavimentação | G28: demanda-tipo (extensão de vias a confirmar) | H28: ='23_TJBA_0001568-38.2011'!J64 -> 1348883.2 | I28: ='23_TJBA_0001568-38.2011'!K64 -> 2846250.3 | J28: ='23_TJBA_0001568-38.2011'!L64 -> 7453266.7 | K28: 23_TJBA_0001568-38.2011
A29: 24 | B29: JUSTICA_8007670-17.2023.8.05.0103 | C29: Estabilização de encosta da Ladeira Júlio Bagana / Rua Rio Almada (Tapera) | D29: Justiça | E29: Justiça | F29: encosta/contenção | G29: demanda-tipo (área da encosta a confirmar) | H29: ='24_TJBA_8007670-17.2023'!J33 -> 584464.71 | I29: ='24_TJBA_8007670-17.2023'!K33 -> 1676406.2 | J29: ='24_TJBA_8007670-17.2023'!L33 -> 4943798.2 | K29: 24_TJBA_8007670-17.2023
A30: 25 | B30: JUSTICA_8008589-69.2024.8.05.0103 | C30: Unidade de Acolhimento Renascer: projeto de incêndio e reforma (Conquista) | D30: Justiça | E30: Justiça | F30: outro | G30: demanda-tipo (área a confirmar) | H30: ='25_TJBA_8008589-69.2024'!J55 -> 44832.489 | I30: ='25_TJBA_8008589-69.2024'!K55 -> 140931.38 | J30: ='25_TJBA_8008589-69.2024'!L55 -> 454217.26 | K30: 25_TJBA_8008589-69.2024
G31: TOTAL GERAL | H31: =SUM(H6:H30) -> 17889012 | I31: =SUM(I6:I30) -> 27738467 | J31: =SUM(J6:J30) -> 53729776
A33: TOTAIS MP, JUSTIÇA E GERAL (MP = pacote do MP de 12/10, inclui processos judiciais e TCM nele; Justiça = objetos novos do pacote da Justiça de 13/10)
A34: Chave | G34: Objetos | H34: Mínimo (R$) | I34: Provável (R$) | J34: Máximo (R$)
A35: MP | G35: =COUNTIF($E$6:$E$30,A35) -> 22 | H35: =SUMIF($E$6:$E$30,$A35,H$6:H$30) -> 15910832 | I35: =SUMIF($E$6:$E$30,$A35,I$6:I$30) -> 23074879 | J35: =SUMIF($E$6:$E$30,$A35,J$6:J$30) -> 40878494
A36: Justiça | G36: =COUNTIF($E$6:$E$30,A36) -> 3 | H36: =SUMIF($E$6:$E$30,$A36,H$6:H$30) -> 1978180.4 | I36: =SUMIF($E$6:$E$30,$A36,I$6:I$30) -> 4663587.9 | J36: =SUMIF($E$6:$E$30,$A36,J$6:J$30) -> 12851282
A37: GERAL (MP + Justiça, sem dupla contagem) | H37: =SUM(H35:H36) -> 17889012 | I37: =SUM(I35:I36) -> 27738467 | J37: =SUM(J35:J36) -> 53729776
A39: Objetos "orçamento paramétrico" da Justiça já calculados no MP (não somados de novo; valor da aba do MP)
B40: JUSTICA_0006323-71.2012.8.05.0103 | C40: Requalificação do Estádio Municipal Mário Pessoa (Cidade Nova) – TAC de 2012 | G40: no MP: JUSTICA_0006323-71.2012.8.05.0103 | H40: ='17_TJBA_0006323-71.2012'!J61 -> 280956.1 | I40: ='17_TJBA_0006323-71.2012'!K61 -> 579542.15 | J40: ='17_TJBA_0006323-71.2012'!L61 -> 1434218.3 | K40: 17_TJBA_0006323-71.2012
B41: JUSTICA_8005837-61.2023.8.05.0103 | C41: Abrigos de ônibus na Rodovia Jorge Amado (BR-415), perto do IFBA | G41: no MP: JUSTICA_8005837-61.2023.8.05.0103 | H41: ='20_TJBA_8005837-61.2023'!J28 -> 25781.309 | I41: ='20_TJBA_8005837-61.2023'!K28 -> 41112.737 | J41: ='20_TJBA_8005837-61.2023'!L28 -> 64526.214 | K41: 20_TJBA_8005837-61.2023
B42: TCM_03973e23 | C42: Creche Municipal Padrão de 6 salas da Rua Genésio Santos (Teotônio Vilela) | G42: no MP: TCM_03973e23-CRECHE_TEOTONIO_VILELA | H42: =21_TCM_03973e23!J55 -> 385923.81 | I42: =21_TCM_03973e23!K55 -> 781244.32 | J42: =21_TCM_03973e23!L55 -> 1448377.8 | K42: 21_TCM_03973e23
A44: Total por origem
A45: Chave | G45: Objetos | H45: Mínimo (R$) | I45: Provável (R$) | J45: Máximo (R$)
A46: MPBA | G46: =COUNTIF($D$6:$D$30,A46) -> 9 | H46: =SUMIF($D$6:$D$30,$A46,H$6:H$30) -> 4026213.5 | I46: =SUMIF($D$6:$D$30,$A46,I$6:I$30) -> 6402696.7 | J46: =SUMIF($D$6:$D$30,$A46,J$6:J$30) -> 12797820
A47: MPF | G47: =COUNTIF($D$6:$D$30,A47) -> 3 | H47: =SUMIF($D$6:$D$30,$A47,H$6:H$30) -> 10080131 | I47: =SUMIF($D$6:$D$30,$A47,I$6:I$30) -> 12970811 | J47: =SUMIF($D$6:$D$30,$A47,J$6:J$30) -> 19348041
A48: MPT | G48: =COUNTIF($D$6:$D$30,A48) -> 4 | H48: =SUMIF($D$6:$D$30,$A48,H$6:H$30) -> 210406.28 | I48: =SUMIF($D$6:$D$30,$A48,I$6:I$30) -> 664428.66 | J48: =SUMIF($D$6:$D$30,$A48,J$6:J$30) -> 2005080.6
A49: Justiça | G49: =COUNTIF($D$6:$D$30,A49) -> 7 | H49: =SUMIF($D$6:$D$30,$A49,H$6:H$30) -> 2907677.3 | I49: =SUMIF($D$6:$D$30,$A49,I$6:I$30) -> 6492958.8 | J49: =SUMIF($D$6:$D$30,$A49,J$6:J$30) -> 17479300
A50: TCM | G50: =COUNTIF($D$6:$D$30,A50) -> 1 | H50: =SUMIF($D$6:$D$30,$A50,H$6:H$30) -> 385923.81 | I50: =SUMIF($D$6:$D$30,$A50,I$6:I$30) -> 781244.32 | J50: =SUMIF($D$6:$D$30,$A50,J$6:J$30) -> 1448377.8
A51: outro | G51: =COUNTIF($D$6:$D$30,A51) -> 1 | H51: =SUMIF($D$6:$D$30,$A51,H$6:H$30) -> 278660.29 | I51: =SUMIF($D$6:$D$30,$A51,I$6:I$30) -> 426327.92 | J51: =SUMIF($D$6:$D$30,$A51,J$6:J$30) -> 651156.79
A52: Soma (confere com o total geral) | H52: =SUM(H46:H51) -> 17889012 | I52: =SUM(I46:I51) -> 27738467 | J52: =SUM(J46:J51) -> 53729776
A54: Total por categoria
A55: Chave | G55: Objetos | H55: Mínimo (R$) | I55: Provável (R$) | J55: Máximo (R$)
A56: outro | G56: =COUNTIF($F$6:$F$30,A56) -> 7 | H56: =SUMIF($F$6:$F$30,$A56,H$6:H$30) -> 267903.88 | I56: =SUMIF($F$6:$F$30,$A56,I$6:I$30) -> 799423.9 | J56: =SUMIF($F$6:$F$30,$A56,J$6:J$30) -> 2886251.1
A57: escola/creche | G57: =COUNTIF($F$6:$F$30,A57) -> 5 | H57: =SUMIF($F$6:$F$30,$A57,H$6:H$30) -> 2346606.9 | I57: =SUMIF($F$6:$F$30,$A57,I$6:I$30) -> 4843195.3 | J57: =SUMIF($F$6:$F$30,$A57,J$6:J$30) -> 9511568.6
A58: drenagem | G58: =COUNTIF($F$6:$F$30,A58) -> 5 | H58: =SUMIF($F$6:$F$30,$A58,H$6:H$30) -> 3046043.8 | I58: =SUMIF($F$6:$F$30,$A58,I$6:I$30) -> 4365994.2 | J58: =SUMIF($F$6:$F$30,$A58,J$6:J$30) -> 8349494
A59: quadra/esporte | G59: =COUNTIF($F$6:$F$30,A59) -> 3 | H59: =SUMIF($F$6:$F$30,$A59,H$6:H$30) -> 1197839.2 | I59: =SUMIF($F$6:$F$30,$A59,I$6:I$30) -> 1861491.7 | J59: =SUMIF($F$6:$F$30,$A59,J$6:J$30) -> 3252107.4
A60: encosta/contenção | G60: =COUNTIF($F$6:$F$30,A60) -> 2 | H60: =SUMIF($F$6:$F$30,$A60,H$6:H$30) -> 1912929.8 | I60: =SUMIF($F$6:$F$30,$A60,I$6:I$30) -> 3968904.5 | J60: =SUMIF($F$6:$F$30,$A60,J$6:J$30) -> 9775812.5
A61: habitação | G61: =COUNTIF($F$6:$F$30,A61) -> 1 | H61: =SUMIF($F$6:$F$30,$A61,H$6:H$30) -> 7461124.6 | I61: =SUMIF($F$6:$F$30,$A61,I$6:I$30) -> 8393660.7 | J61: =SUMIF($F$6:$F$30,$A61,J$6:J$30) -> 10752292
A62: drenagem+pavimentação | G62: =COUNTIF($F$6:$F$30,A62) -> 2 | H62: =SUMIF($F$6:$F$30,$A62,H$6:H$30) -> 1656564.1 | I62: =SUMIF($F$6:$F$30,$A62,I$6:I$30) -> 3505796.9 | J62: =SUMIF($F$6:$F$30,$A62,J$6:J$30) -> 9202250.2
A63: Soma (confere com o total geral) | H63: =SUM(H56:H62) -> 17889012 | I63: =SUM(I56:I62) -> 27738467 | J63: =SUM(J56:J62) -> 53729776
A65: Leitura: o valor "provável" é a referência para reserva orçamentária; mínimo e máximo dão a faixa de incerteza.
A66: Quantidades: metragem do documento quando existe; nos demais casos, demanda-tipo com premissas na aba de cada objeto (a confirmar em campo/projeto).
A67: BDI, contingência e fator regional: aba PARAMETROS (PROVISORIO - aguarda aprovacao).
A68: Origem "outro" = processo interno "Resposta Ministério Público" sem indicação do ramo do MP (somado em MP).
A69: Justiça: só os objetos "orçamento paramétrico" do pacote da Justiça que não estavam calculados no MP (triagem_provisoria_justica.json). A triagem do MP não foi alterada.
A70: Não usar como orçamento de licitação. Estimativa não vinculante, com SINAPI como base oficial de referência, nos termos da Lei n. 14.133/2021 e do Decreto Municipal n. 269/2025.

Sheet PARAMETROS
A1: Parâmetros da estimativa (BDI, contingência e fator regional)
A2: PROVISORIO - aguarda aprovacao
A3: Custo = Σ(Quantidade × Preço unitário) × (1 + BDI) × (1 + Contingência) × Fator regional. Células amarelas: valores a aprovar.
A5: Parâmetro | B5: Mínimo | C5: Provável | D5: Máximo | E5: Fonte / justificativa
A6: BDI - edificações, encostas, quadras e outros | B6: 0.2034 | C6: 0.2212 | D6: 0.25 | E6: Acórdão n. 2.622/2013-TCU-Plenário, "construção de edifícios": 1º quartil / médio / 3º quartil (sem CPRB; regime não desonerado).
A7: BDI - pavimentação e drenagem de vias | B7: 0.196 | C7: 0.2097 | D7: 0.2423 | E7: Acórdão n. 2.622/2013-TCU-Plenário, "construção de rodovias e ferrovias": 1º quartil / médio / 3º quartil (sem CPRB).
A8: Contingência (projeto, sondagem, topografia, licenciamento, fiscalização) | B8: 0.05 | C8: 0.1 | D8: 0.15 | E8: Parâmetro técnico declarado; teto de referência: precisão de ±30% para estudos preliminares (OT-IBR 004/2012, IBRAOP).
A9: Fator regional | B9: 1 | C9: 1 | D9: 1.1 | E9: SINAPI coleta preços na capital (Salvador). Máximo cobre frete até Ilhéus, acesso difícil e mobilização (parâmetro declarado).
A11: Preços unitários: SINAPI/CAIXA, ref. 08/2026, Bahia (localidade Salvador), regime não desonerado; encargos sociais horista 117,73% e mensalista 72,85%.
A12: Ver proposta_bdi_contingencia_fator.md para as fontes conferidas e as limitações da conferência.

Sheet 01_MPBA_001.9.102305.2021
A1: 01 - Proteção e estabilização do prédio da Sociedade União Protetora dos Artífices e Operários (Centro)
A2: PROVISORIO - aguarda aprovacao
A4: Grupo-objeto | B4: MPBA_001.9.102305.2021
A5: Levantamento | B5: MP
A6: Origem | B6: MPBA
A7: Categoria | B7: outro
A8: Local | B8: Praça José Marcelino, s/n, Centro
A9: Fonte das quantidades | B9: demanda-tipo (medidas do próprio documento)
A10: Preços | B10: SINAPI/CAIXA ref. 08/2026, BA, não desonerado (código de cada item na coluna B)
A11: BDI aplicado | B11: edificações (Acórdão 2.622/2013, construção de edifícios)
A12: Premissas | B12: Medidas citadas no documento: tapumes, escoramento da fachada com estroncas de eucalipto, rede de proteção e lona na cobertura.
B13: Fachada 150/250/400 m², cobertura 250/350/500 m², 30/40/60 estroncas (premissa; medir no local).
B14: Cenário máximo inclui início da estabilização/recuperação (reforma pesada de 500 m²). Restauro de prédio histórico não está incluído.
B15: Locação do andaime e da tela não têm preço no SINAPI-BA usado; só montagem e colocação.
A17: Macroetapa | B17: Código SINAPI | C17: Tipo | D17: Descrição | E17: Unid. | F17: Preço unit. (R$) | G17: Qtd. mínimo | H17: Qtd. provável | I17: Qtd. máximo | J17: Total mínimo (R$) | K17: Total provável (R$) | L17: Total máximo (R$) | M17: Memória de cálculo
A18: 1. Isolamento | B18: 98458 | C18: SINAPI composição | D18: TAPUME COM COMPENSADO DE MADEIRA. AF_03/2024 | E18: M2 | F18: 105.08 | G18: 50 | H18: 66 | I18: 90 | J18: =F18*G18 -> 5254 | K18: =F18*H18 -> 6935.28 | L18: =F18*I18 -> 9457.2 | M18: tapume de compensado no perímetro frontal
A19: 2. Escoramento da fachada | B19: 14439 | C19: SINAPI insumo | D19: PONTALETE ROLICO SEM TRATAMENTO, D = 8 A 11 CM, H = 6 M, EM EUCALIPTO OU EQUIVALENTE DA REGIAO - BRUTA (PARA ESCORAMENTO) | E19: M | F19: 5.57 | G19: 180 | H19: 240 | I19: 360 | J19: =F19*G19 -> 1002.6 | K19: =F19*H19 -> 1336.8 | L19: =F19*I19 -> 2005.2 | M19: estroncas de eucalipto 6 m
A20: 2. Escoramento da fachada | B20: 88262 | C20: SINAPI composição | D20: CARPINTEIRO DE FORMAS COM ENCARGOS COMPLEMENTARES | E20: H | F20: 35.15 | G20: 60 | H20: 80 | I20: 120 | J20: =F20*G20 -> 2109 | K20: =F20*H20 -> 2812 | L20: =F20*I20 -> 4218 | M20: carpinteiro, 2 h por estronca
A21: 2. Escoramento da fachada | B21: 88316 | C21: SINAPI composição | D21: SERVENTE COM ENCARGOS COMPLEMENTARES | E21: H | F21: 26.14 | G21: 60 | H21: 80 | I21: 120 | J21: =F21*G21 -> 1568.4 | K21: =F21*H21 -> 2091.2 | L21: =F21*I21 -> 3136.8 | M21: servente, 2 h por estronca
A22: 3. Proteção da fachada | B22: 97063 | C22: SINAPI composição | D22: MONTAGEM E DESMONTAGEM DE ANDAIME MODULAR FACHADEIRO, COM PISO METÁLICO, PARA EDIFÍCIOS COM MULTIPLOS PAVIMENTOS (EXCLUSIVE ANDAIME E LIMPEZA). AF_03/2024 | E22: M2 | F22: 27.41 | G22: 150 | H22: 250 | I22: 400 | J22: =F22*G22 -> 4111.5 | K22: =F22*H22 -> 6852.5 | L22: =F22*I22 -> 10964 | M22: montagem/desmontagem de andaime fachadeiro (exclusive locação)
A23: 3. Proteção da fachada | B23: 97062 | C23: SINAPI composição | D23: COLOCAÇÃO DE TELA EM ANDAIME FACHADEIRO. AF_03/2024 | E23: M2 | F23: 7.11 | G23: 150 | H23: 250 | I23: 400 | J23: =F23*G23 -> 1066.5 | K23: =F23*H23 -> 1777.5 | L23: =F23*I23 -> 2844 | M23: colocação de tela de proteção na fachada
A24: 4. Proteção da cobertura | B24: 42408 | C24: SINAPI insumo | D24: LONA PLASTICA EXTRA FORTE PRETA, E = 200 MICRA | E24: M2 | F24: 2.1 | G24: 275 | H24: 385 | I24: 550 | J24: =F24*G24 -> 577.5 | K24: =F24*H24 -> 808.5 | L24: =F24*I24 -> 1155 | M24: lona plástica 200 micra (+10% de transpasse)
A25: 4. Proteção da cobertura | B25: 88316 | C25: SINAPI composição | D25: SERVENTE COM ENCARGOS COMPLEMENTARES | E25: H | F25: 26.14 | G25: 16.67 | H25: 23.33 | I25: 33.33 | J25: =F25*G25 -> 435.7538 | K25: =F25*H25 -> 609.8462 | L25: =F25*I25 -> 871.2462 | M25: servente para colocar a lona
A26: Início da estabilização/recuperação - 1. Serviços preliminares | B26: 103689 | C26: SINAPI composição | D26: FORNECIMENTO E INSTALAÇÃO DE PLACA DE OBRA COM CHAPA GALVANIZADA E ESTRUTURA DE MADEIRA. AF_03/2022_PS | E26: M2 | F26: 454.97 | G26: 0 | H26: 0 | I26: 6 | J26: =F26*G26 -> 0 | K26: =F26*H26 -> 0 | L26: =F26*I26 -> 2729.82 | M26: placa de obra
A27: Início da estabilização/recuperação - 2. Demolições e retiradas | B27: 97647 | C27: SINAPI composição | D27: REMOÇÃO DE TELHAS DE FIBROCIMENTO METÁLICA E CERÂMICA, DE FORMA MANUAL, SEM REAPROVEITAMENTO. AF_09/2023 | E27: M2 | F27: 4.43 | G27: 0 | H27: 0 | I27: 625 | J27: =F27*G27 -> 0 | K27: =F27*H27 -> 0 | L27: =F27*I27 -> 2768.75 | M27: remoção de telhas
A28: Início da estabilização/recuperação - 2. Demolições e retiradas | B28: 97650 | C28: SINAPI composição | D28: REMOÇÃO DE TRAMA DE MADEIRA PARA COBERTURA, DE FORMA MANUAL, SEM REAPROVEITAMENTO. AF_09/2023 | E28: M2 | F28: 9.56 | G28: 0 | H28: 0 | I28: 312.5 | J28: =F28*G28 -> 0 | K28: =F28*H28 -> 0 | L28: =F28*I28 -> 2987.5 | M28: remoção de trama de madeira (metade da área refeita)
A29: Início da estabilização/recuperação - 2. Demolições e retiradas | B29: 97640 | C29: SINAPI composição | D29: REMOÇÃO DE FORROS DE DRYWALL, PVC E FIBROMINERAL, DE FORMA MANUAL, SEM REAPROVEITAMENTO. AF_09/2023 | E29: M2 | F29: 2.58 | G29: 0 | H29: 0 | I29: 500 | J29: =F29*G29 -> 0 | K29: =F29*H29 -> 0 | L29: =F29*I29 -> 1290 | M29: remoção de forro
... A57: Início da estabilização/recuperação - 9. Entulho | B57: 95875 | C57: SINAPI composição | D57: TRANSPORTE COM CAMINHÃO BASCULANTE DE 10 M³, EM VIA URBANA PAVIMENTADA, DMT ATÉ 30 KM (UNIDADE: M3XKM). AF_02/2026 | E57: M3XKM | F57: 2.83 | G57: 0 | H57: 0 | I57: 250 | J57: =F57*G57 -> 0 | K57: =F57*H57 -> 0 | L57: =F57*I57 -> 707.5 | M57: transporte de entulho, DMT 10 km
I58: Custo direto | J58: =SUM(J18:J57) -> 16125.254 | K58: =SUM(K18:K57) -> 23223.626 | L58: =SUM(L18:L57) -> 350729.18
I59: BDI | J59: =PARAMETROS!$B$6 -> 0.2034 | K59: =PARAMETROS!$C$6 -> 0.2212 | L59: =PARAMETROS!$D$6 -> 0.25
I60: Contingência | J60: =PARAMETROS!$B$8 -> 0.05 | K60: =PARAMETROS!$C$8 -> 0.1 | L60: =PARAMETROS!$D$8 -> 0.15
I61: Fator regional | J61: =PARAMETROS!$B$9 -> 1 | K61: =PARAMETROS!$C$9 -> 1 | L61: =PARAMETROS!$D$9 -> 1.1
I62: TOTAL ESTIMADO (R$) | J62: =J58*(1+J59)*(1+J60)*J61 -> 20375.387 | K62: =K58*(1+K59)*(1+K60)*K61 -> 31196.762 | L62: =L58*(1+L59)*(1+L60)*L61 -> 554590.52
A64: Estimativa preliminar paramétrica, não vinculante, para planejamento orçamentário. Não substitui o orçamento detalhado do projeto. PROVISORIO - aguarda aprovacao

Sheet 02_MPBA_001.9.190096.2025
A1: 02 - Conclusão de unidades escolares paralisadas (Recomendação MPBA 02/2025)
A2: PROVISORIO - aguarda aprovacao
A4: Grupo-objeto | B4: MPBA_001.9.190096.2025
A5: Levantamento | B5: MP
A6: Origem | B6: MPBA
A7: Categoria | B7: escola/creche
A8: Local | B8: Rede municipal de ensino de Ilhéus (cita a Escola Municipal Vovó Isaac, Rua do Cano)
A9: Fonte das quantidades | B9: demanda-tipo (unidades não listadas)
A10: Preços | B10: SINAPI/CAIXA ref. 08/2026, BA, não desonerado (código de cada item na coluna B)
A11: BDI aplicado | B11: edificações (Acórdão 2.622/2013, construção de edifícios)
A12: Premissas | B12: A Recomendação não lista as escolas; foi estimada só a conclusão da Escola Municipal Vovó Isaac (citada).
B13: Escola de 600/800/1.000 m² com remanescente de 30/50/70% (área equivalente 180/400/700 m²).
B14: Edificação térrea-tipo por m²: concreto 0,12 m³/m², aço 10 kg/m², fôrma 1,1 m²/m², alvenaria 1,5 m²/m², cobertura em telha cerâmica (1,25 m²/m²), forro de PVC, piso cerâmico, 1 porta a cada 15 m², janelas 0,15 m²/m², instalações simplificadas.
A16: Macroetapa | B16: Código SINAPI | C16: Tipo | D16: Descrição | E16: Unid. | F16: Preço unit. (R$) | G16: Qtd. mínimo | H16: Qtd. provável | I16: Qtd. máximo | J16: Total mínimo (R$) | K16: Total provável (R$) | L16: Total máximo (R$) | M16: Memória de cálculo
A17: 1. Serviços preliminares | B17: 99059 | C17: SINAPI composição | D17: LOCAÇÃO CONVENCIONAL DE OBRA, UTILIZANDO GABARITO DE TÁBUAS CORRIDAS PONTALETADAS A CADA 2,00M - 2 UTILIZAÇÕES. AF_03/2024 | E17: M | F17: 75.94 | G17: 45 | H17: 100 | I17: 175 | J17: =F17*G17 -> 3417.3 | K17: =F17*H17 -> 7594 | L17: =F17*I17 -> 13289.5 | M17: locação de obra, 0,25 m de gabarito por m²
A18: 2. Fundação e estrutura | B18: 93358 | C18: SINAPI composição | D18: ESCAVAÇÃO MANUAL DE VALA. AF_09/2024 | E18: M3 | F18: 103.4 | G18: 14.4 | H18: 32 | I18: 56 | J18: =F18*G18 -> 1488.96 | K18: =F18*H18 -> 3308.8 | L18: =F18*I18 -> 5790.4 | M18: escavação manual, 0,08 m³/m²
A19: 2. Fundação e estrutura | B19: 103672 | C19: SINAPI composição | D19: CONCRETAGEM DE PILARES, FCK = 25 MPA, COM USO DE BOMBA - LANÇAMENTO, ADENSAMENTO E ACABAMENTO. AF_02/2022_PS | E19: M3 | F19: 828.32 | G19: 21.6 | H19: 48 | I19: 84 | J19: =F19*G19 -> 17891.712 | K19: =F19*H19 -> 39759.36 | L19: =F19*I19 -> 69578.88 | M19: concreto estrutural fck 25 MPa, 0,12 m³/m²
A20: 2. Fundação e estrutura | B20: 92762 | C20: SINAPI composição | D20: ARMAÇÃO DE PILAR OU VIGA DE ESTRUTURA CONVENCIONAL DE CONCRETO ARMADO UTILIZANDO AÇO CA-50 DE 10,0 MM - MONTAGEM. AF_06/2022 | E20: KG | F20: 10.41 | G20: 1800 | H20: 4000 | I20: 7000 | J20: =F20*G20 -> 18738 | K20: =F20*H20 -> 41640 | L20: =F20*I20 -> 72870 | M20: armação CA-50, 10 kg/m²
A21: 2. Fundação e estrutura | B21: 92421 | C21: SINAPI composição | D21: MONTAGEM E DESMONTAGEM DE FÔRMA DE PILARES RETANGULARES E ESTRUTURAS SIMILARES, PÉ-DIREITO DUPLO, EM CHAPA DE MADEIRA COMPENSADA RESINADA, 4 UTILIZAÇÕES. AF_09/2020 | E21: M2 | F21: 122.64 | G21: 198 | H21: 440 | I21: 770 | J21: =F21*G21 -> 24282.72 | K21: =F21*H21 -> 53961.6 | L21: =F21*I21 -> 94432.8 | M21: fôrmas, 1,1 m²/m²
A22: 3. Vedação e revestimentos | B22: 103328 | C22: SINAPI composição | D22: ALVENARIA DE VEDAÇÃO DE BLOCOS CERÂMICOS FURADOS NA HORIZONTAL DE 9X19X19 CM (ESPESSURA 9 CM) E ARGAMASSA DE ASSENTAMENTO COM PREPARO EM BETONEIRA. AF_08/2026 | E22: M2 | F22: 119.54 | G22: 270 | H22: 600 | I22: 1050 | J22: =F22*G22 -> 32275.8 | K22: =F22*H22 -> 71724 | L22: =F22*I22 -> 125517 | M22: alvenaria de vedação, 1,5 m²/m²
A23: 3. Vedação e revestimentos | B23: 87879 | C23: SINAPI composição | D23: CHAPISCO APLICADO EM ALVENARIAS E ESTRUTURAS DE CONCRETO INTERNAS, COM COLHER DE PEDREIRO. ARGAMASSA TRAÇO 1:3 COM PREPARO EM BETONEIRA 400L. AF_10/2022 | E23: M2 | F23: 6.03 | G23: 540 | H23: 1200 | I23: 2100 | J23: =F23*G23 -> 3256.2 | K23: =F23*H23 -> 7236 | L23: =F23*I23 -> 12663 | M23: chapisco nas duas faces
A24: 3. Vedação e revestimentos | B24: 104958 | C24: SINAPI composição | D24: MASSA ÚNICA, EM ARGAMASSA TRAÇO 1:2:8 PREPARO MECÂNICO, APLICADA MANUALMENTE EM PAREDES INTERNAS DE AMBIENTES COM ÁREA MAIOR QUE 10M², E = 10MM, COM TALISCAS. AF_03/2024 | E24: M2 | F24: 31.79 | G24: 432 | H24: 960 | I24: 1680 | J24: =F24*G24 -> 13733.28 | K24: =F24*H24 -> 30518.4 | L24: =F24*I24 -> 53407.2 | M24: massa única interna
A25: 3. Vedação e revestimentos | B25: 104235 | C25: SINAPI composição | D25: EMBOÇO OU MASSA ÚNICA EM ARGAMASSA INDUSTRIALIZADA, PREPARO MECÂNICA E APLICAÇÃO COM EQUIPAMENTO DE MISTURA E PROJEÇÃO DE 1,5 M3/H DE ARGAMASSA EM PANOS DE FACHADA SEM PRESENÇA DE VÃOS, ESPESSURA DE 25 MM, ACESSO POR ANDAIME. AF_08/2022 | E25: M2 | F25: 83.28 | G25: 108 | H25: 240 | I25: 420 | J25: =F25*G25 -> 8994.24 | K25: =F25*H25 -> 19987.2 | L25: =F25*I25 -> 34977.6 | M25: emboço externo
A26: 3. Vedação e revestimentos | B26: 87265 | C26: SINAPI composição | D26: REVESTIMENTO CERÂMICO PARA PAREDES INTERNAS COM PLACAS TIPO ESMALTADA DE DIMENSÕES 20X20 CM APLICADAS NA ALTURA INTEIRA DAS PAREDES. AF_02/2023_PE | E26: M2 | F26: 59.3 | G26: 54 | H26: 120 | I26: 210 | J26: =F26*G26 -> 3202.2 | K26: =F26*H26 -> 7116 | L26: =F26*I26 -> 12453 | M26: revestimento cerâmico em áreas molhadas
A27: 4. Pisos | B27: 95241 | C27: SINAPI composição | D27: LASTRO DE CONCRETO MAGRO, APLICADO EM PISOS, LAJES SOBRE SOLO OU RADIERS, ESPESSURA DE 5 CM. AF_01/2024 | E27: M2 | F27: 48.41 | G27: 180 | H27: 400 | I27: 700 | J27: =F27*G27 -> 8713.8 | K27: =F27*H27 -> 19364 | L27: =F27*I27 -> 33887 | M27: lastro de concreto magro 5 cm
A28: 4. Pisos | B28: 98680 | C28: SINAPI composição | D28: PISO CIMENTADO, TRAÇO 1:5 (CIMENTO E AREIA), ACABAMENTO LISO, ESPESSURA 3,0 CM, PREPARO MECÂNICO DA ARGAMASSA. AF_02/2026 | E28: M2 | F28: 58.19 | G28: 180 | H28: 400 | I28: 700 | J28: =F28*G28 -> 10474.2 | K28: =F28*H28 -> 23276 | L28: =F28*I28 -> 40733 | M28: regularização/contrapiso cimentado 3 cm
... A50: 10. Prevenção contra incêndio | B50: 37556 | C50: SINAPI insumo | D50: PLACA DE SINALIZACAO DE SEGURANCA CONTRA INCENDIO, FOTOLUMINESCENTE, QUADRADA, *20 X 20* CM, EM PVC *2* MM ANTI-CHAMAS (SIMBOLOS, CORES E PICTOGRAMAS CONFORME NBR 16820) | E50: UN | F50: 20.47 | G50: 3.6 | H50: 8 | I50: 14 | J50: =F50*G50 -> 73.692 | K50: =F50*H50 -> 163.76 | L50: =F50*I50 -> 286.58 | M50: placa fotoluminescente de rota de fuga
I51: Custo direto | J51: =SUM(J17:J50) -> 261839.08 | K51: =SUM(K17:K50) -> 581577.22 | L51: =SUM(L17:L50) -> 1017753.5
I52: BDI | J52: =PARAMETROS!$B$6 -> 0.2034 | K52: =PARAMETROS!$C$6 -> 0.2212 | L52: =PARAMETROS!$D$6 -> 0.25
I53: Contingência | J53: =PARAMETROS!$B$8 -> 0.05 | K53: =PARAMETROS!$C$8 -> 0.1 | L53: =PARAMETROS!$D$8 -> 0.15
I54: Fator regional | J54: =PARAMETROS!$B$9 -> 1 | K54: =PARAMETROS!$C$9 -> 1 | L54: =PARAMETROS!$D$9 -> 1.1
I55: TOTAL ESTIMADO (R$) | J55: =J51*(1+J52)*(1+J53)*J54 -> 330852.01 | K55: =K51*(1+K52)*(1+K53)*K54 -> 781244.32 | L55: =L51*(1+L52)*(1+L53)*L54 -> 1609322.7
A57: Estimativa preliminar paramétrica, não vinculante, para planejamento orçamentário. Não substitui o orçamento detalhado do projeto. PROVISORIO - aguarda aprovacao

Sheet 03_MPBA_001.9.24192.2024
A1: 03 - Requalificação da drenagem pluvial da Av. Soares Lopes
A2: PROVISORIO - aguarda aprovacao
A4: Grupo-objeto | B4: MPBA_001.9.24192.2024
A5: Levantamento | B5: MP
A6: Origem | B6: MPBA
A7: Categoria | B7: drenagem
A8: Local | B8: Av. Soares Lopes
A9: Fonte das quantidades | B9: documento (extensão de 1.600 m)
A10: Preços | B10: SINAPI/CAIXA ref. 08/2026, BA, não desonerado (código de cada item na coluna B)
A11: BDI aplicado | B11: vias e drenagem (Acórdão 2.622/2013, rodovias e ferrovias)
A12: Premissas | B12: Extensão de 1.600 m citada no pedido de prorrogação da SEINFRA (minuta de 12/11/2024).
B13: Rede principal DN 800/1.000/1.200 mm (premissa até haver projeto).
B14: Microdrenagem em via existente: vala com largura DN + 0,6 m e profundidade DN + 1,0 m, PV a cada 40 m, 2 bocas de lobo a cada 40 m, recomposição de base (20 cm) e CBUQ (5 cm) na faixa da vala, bota-fora a 10 km.
A16: Macroetapa | B16: Código SINAPI | C16: Tipo | D16: Descrição | E16: Unid. | F16: Preço unit. (R$) | G16: Qtd. mínimo | H16: Qtd. provável | I16: Qtd. máximo | J16: Total mínimo (R$) | K16: Total provável (R$) | L16: Total máximo (R$) | M16: Memória de cálculo
A17: 1. Serviços preliminares | B17: 103689 | C17: SINAPI composição | D17: FORNECIMENTO E INSTALAÇÃO DE PLACA DE OBRA COM CHAPA GALVANIZADA E ESTRUTURA DE MADEIRA. AF_03/2022_PS | E17: M2 | F17: 454.97 | G17: 6 | H17: 6 | I17: 6 | J17: =F17*G17 -> 2729.82 | K17: =F17*H17 -> 2729.82 | L17: =F17*I17 -> 2729.82 | M17: placa de obra 3 m x 2 m
A18: 2. Drenagem | B18: 90082 | C18: SINAPI composição | D18: ESCAVAÇÃO MECANIZADA DE VALA COM PROF. ATÉ 1,5 M (MÉDIA MONTANTE E JUSANTE/UMA COMPOSIÇÃO POR TRECHO), ESCAVADEIRA (0,8 M3), LARG. DE 1,5 M A 2,5 M, EM SOLO DE 1A CATEGORIA, EM LOCAIS COM ALTO NÍVEL DE INTERFERÊNCIA. AF_09/2024 | E18: M3 | F18: 10.58 | G18: 4032 | H18: 0 | I18: 0 | J18: =F18*G18 -> 42658.56 | K18: =F18*H18 -> 0 | L18: =F18*I18 -> 0 | M18: vala 1.40 m x 1.80 m x L 1600 m
A19: 2. Drenagem | B19: 92214 | C19: SINAPI composição | D19: TUBO DE CONCRETO PARA REDES COLETORAS DE ÁGUAS PLUVIAIS, DIÂMETRO DE 800 MM, JUNTA RÍGIDA, INSTALADO EM LOCAL COM BAIXO NÍVEL DE INTERFERÊNCIAS - FORNECIMENTO E ASSENTAMENTO. AF_03/2024 | E19: M | F19: 567.96 | G19: 1600 | H19: 0 | I19: 0 | J19: =F19*G19 -> 908736 | K19: =F19*H19 -> 0 | L19: =F19*I19 -> 0 | M19: rede DN 800 mm ao longo de L
A20: 2. Drenagem | B20: 93369 | C20: SINAPI composição | D20: REATERRO MECANIZADO DE VALA COM ESCAVADEIRA HIDRÁULICA (CAPACIDADE DA CAÇAMBA: 0,8 M³/POTÊNCIA: 111 HP), LARGURA 1,5 A 2,5 M, PROFUNDIDADE 1,5 A 3,0 M, COM SOLO (SEM SUBSTITUIÇÃO) DE 1ª CATEGORIA, COM COMPACTADOR DE SOLOS DE PERCUSSÃO. AF_08/2023 | E20: M3 | F20: 20.26 | G20: 3014.12 | H20: 3599.47 | I20: 4212.28 | J20: =F20*G20 -> 61066.071 | K20: =F20*H20 -> 72925.262 | L20: =F20*I20 -> 85340.793 | M20: volume da vala - volume externo do tubo
A21: 2. Drenagem | B21: 102457 | C21: SINAPI composição | D21: BASE PARA POÇO DE VISITA CIRCULAR PARA DRENAGEM, EM CONCRETO PRÉ-MOLDADO, DIÂMETRO INTERNO = 1,20 M, PROFUNDIDADE = 1,60 M, EXCLUINDO TAMPÃO. AF_05/2021 | E21: UN | F21: 2008.56 | G21: 41 | H21: 0 | I21: 0 | J21: =F21*G21 -> 82350.96 | K21: =F21*H21 -> 0 | L21: =F21*I21 -> 0 | M21: PV a cada 40 m + 1
A22: 2. Drenagem | B22: 99240 | C22: SINAPI composição | D22: ACRÉSCIMO PARA POÇO DE VISITA CIRCULAR PARA DRENAGEM, EM CONCRETO PRÉ-MOLDADO, DIÂMETRO INTERNO = 1,2 M. AF_12/2020 | E22: M | F22: 844.48 | G22: 20.5 | H22: 0 | I22: 0 | J22: =F22*G22 -> 17311.84 | K22: =F22*H22 -> 0 | L22: =F22*I22 -> 0 | M22: acréscimo médio de 0,5 m de profundidade por PV
A23: 2. Drenagem | B23: 97956 | C23: SINAPI composição | D23: CAIXA PARA BOCA DE LOBO SIMPLES RETANGULAR, EM ALVENARIA COM BLOCOS DE CONCRETO, DIMENSÕES INTERNAS: 0,6X1X1,2 M. AF_12/2020 | E23: UN | F23: 1812.94 | G23: 80 | H23: 80 | I23: 80 | J23: =F23*G23 -> 145035.2 | K23: =F23*H23 -> 145035.2 | L23: =F23*I23 -> 145035.2 | M23: boca de lobo simples, 2 a cada 40 m
A24: 2. Drenagem | B24: 92210 | C24: SINAPI composição | D24: TUBO DE CONCRETO PARA REDES COLETORAS DE ÁGUAS PLUVIAIS, DIÂMETRO DE 400 MM, JUNTA RÍGIDA, INSTALADO EM LOCAL COM BAIXO NÍVEL DE INTERFERÊNCIAS - FORNECIMENTO E ASSENTAMENTO. AF_03/2024 | E24: M | F24: 188.74 | G24: 320 | H24: 320 | I24: 320 | J24: =F24*G24 -> 60396.8 | K24: =F24*H24 -> 60396.8 | L24: =F24*I24 -> 60396.8 | M24: ligação BL-PV em DN 400 mm, 4 m por boca de lobo
A25: 2. Drenagem | B25: 100982 | C25: SINAPI composição | D25: CARGA, MANOBRA E DESCARGA DE ENTULHO EM CAMINHÃO BASCULANTE 10 M³ - CARGA COM ESCAVADEIRA HIDRÁULICA (CAÇAMBA DE 0,80 M³ / 111 HP) E DESCARGA LIVRE (UNIDADE: M3). AF_02/2026 | E25: M3 | F25: 9.88 | G25: 1017.88 | H25: 1520.53 | I25: 2123.72 | J25: =F25*G25 -> 10056.654 | K25: =F25*H25 -> 15022.836 | L25: =F25*I25 -> 20982.354 | M25: carga do solo excedente (volume do tubo)
A26: 2. Drenagem | B26: 95875 | C26: SINAPI composição | D26: TRANSPORTE COM CAMINHÃO BASCULANTE DE 10 M³, EM VIA URBANA PAVIMENTADA, DMT ATÉ 30 KM (UNIDADE: M3XKM). AF_02/2026 | E26: M3XKM | F26: 2.83 | G26: 10178.76 | H26: 15205.31 | I26: 21237.17 | J26: =F26*G26 -> 28805.891 | K26: =F26*H26 -> 43031.027 | L26: =F26*I26 -> 60101.191 | M26: transporte do excedente, DMT 10 km
A27: 3. Recomposição do pavimento | B27: 101849 | C27: SINAPI composição | D27: RECOMPOSIÇÃO DE BASE E OU SUB-BASE PARA FECHAMENTO DE VALAS DE BRITA GRADUADA SIMPLES - INCLUSO RETIRADA E COLOCAÇÃO DO MATERIAL. AF_12/2020 | E27: M3 | F27: 232.27 | G27: 512 | H27: 0 | I27: 0 | J27: =F27*G27 -> 118922.24 | K27: =F27*H27 -> 0 | L27: =F27*I27 -> 0 | M27: base de brita graduada 20 cm na faixa da vala (1.60 m)
A28: 3. Recomposição do pavimento | B28: 102098 | C28: SINAPI composição | D28: RECOMPOSIÇÃO DE REVESTIMENTO EM CONCRETO ASFÁLTICO (AQUISIÇÃO EM USINA), PARA O FECHAMENTO DE VALAS - INCLUSO DEMOLIÇÃO DO PAVIMENTO. AF_12/2020 | E28: M3 | F28: 2136.03 | G28: 128 | H28: 144 | I28: 160 | J28: =F28*G28 -> 273411.84 | K28: =F28*H28 -> 307588.32 | L28: =F28*I28 -> 341764.8 | M28: revestimento em CBUQ 5 cm na faixa da vala (inclui demolição)
... A36: 3. Recomposição do pavimento | B36: 101849 | C36: SINAPI composição | D36: RECOMPOSIÇÃO DE BASE E OU SUB-BASE PARA FECHAMENTO DE VALAS DE BRITA GRADUADA SIMPLES - INCLUSO RETIRADA E COLOCAÇÃO DO MATERIAL. AF_12/2020 | E36: M3 | F36: 232.27 | G36: 0 | H36: 0 | I36: 640 | J36: =F36*G36 -> 0 | K36: =F36*H36 -> 0 | L36: =F36*I36 -> 148652.8 | M36: base de brita graduada 20 cm na faixa da vala (2.00 m)
I37: Custo direto | J37: =SUM(J17:J36) -> 1751481.9 | K37: =SUM(K17:K36) -> 2071387.3 | L37: =SUM(L17:L36) -> 2656595.6
I38: BDI | J38: =PARAMETROS!$B$7 -> 0.196 | K38: =PARAMETROS!$C$7 -> 0.2097 | L38: =PARAMETROS!$D$7 -> 0.2423
I39: Contingência | J39: =PARAMETROS!$B$8 -> 0.05 | K39: =PARAMETROS!$C$8 -> 0.1 | L39: =PARAMETROS!$D$8 -> 0.15
I40: Fator regional | J40: =PARAMETROS!$B$9 -> 1 | K40: =PARAMETROS!$C$9 -> 1 | L40: =PARAMETROS!$D$9 -> 1.1
I41: TOTAL ESTIMADO (R$) | J41: =J37*(1+J38)*(1+J39)*J40 -> 2199510.9 | K41: =K37*(1+K38)*(1+K39)*K40 -> 2756333 | L41: =L37*(1+L38)*(1+L39)*L40 -> 4174865.2
A43: Estimativa preliminar paramétrica, não vinculante, para planejamento orçamentário. Não substitui o orçamento detalhado do projeto. PROVISORIO - aguarda aprovacao

Sheet 04_MPBA_001.9.250850.2021
A1: 04 - Banheiro com chuveiro e grade na sede do Conselho Municipal de Educação
A2: PROVISORIO - aguarda aprovacao
A4: Grupo-objeto | B4: MPBA_001.9.250850.2021
A5: Levantamento | B5: MP
A6: Origem | B6: MPBA
A7: Categoria | B7: outro
A8: Local | B8: Sede do Conselho Municipal de Educação
A9: Fonte das quantidades | B9: demanda-tipo (banheiro-tipo)
A10: Preços | B10: SINAPI/CAIXA ref. 08/2026, BA, não desonerado (código de cada item na coluna B)
A11: BDI aplicado | B11: edificações (Acórdão 2.622/2013, construção de edifícios)
A12: Premissas | B12: Banheiro com chuveiro de cerca de 4 m² e grade de 1,0 x 2,1 m na porta de entrada, como pedido pela 6ª PJ.
B13: Quantidades de alvenaria e revestimento x 0,7 / 1,0 / 1,4; no máximo, inclui cobertura própria.
A15: Macroetapa | B15: Código SINAPI | C15: Tipo | D15: Descrição | E15: Unid. | F15: Preço unit. (R$) | G15: Qtd. mínimo | H15: Qtd. provável | I15: Qtd. máximo | J15: Total mínimo (R$) | K15: Total provável (R$) | L15: Total máximo (R$) | M15: Memória de cálculo
A16: 1. Banheiro com chuveiro | B16: 103328 | C16: SINAPI composição | D16: ALVENARIA DE VEDAÇÃO DE BLOCOS CERÂMICOS FURADOS NA HORIZONTAL DE 9X19X19 CM (ESPESSURA 9 CM) E ARGAMASSA DE ASSENTAMENTO COM PREPARO EM BETONEIRA. AF_08/2026 | E16: M2 | F16: 119.54 | G16: 7 | H16: 10 | I16: 14 | J16: =F16*G16 -> 836.78 | K16: =F16*H16 -> 1195.4 | L16: =F16*I16 -> 1673.56 | M16: alvenaria
A17: 1. Banheiro com chuveiro | B17: 87879 | C17: SINAPI composição | D17: CHAPISCO APLICADO EM ALVENARIAS E ESTRUTURAS DE CONCRETO INTERNAS, COM COLHER DE PEDREIRO. ARGAMASSA TRAÇO 1:3 COM PREPARO EM BETONEIRA 400L. AF_10/2022 | E17: M2 | F17: 6.03 | G17: 14 | H17: 20 | I17: 28 | J17: =F17*G17 -> 84.42 | K17: =F17*H17 -> 120.6 | L17: =F17*I17 -> 168.84 | M17: chapisco
A18: 1. Banheiro com chuveiro | B18: 104958 | C18: SINAPI composição | D18: MASSA ÚNICA, EM ARGAMASSA TRAÇO 1:2:8 PREPARO MECÂNICO, APLICADA MANUALMENTE EM PAREDES INTERNAS DE AMBIENTES COM ÁREA MAIOR QUE 10M², E = 10MM, COM TALISCAS. AF_03/2024 | E18: M2 | F18: 31.79 | G18: 14 | H18: 20 | I18: 28 | J18: =F18*G18 -> 445.06 | K18: =F18*H18 -> 635.8 | L18: =F18*I18 -> 890.12 | M18: massa única
A19: 1. Banheiro com chuveiro | B19: 87265 | C19: SINAPI composição | D19: REVESTIMENTO CERÂMICO PARA PAREDES INTERNAS COM PLACAS TIPO ESMALTADA DE DIMENSÕES 20X20 CM APLICADAS NA ALTURA INTEIRA DAS PAREDES. AF_02/2023_PE | E19: M2 | F19: 59.3 | G19: 12.6 | H19: 18 | I19: 25.2 | J19: =F19*G19 -> 747.18 | K19: =F19*H19 -> 1067.4 | L19: =F19*I19 -> 1494.36 | M19: revestimento cerâmico
A20: 1. Banheiro com chuveiro | B20: 95241 | C20: SINAPI composição | D20: LASTRO DE CONCRETO MAGRO, APLICADO EM PISOS, LAJES SOBRE SOLO OU RADIERS, ESPESSURA DE 5 CM. AF_01/2024 | E20: M2 | F20: 48.41 | G20: 2.8 | H20: 4 | I20: 5.6 | J20: =F20*G20 -> 135.548 | K20: =F20*H20 -> 193.64 | L20: =F20*I20 -> 271.096 | M20: lastro de piso
A21: 1. Banheiro com chuveiro | B21: 98680 | C21: SINAPI composição | D21: PISO CIMENTADO, TRAÇO 1:5 (CIMENTO E AREIA), ACABAMENTO LISO, ESPESSURA 3,0 CM, PREPARO MECÂNICO DA ARGAMASSA. AF_02/2026 | E21: M2 | F21: 58.19 | G21: 2.8 | H21: 4 | I21: 5.6 | J21: =F21*G21 -> 162.932 | K21: =F21*H21 -> 232.76 | L21: =F21*I21 -> 325.864 | M21: regularização
A22: 1. Banheiro com chuveiro | B22: 87248 | C22: SINAPI composição | D22: REVESTIMENTO CERÂMICO PARA PISO COM PLACAS TIPO ESMALTADA DE DIMENSÕES 35X35 CM APLICADA EM AMBIENTES DE ÁREA MAIOR QUE 10 M2. AF_02/2023_PE | E22: M2 | F22: 50.14 | G22: 2.8 | H22: 4 | I22: 5.6 | J22: =F22*G22 -> 140.392 | K22: =F22*H22 -> 200.56 | L22: =F22*I22 -> 280.784 | M22: piso cerâmico
A23: 1. Banheiro com chuveiro | B23: 86931 | C23: SINAPI composição | D23: BACIA SANITÁRIA COM CAIXA ACOPLADA LOUÇA BRANCA, INCLUSO ENGATE FLEXÍVEL EM PLÁSTICO BRANCO, 1/2" X 40 CM - FORNECIMENTO E INSTALAÇÃO. AF_02/2026 | E23: UN | F23: 630.3 | G23: 1 | H23: 1 | I23: 1 | J23: =F23*G23 -> 630.3 | K23: =F23*H23 -> 630.3 | L23: =F23*I23 -> 630.3 | M23: bacia sanitária
A24: 1. Banheiro com chuveiro | B24: 86902 | C24: SINAPI composição | D24: LAVATÓRIO LOUÇA BRANCA COM COLUNA, *44 X 35* CM, PADRÃO POPULAR - FORNECIMENTO E INSTALAÇÃO. AF_02/2026 | E24: UN | F24: 368.02 | G24: 1 | H24: 1 | I24: 1 | J24: =F24*G24 -> 368.02 | K24: =F24*H24 -> 368.02 | L24: =F24*I24 -> 368.02 | M24: lavatório
A25: 1. Banheiro com chuveiro | B25: 100860 | C25: SINAPI composição | D25: CHUVEIRO ELÉTRICO COMUM CORPO PLÁSTICO, TIPO DUCHA - FORNECIMENTO E INSTALAÇÃO. AF_02/2026 | E25: UN | F25: 168.16 | G25: 1 | H25: 1 | I25: 1 | J25: =F25*G25 -> 168.16 | K25: =F25*H25 -> 168.16 | L25: =F25*I25 -> 168.16 | M25: chuveiro elétrico
A26: 1. Banheiro com chuveiro | B26: 89714 | C26: SINAPI composição | D26: TUBO PVC, SERIE NORMAL, ESGOTO PREDIAL, DN 100 MM, FORNECIDO E INSTALADO EM RAMAL DE DESCARGA OU RAMAL DE ESGOTO SANITÁRIO. AF_08/2022 | E26: M | F26: 43.26 | G26: 4.2 | H26: 6 | I26: 8.4 | J26: =F26*G26 -> 181.692 | K26: =F26*H26 -> 259.56 | L26: =F26*I26 -> 363.384 | M26: esgoto DN 100
A27: 1. Banheiro com chuveiro | B27: 92023 | C27: SINAPI composição | D27: INTERRUPTOR SIMPLES (1 MÓDULO) COM 1 TOMADA DE EMBUTIR 2P+T 10 A, INCLUINDO SUPORTE E PLACA - FORNECIMENTO E INSTALAÇÃO. AF_03/2023 | E27: UN | F27: 53.69 | G27: 2 | H27: 2 | I27: 2 | J27: =F27*G27 -> 107.38 | K27: =F27*H27 -> 107.38 | L27: =F27*I27 -> 107.38 | M27: pontos elétricos
... A33: 1. Banheiro com chuveiro | B33: 94440 | C33: SINAPI composição | D33: TELHAMENTO COM TELHA CERÂMICA DE ENCAIXE, TIPO FRANCESA, COM ATÉ 2 ÁGUAS, INCLUSO TRANSPORTE VERTICAL. AF_06/2026 | E33: M2 | F33: 42.42 | G33: 0 | H33: 0 | I33: 7 | J33: =F33*G33 -> 0 | K33: =F33*H33 -> 0 | L33: =F33*I33 -> 296.94 | M33: telha cerâmica
I34: Custo direto | J34: =SUM(J16:J33) -> 6439.88 | K34: =SUM(K16:K33) -> 7642.851 | L34: =SUM(L16:L33) -> 10255.276
I35: BDI | J35: =PARAMETROS!$B$6 -> 0.2034 | K35: =PARAMETROS!$C$6 -> 0.2212 | L35: =PARAMETROS!$D$6 -> 0.25
I36: Contingência | J36: =PARAMETROS!$B$8 -> 0.05 | K36: =PARAMETROS!$C$8 -> 0.1 | L36: =PARAMETROS!$D$8 -> 0.15
I37: Fator regional | J37: =PARAMETROS!$B$9 -> 1 | K37: =PARAMETROS!$C$9 -> 1 | L37: =PARAMETROS!$D$9 -> 1.1
I38: TOTAL ESTIMADO (R$) | J38: =J34*(1+J35)*(1+J36)*J37 -> 8137.2392 | K38: =K34*(1+K35)*(1+K36)*K37 -> 10266.795 | L38: =L34*(1+L35)*(1+L36)*L37 -> 16216.156
A40: Estimativa preliminar paramétrica, não vinculante, para planejamento orçamentário. Não substitui o orçamento detalhado do projeto. PROVISORIO - aguarda aprovacao

Sheet 05_MPBA_001.9.379764.2023
A1: 05 - Valetão aberto pela EMBASA em via pública (local não identificado)
A2: PROVISORIO - aguarda aprovacao
A4: Grupo-objeto | B4: MPBA_001.9.379764.2023
A5: Levantamento | B5: MP
A6: Origem | B6: MPBA
A7: Categoria | B7: drenagem
A8: Local | B8: não informado
A9: Fonte das quantidades | B9: demanda-tipo (local não identificado)
A10: Preços | B10: SINAPI/CAIXA ref. 08/2026, BA, não desonerado (código de cada item na coluna B)
A11: BDI aplicado | B11: vias e drenagem (Acórdão 2.622/2013, rodovias e ferrovias)
A12: Premissas | B12: Local do valetão não identificado; trecho de 50/100/200 m de rede com recomposição.
B13: A vala foi aberta pela EMBASA: parte do custo pode caber à concessionária.
B14: Microdrenagem em via existente: vala com largura DN + 0,6 m e profundidade DN + 1,0 m, PV a cada 40 m, 2 bocas de lobo a cada 40 m, recomposição de base (20 cm) e CBUQ (5 cm) na faixa da vala, bota-fora a 10 km.
A16: Macroetapa | B16: Código SINAPI | C16: Tipo | D16: Descrição | E16: Unid. | F16: Preço unit. (R$) | G16: Qtd. mínimo | H16: Qtd. provável | I16: Qtd. máximo | J16: Total mínimo (R$) | K16: Total provável (R$) | L16: Total máximo (R$) | M16: Memória de cálculo
A17: 1. Serviços preliminares | B17: 103689 | C17: SINAPI composição | D17: FORNECIMENTO E INSTALAÇÃO DE PLACA DE OBRA COM CHAPA GALVANIZADA E ESTRUTURA DE MADEIRA. AF_03/2022_PS | E17: M2 | F17: 454.97 | G17: 6 | H17: 6 | I17: 6 | J17: =F17*G17 -> 2729.82 | K17: =F17*H17 -> 2729.82 | L17: =F17*I17 -> 2729.82 | M17: placa de obra 3 m x 2 m
A18: 2. Drenagem | B18: 90082 | C18: SINAPI composição | D18: ESCAVAÇÃO MECANIZADA DE VALA COM PROF. ATÉ 1,5 M (MÉDIA MONTANTE E JUSANTE/UMA COMPOSIÇÃO POR TRECHO), ESCAVADEIRA (0,8 M3), LARG. DE 1,5 M A 2,5 M, EM SOLO DE 1A CATEGORIA, EM LOCAIS COM ALTO NÍVEL DE INTERFERÊNCIA. AF_09/2024 | E18: M3 | F18: 10.58 | G18: 96 | H18: 0 | I18: 0 | J18: =F18*G18 -> 1015.68 | K18: =F18*H18 -> 0 | L18: =F18*I18 -> 0 | M18: vala 1.20 m x 1.60 m x L 50 m
A19: 2. Drenagem | B19: 92212 | C19: SINAPI composição | D19: TUBO DE CONCRETO PARA REDES COLETORAS DE ÁGUAS PLUVIAIS, DIÂMETRO DE 600 MM, JUNTA RÍGIDA, INSTALADO EM LOCAL COM BAIXO NÍVEL DE INTERFERÊNCIAS - FORNECIMENTO E ASSENTAMENTO. AF_03/2024 | E19: M | F19: 351.67 | G19: 50 | H19: 100 | I19: 0 | J19: =F19*G19 -> 17583.5 | K19: =F19*H19 -> 35167 | L19: =F19*I19 -> 0 | M19: rede DN 600 mm ao longo de L
A20: 2. Drenagem | B20: 93369 | C20: SINAPI composição | D20: REATERRO MECANIZADO DE VALA COM ESCAVADEIRA HIDRÁULICA (CAPACIDADE DA CAÇAMBA: 0,8 M³/POTÊNCIA: 111 HP), LARGURA 1,5 A 2,5 M, PROFUNDIDADE 1,5 A 3,0 M, COM SOLO (SEM SUBSTITUIÇÃO) DE 1ª CATEGORIA, COM COMPACTADOR DE SOLOS DE PERCUSSÃO. AF_08/2023 | E20: M3 | F20: 20.26 | G20: 76.76 | H20: 153.52 | I20: 376.77 | J20: =F20*G20 -> 1555.1576 | K20: =F20*H20 -> 3110.3152 | L20: =F20*I20 -> 7633.3602 | M20: volume da vala - volume externo do tubo
A21: 2. Drenagem | B21: 99285 | C21: SINAPI composição | D21: BASE PARA POÇO DE VISITA CIRCULAR PARA DRENAGEM, EM CONCRETO PRÉ-MOLDADO, DIÂMETRO INTERNO = 1,0 M, PROFUNDIDADE = 1,35 M, EXCLUINDO TAMPÃO. AF_05/2018 | E21: UN | F21: 1613.82 | G21: 3 | H21: 4 | I21: 0 | J21: =F21*G21 -> 4841.46 | K21: =F21*H21 -> 6455.28 | L21: =F21*I21 -> 0 | M21: PV a cada 40 m + 1
A22: 2. Drenagem | B22: 99288 | C22: SINAPI composição | D22: ACRÉSCIMO PARA POÇO DE VISITA CIRCULAR PARA DRENAGEM, EM CONCRETO PRÉ-MOLDADO, DIÂMETRO INTERNO = 1 M. AF_12/2020 | E22: M | F22: 634.89 | G22: 1.5 | H22: 2 | I22: 0 | J22: =F22*G22 -> 952.335 | K22: =F22*H22 -> 1269.78 | L22: =F22*I22 -> 0 | M22: acréscimo médio de 0,5 m de profundidade por PV
A23: 2. Drenagem | B23: 97956 | C23: SINAPI composição | D23: CAIXA PARA BOCA DE LOBO SIMPLES RETANGULAR, EM ALVENARIA COM BLOCOS DE CONCRETO, DIMENSÕES INTERNAS: 0,6X1X1,2 M. AF_12/2020 | E23: UN | F23: 1812.94 | G23: 4 | H23: 6 | I23: 10 | J23: =F23*G23 -> 7251.76 | K23: =F23*H23 -> 10877.64 | L23: =F23*I23 -> 18129.4 | M23: boca de lobo simples, 2 a cada 40 m
A24: 2. Drenagem | B24: 92210 | C24: SINAPI composição | D24: TUBO DE CONCRETO PARA REDES COLETORAS DE ÁGUAS PLUVIAIS, DIÂMETRO DE 400 MM, JUNTA RÍGIDA, INSTALADO EM LOCAL COM BAIXO NÍVEL DE INTERFERÊNCIAS - FORNECIMENTO E ASSENTAMENTO. AF_03/2024 | E24: M | F24: 188.74 | G24: 16 | H24: 24 | I24: 40 | J24: =F24*G24 -> 3019.84 | K24: =F24*H24 -> 4529.76 | L24: =F24*I24 -> 7549.6 | M24: ligação BL-PV em DN 400 mm, 4 m por boca de lobo
A25: 2. Drenagem | B25: 100982 | C25: SINAPI composição | D25: CARGA, MANOBRA E DESCARGA DE ENTULHO EM CAMINHÃO BASCULANTE 10 M³ - CARGA COM ESCAVADEIRA HIDRÁULICA (CAÇAMBA DE 0,80 M³ / 111 HP) E DESCARGA LIVRE (UNIDADE: M3). AF_02/2026 | E25: M3 | F25: 9.88 | G25: 19.24 | H25: 38.48 | I25: 127.23 | J25: =F25*G25 -> 190.0912 | K25: =F25*H25 -> 380.1824 | L25: =F25*I25 -> 1257.0324 | M25: carga do solo excedente (volume do tubo)
A26: 2. Drenagem | B26: 95875 | C26: SINAPI composição | D26: TRANSPORTE COM CAMINHÃO BASCULANTE DE 10 M³, EM VIA URBANA PAVIMENTADA, DMT ATÉ 30 KM (UNIDADE: M3XKM). AF_02/2026 | E26: M3XKM | F26: 2.83 | G26: 192.42 | H26: 384.85 | I26: 1272.35 | J26: =F26*G26 -> 544.5486 | K26: =F26*H26 -> 1089.1255 | L26: =F26*I26 -> 3600.7505 | M26: transporte do excedente, DMT 10 km
A27: 3. Recomposição do pavimento | B27: 101849 | C27: SINAPI composição | D27: RECOMPOSIÇÃO DE BASE E OU SUB-BASE PARA FECHAMENTO DE VALAS DE BRITA GRADUADA SIMPLES - INCLUSO RETIRADA E COLOCAÇÃO DO MATERIAL. AF_12/2020 | E27: M3 | F27: 232.27 | G27: 14 | H27: 28 | I27: 0 | J27: =F27*G27 -> 3251.78 | K27: =F27*H27 -> 6503.56 | L27: =F27*I27 -> 0 | M27: base de brita graduada 20 cm na faixa da vala (1.40 m)
A28: 3. Recomposição do pavimento | B28: 102098 | C28: SINAPI composição | D28: RECOMPOSIÇÃO DE REVESTIMENTO EM CONCRETO ASFÁLTICO (AQUISIÇÃO EM USINA), PARA O FECHAMENTO DE VALAS - INCLUSO DEMOLIÇÃO DO PAVIMENTO. AF_12/2020 | E28: M3 | F28: 2136.03 | G28: 3.5 | H28: 7 | I28: 16 | J28: =F28*G28 -> 7476.105 | K28: =F28*H28 -> 14952.21 | L28: =F28*I28 -> 34176.48 | M28: revestimento em CBUQ 5 cm na faixa da vala (inclui demolição)
... A34: 3. Recomposição do pavimento | B34: 101849 | C34: SINAPI composição | D34: RECOMPOSIÇÃO DE BASE E OU SUB-BASE PARA FECHAMENTO DE VALAS DE BRITA GRADUADA SIMPLES - INCLUSO RETIRADA E COLOCAÇÃO DO MATERIAL. AF_12/2020 | E34: M3 | F34: 232.27 | G34: 0 | H34: 0 | I34: 64 | J34: =F34*G34 -> 0 | K34: =F34*H34 -> 0 | L34: =F34*I34 -> 14865.28 | M34: base de brita graduada 20 cm na faixa da vala (1.60 m)
I35: Custo direto | J35: =SUM(J17:J34) -> 50412.077 | K35: =SUM(K17:K34) -> 89096.033 | L35: =SUM(L17:L34) -> 223450.84
I36: BDI | J36: =PARAMETROS!$B$7 -> 0.196 | K36: =PARAMETROS!$C$7 -> 0.2097 | L36: =PARAMETROS!$D$7 -> 0.2423
I37: Contingência | J37: =PARAMETROS!$B$8 -> 0.05 | K37: =PARAMETROS!$C$8 -> 0.1 | L37: =PARAMETROS!$D$8 -> 0.15
I38: Fator regional | J38: =PARAMETROS!$B$9 -> 1 | K38: =PARAMETROS!$C$9 -> 1 | L38: =PARAMETROS!$D$9 -> 1.1
I39: TOTAL ESTIMADO (R$) | J39: =J35*(1+J36)*(1+J37)*J38 -> 63307.487 | K39: =K35*(1+K36)*(1+K37)*K38 -> 118557.42 | L39: =L35*(1+L36)*(1+L37)*L38 -> 351155.12
A41: Estimativa preliminar paramétrica, não vinculante, para planejamento orçamentário. Não substitui o orçamento detalhado do projeto. PROVISORIO - aguarda aprovacao

Sheet 06_MPBA_001.9.52800.2024
A1: 06 - Quadra poliesportiva do distrito de Banco do Pedro
A2: PROVISORIO - aguarda aprovacao
A4: Grupo-objeto | B4: MPBA_001.9.52800.2024
A5: Levantamento | B5: MP
A6: Origem | B6: MPBA
A7: Categoria | B7: quadra/esporte
A8: Local | B8: Distrito de Banco do Pedro
A9: Fonte das quantidades | B9: documento (1 quadra) + demanda-tipo
A10: Preços | B10: SINAPI/CAIXA ref. 08/2026, BA, não desonerado (código de cada item na coluna B)
A11: BDI aplicado | B11: edificações (Acórdão 2.622/2013, construção de edifícios)
A12: Premissas | B12: Quadra poliesportiva coberta-tipo: piso 32 m x 20 m em concreto armado, cobertura metálica de 748 m², alambrado de 104 m.
B13: Estrutura de aço 18/25/32 kg/m²; vestiário de 0/40/60 m².
B14: Iluminação esportiva representada por refletores do SINAPI; o projeto luminotécnico pode elevar o custo.
A16: Macroetapa | B16: Código SINAPI | C16: Tipo | D16: Descrição | E16: Unid. | F16: Preço unit. (R$) | G16: Qtd. mínimo | H16: Qtd. provável | I16: Qtd. máximo | J16: Total mínimo (R$) | K16: Total provável (R$) | L16: Total máximo (R$) | M16: Memória de cálculo
A17: 1. Serviços preliminares | B17: 103689 | C17: SINAPI composição | D17: FORNECIMENTO E INSTALAÇÃO DE PLACA DE OBRA COM CHAPA GALVANIZADA E ESTRUTURA DE MADEIRA. AF_03/2022_PS | E17: M2 | F17: 454.97 | G17: 6 | H17: 6 | I17: 6 | J17: =F17*G17 -> 2729.82 | K17: =F17*H17 -> 2729.82 | L17: =F17*I17 -> 2729.82 | M17: placa de obra
A18: 1. Serviços preliminares | B18: 98525 | C18: SINAPI composição | D18: LIMPEZA MECANIZADA DE CAMADA VEGETAL, VEGETAÇÃO E PEQUENAS ÁRVORES (DIÂMETRO DE TRONCO MENOR QUE 0,20 M), COM TRATOR DE ESTEIRAS. AF_03/2024 | E18: M2 | F18: 0.76 | G18: 900 | H18: 900 | I18: 900 | J18: =F18*G18 -> 684 | K18: =F18*H18 -> 684 | L18: =F18*I18 -> 684 | M18: limpeza do terreno
A19: 2. Fundações e pilares | B19: 93358 | C19: SINAPI composição | D19: ESCAVAÇÃO MANUAL DE VALA. AF_09/2024 | E19: M3 | F19: 103.4 | G19: 30 | H19: 30 | I19: 30 | J19: =F19*G19 -> 3102 | K19: =F19*H19 -> 3102 | L19: =F19*I19 -> 3102 | M19: escavação de blocos
A20: 2. Fundações e pilares | B20: 103672 | C20: SINAPI composição | D20: CONCRETAGEM DE PILARES, FCK = 25 MPA, COM USO DE BOMBA - LANÇAMENTO, ADENSAMENTO E ACABAMENTO. AF_02/2022_PS | E20: M3 | F20: 828.32 | G20: 15 | H20: 15 | I20: 15 | J20: =F20*G20 -> 12424.8 | K20: =F20*H20 -> 12424.8 | L20: =F20*I20 -> 12424.8 | M20: concreto de blocos e pilares
A21: 2. Fundações e pilares | B21: 92762 | C21: SINAPI composição | D21: ARMAÇÃO DE PILAR OU VIGA DE ESTRUTURA CONVENCIONAL DE CONCRETO ARMADO UTILIZANDO AÇO CA-50 DE 10,0 MM - MONTAGEM. AF_06/2022 | E21: KG | F21: 10.41 | G21: 1500 | H21: 1500 | I21: 1500 | J21: =F21*G21 -> 15615 | K21: =F21*H21 -> 15615 | L21: =F21*I21 -> 15615 | M21: armação
A22: 2. Fundações e pilares | B22: 92421 | C22: SINAPI composição | D22: MONTAGEM E DESMONTAGEM DE FÔRMA DE PILARES RETANGULARES E ESTRUTURAS SIMILARES, PÉ-DIREITO DUPLO, EM CHAPA DE MADEIRA COMPENSADA RESINADA, 4 UTILIZAÇÕES. AF_09/2020 | E22: M2 | F22: 122.64 | G22: 120 | H22: 120 | I22: 120 | J22: =F22*G22 -> 14716.8 | K22: =F22*H22 -> 14716.8 | L22: =F22*I22 -> 14716.8 | M22: fôrmas
A23: 3. Piso esportivo | B23: 100576 | C23: SINAPI composição | D23: REGULARIZAÇÃO E COMPACTAÇÃO DE SUBLEITO DE SOLO PREDOMINANTEMENTE ARGILOSO, PARA OBRAS DE CONSTRUÇÃO DE PAVIMENTOS. AF_09/2024 | E23: M2 | F23: 3.35 | G23: 640 | H23: 640 | I23: 640 | J23: =F23*G23 -> 2144 | K23: =F23*H23 -> 2144 | L23: =F23*I23 -> 2144 | M23: regularização (área 32 m x 20 m)
A24: 3. Piso esportivo | B24: 96396 | C24: SINAPI composição | D24: CONSTRUÇÃO DE BASE E SUB-BASE PARA PAVIMENTAÇÃO DE BRITA GRADUADA SIMPLES, COM ESPESSURA DE 15 CM - EXCLUSIVE CARGA E TRANSPORTE. AF_09/2024 | E24: M3 | F24: 216.4 | G24: 64 | H24: 64 | I24: 64 | J24: =F24*G24 -> 13849.6 | K24: =F24*H24 -> 13849.6 | L24: =F24*I24 -> 13849.6 | M24: base de brita graduada 10 cm
A25: 3. Piso esportivo | B25: 94995 | C25: SINAPI composição | D25: EXECUÇÃO DE PASSEIO (CALÇADA) OU PISO DE CONCRETO COM CONCRETO MOLDADO IN LOCO, USINADO, ACABAMENTO CONVENCIONAL, ESPESSURA 8 CM, ARMADO. AF_08/2022 | E25: M2 | F25: 103.21 | G25: 640 | H25: 640 | I25: 640 | J25: =F25*G25 -> 66054.4 | K25: =F25*H25 -> 66054.4 | L25: =F25*I25 -> 66054.4 | M25: piso de concreto armado 8 cm
A26: 3. Piso esportivo | B26: 102504 | C26: SINAPI composição | D26: PINTURA DE DEMARCAÇÃO DE QUADRA POLIESPORTIVA COM TINTA ACRÍLICA, E = 5 CM, APLICAÇÃO MANUAL. AF_05/2021 | E26: M | F26: 12.45 | G26: 250 | H26: 250 | I26: 250 | J26: =F26*G26 -> 3112.5 | K26: =F26*H26 -> 3112.5 | L26: =F26*I26 -> 3112.5 | M26: demarcação das quadras
A27: 4. Cobertura | B27: 104314 | C27: SINAPI composição | D27: TRAMA DE AÇO COMPOSTA POR TERÇAS PARA TELHADOS DE ATÉ 2 ÁGUAS PARA TELHA ONDULADA DE FIBROCIMENTO, METÁLICA, PLÁSTICA OU TERMOACÚSTICA, INCLUSO TRANSPORTE VERTICAL (EM KG). EXCLUSIVE PINTURA. AF_10/2025_PS | E27: KG | F27: 13.77 | G27: 13464 | H27: 0 | I27: 0 | J27: =F27*G27 -> 185399.28 | K27: =F27*H27 -> 0 | L27: =F27*I27 -> 0 | M27: estrutura de aço da cobertura, 18 kg/m² em 748 m²
A28: 4. Cobertura | B28: 94216 | C28: SINAPI composição | D28: TELHAMENTO COM TELHA METÁLICA TERMOACÚSTICA E = 30 MM, COM ATÉ 2 ÁGUAS, INCLUSO IÇAMENTO. AF_06/2026 | E28: M2 | F28: 192.73 | G28: 748 | H28: 748 | I28: 748 | J28: =F28*G28 -> 144162.04 | K28: =F28*H28 -> 144162.04 | L28: =F28*I28 -> 144162.04 | M28: telha metálica termoacústica
... A67: 4. Cobertura | B67: 104314 | C67: SINAPI composição | D67: TRAMA DE AÇO COMPOSTA POR TERÇAS PARA TELHADOS DE ATÉ 2 ÁGUAS PARA TELHA ONDULADA DE FIBROCIMENTO, METÁLICA, PLÁSTICA OU TERMOACÚSTICA, INCLUSO TRANSPORTE VERTICAL (EM KG). EXCLUSIVE PINTURA. AF_10/2025_PS | E67: KG | F67: 13.77 | G67: 0 | H67: 0 | I67: 23936 | J67: =F67*G67 -> 0 | K67: =F67*H67 -> 0 | L67: =F67*I67 -> 329598.72 | M67: estrutura de aço da cobertura, 32 kg/m² em 748 m²
I68: Custo direto | J68: =SUM(J17:J67) -> 505094.91 | K68: =SUM(K17:K67) -> 636945.47 | L68: =SUM(L17:L67) -> 737854.44
I69: BDI | J69: =PARAMETROS!$B$6 -> 0.2034 | K69: =PARAMETROS!$C$6 -> 0.2212 | L69: =PARAMETROS!$D$6 -> 0.25
I70: Contingência | J70: =PARAMETROS!$B$8 -> 0.05 | K70: =PARAMETROS!$C$8 -> 0.1 | L70: =PARAMETROS!$D$8 -> 0.15
I71: Fator regional | J71: =PARAMETROS!$B$9 -> 1 | K71: =PARAMETROS!$C$9 -> 1 | L71: =PARAMETROS!$D$9 -> 1.1
I72: TOTAL ESTIMADO (R$) | J72: =J68*(1+J69)*(1+J70)*J71 -> 638222.78 | K72: =K68*(1+K69)*(1+K70)*K71 -> 855621.59 | L72: =L68*(1+L69)*(1+L70)*L71 -> 1166732.3
A74: Estimativa preliminar paramétrica, não vinculante, para planejamento orçamentário. Não substitui o orçamento detalhado do projeto. PROVISORIO - aguarda aprovacao

Sheet 07_MPBA_003.9.153337.2023
A1: 07 - Reforma do Instituto Municipal de Ensino Eusínio Lavigne – IME (Av. Canavieiras, Centro)
A2: PROVISORIO - aguarda aprovacao
A4: Grupo-objeto | B4: MPBA_003.9.153337.2023
A5: Levantamento | B5: MP
A6: Origem | B6: MPBA
A7: Categoria | B7: escola/creche
A8: Local | B8: Instituto Municipal de Ensino Eusínio Lavigne (IME), Av. Canavieiras, s/n, Centro
A9: Fonte das quantidades | B9: demanda-tipo (área a confirmar)
A10: Preços | B10: SINAPI/CAIXA ref. 08/2026, BA, não desonerado (código de cada item na coluna B)
A11: BDI aplicado | B11: edificações (Acórdão 2.622/2013, construção de edifícios)
A12: Premissas | B12: Prédio escolar de 1939 com dois pavimentos; área de 1.500/2.000/2.500 m² (premissa; confirmar).
B13: Inclui requalificação de cobertura pedida pela 6ª PJ. Exigências de preservação histórica podem elevar o custo.
B14: Reforma-tipo por m²: fração refeita de cobertura/forro/piso/reboco/esquadrias/instalações = 20/20/10/10/10/20% (mín), 50/50/30/30/30/50% (prov) e 100/100/60/60/60/100% (máx); pintura integral; extintores, emergência e sinalização de rota de fuga.
A16: Macroetapa | B16: Código SINAPI | C16: Tipo | D16: Descrição | E16: Unid. | F16: Preço unit. (R$) | G16: Qtd. mínimo | H16: Qtd. provável | I16: Qtd. máximo | J16: Total mínimo (R$) | K16: Total provável (R$) | L16: Total máximo (R$) | M16: Memória de cálculo
A17: 1. Serviços preliminares | B17: 103689 | C17: SINAPI composição | D17: FORNECIMENTO E INSTALAÇÃO DE PLACA DE OBRA COM CHAPA GALVANIZADA E ESTRUTURA DE MADEIRA. AF_03/2022_PS | E17: M2 | F17: 454.97 | G17: 6 | H17: 6 | I17: 6 | J17: =F17*G17 -> 2729.82 | K17: =F17*H17 -> 2729.82 | L17: =F17*I17 -> 2729.82 | M17: placa de obra
A18: 2. Demolições e retiradas | B18: 97647 | C18: SINAPI composição | D18: REMOÇÃO DE TELHAS DE FIBROCIMENTO METÁLICA E CERÂMICA, DE FORMA MANUAL, SEM REAPROVEITAMENTO. AF_09/2023 | E18: M2 | F18: 4.43 | G18: 375 | H18: 1250 | I18: 3125 | J18: =F18*G18 -> 1661.25 | K18: =F18*H18 -> 5537.5 | L18: =F18*I18 -> 13843.75 | M18: remoção de telhas
A19: 2. Demolições e retiradas | B19: 97650 | C19: SINAPI composição | D19: REMOÇÃO DE TRAMA DE MADEIRA PARA COBERTURA, DE FORMA MANUAL, SEM REAPROVEITAMENTO. AF_09/2023 | E19: M2 | F19: 9.56 | G19: 187.5 | H19: 625 | I19: 1562.5 | J19: =F19*G19 -> 1792.5 | K19: =F19*H19 -> 5975 | L19: =F19*I19 -> 14937.5 | M19: remoção de trama de madeira (metade da área refeita)
A20: 2. Demolições e retiradas | B20: 97640 | C20: SINAPI composição | D20: REMOÇÃO DE FORROS DE DRYWALL, PVC E FIBROMINERAL, DE FORMA MANUAL, SEM REAPROVEITAMENTO. AF_09/2023 | E20: M2 | F20: 2.58 | G20: 300 | H20: 1000 | I20: 2500 | J20: =F20*G20 -> 774 | K20: =F20*H20 -> 2580 | L20: =F20*I20 -> 6450 | M20: remoção de forro
A21: 2. Demolições e retiradas | B21: 97634 | C21: SINAPI composição | D21: DEMOLIÇÃO DE REVESTIMENTO CERÂMICO, DE FORMA MECANIZADA COM MARTELETE, SEM REAPROVEITAMENTO. AF_09/2023 | E21: M2 | F21: 10.04 | G21: 150 | H21: 600 | I21: 1500 | J21: =F21*G21 -> 1506 | K21: =F21*H21 -> 6024 | L21: =F21*I21 -> 15060 | M21: demolição de piso cerâmico
A22: 2. Demolições e retiradas | B22: 97633 | C22: SINAPI composição | D22: DEMOLIÇÃO DE REVESTIMENTO CERÂMICO, DE FORMA MANUAL, SEM REAPROVEITAMENTO. AF_09/2023 | E22: M2 | F22: 28.42 | G22: 45 | H22: 180 | I22: 450 | J22: =F22*G22 -> 1278.9 | K22: =F22*H22 -> 5115.6 | L22: =F22*I22 -> 12789 | M22: demolição de revestimento de parede
A23: 2. Demolições e retiradas | B23: 97645 | C23: SINAPI composição | D23: REMOÇÃO DE JANELAS, DE FORMA MANUAL, SEM REAPROVEITAMENTO. AF_09/2023 | E23: M2 | F23: 30.78 | G23: 22.5 | H23: 90 | I23: 225 | J23: =F23*G23 -> 692.55 | K23: =F23*H23 -> 2770.2 | L23: =F23*I23 -> 6925.5 | M23: remoção de janelas
A24: 3. Cobertura e forro | B24: 92539 | C24: SINAPI composição | D24: TRAMA DE MADEIRA COMPOSTA POR RIPAS, CAIBROS E TERÇAS PARA TELHADOS DE ATÉ 2 ÁGUAS PARA TELHA CERÂMICA OU DE CONCRETO, INCLUSO TRANSPORTE VERTICAL. AF_10/2025 | E24: M2 | F24: 101.54 | G24: 187.5 | H24: 625 | I24: 1562.5 | J24: =F24*G24 -> 19038.75 | K24: =F24*H24 -> 63462.5 | L24: =F24*I24 -> 158656.25 | M24: trama de madeira nova
A25: 3. Cobertura e forro | B25: 94440 | C25: SINAPI composição | D25: TELHAMENTO COM TELHA CERÂMICA DE ENCAIXE, TIPO FRANCESA, COM ATÉ 2 ÁGUAS, INCLUSO TRANSPORTE VERTICAL. AF_06/2026 | E25: M2 | F25: 42.42 | G25: 375 | H25: 1250 | I25: 3125 | J25: =F25*G25 -> 15907.5 | K25: =F25*H25 -> 53025 | L25: =F25*I25 -> 132562.5 | M25: telha cerâmica nova
A26: 3. Cobertura e forro | B26: 96116 | C26: SINAPI composição | D26: FORRO EM RÉGUAS DE PVC, FRISADO, PARA AMBIENTES COMERCIAIS, INCLUSIVE ESTRUTURA BIDIRECIONAL DE FIXAÇÃO. AF_08/2023_PS | E26: M2 | F26: 73.2 | G26: 300 | H26: 1000 | I26: 2500 | J26: =F26*G26 -> 21960 | K26: =F26*H26 -> 73200 | L26: =F26*I26 -> 183000 | M26: forro de PVC novo
A27: 4. Revestimentos e pisos | B27: 87879 | C27: SINAPI composição | D27: CHAPISCO APLICADO EM ALVENARIAS E ESTRUTURAS DE CONCRETO INTERNAS, COM COLHER DE PEDREIRO. ARGAMASSA TRAÇO 1:3 COM PREPARO EM BETONEIRA 400L. AF_10/2022 | E27: M2 | F27: 6.03 | G27: 360 | H27: 1440 | I27: 3600 | J27: =F27*G27 -> 2170.8 | K27: =F27*H27 -> 8683.2 | L27: =F27*I27 -> 21708 | M27: chapisco em paredes recuperadas
A28: 4. Revestimentos e pisos | B28: 104958 | C28: SINAPI composição | D28: MASSA ÚNICA, EM ARGAMASSA TRAÇO 1:2:8 PREPARO MECÂNICO, APLICADA MANUALMENTE EM PAREDES INTERNAS DE AMBIENTES COM ÁREA MAIOR QUE 10M², E = 10MM, COM TALISCAS. AF_03/2024 | E28: M2 | F28: 31.79 | G28: 360 | H28: 1440 | I28: 3600 | J28: =F28*G28 -> 11444.4 | K28: =F28*H28 -> 45777.6 | L28: =F28*I28 -> 114444 | M28: massa única em paredes recuperadas
... A48: 9. Entulho | B48: 95875 | C48: SINAPI composição | D48: TRANSPORTE COM CAMINHÃO BASCULANTE DE 10 M³, EM VIA URBANA PAVIMENTADA, DMT ATÉ 30 KM (UNIDADE: M3XKM). AF_02/2026 | E48: M3XKM | F48: 2.83 | G48: 750 | H48: 1000 | I48: 1250 | J48: =F48*G48 -> 2122.5 | K48: =F48*H48 -> 2830 | L48: =F48*I48 -> 3537.5 | M48: transporte de entulho, DMT 10 km
I49: Custo direto | J49: =SUM(J17:J48) -> 235571.33 | K49: =SUM(K17:K48) -> 675596.65 | L49: =SUM(L17:L48) -> 1569488.7
I50: BDI | J50: =PARAMETROS!$B$6 -> 0.2034 | K50: =PARAMETROS!$C$6 -> 0.2212 | L50: =PARAMETROS!$D$6 -> 0.25
I51: Contingência | J51: =PARAMETROS!$B$8 -> 0.05 | K51: =PARAMETROS!$C$8 -> 0.1 | L51: =PARAMETROS!$D$8 -> 0.15
I52: Fator regional | J52: =PARAMETROS!$B$9 -> 1 | K52: =PARAMETROS!$C$9 -> 1 | L52: =PARAMETROS!$D$9 -> 1.1
I53: TOTAL ESTIMADO (R$) | J53: =J49*(1+J50)*(1+J51)*J52 -> 297660.86 | K53: =K49*(1+K50)*(1+K51)*K52 -> 907542.49 | L53: =L49*(1+L50)*(1+L51)*L52 -> 2481754
A55: Estimativa preliminar paramétrica, não vinculante, para planejamento orçamentário. Não substitui o orçamento detalhado do projeto. PROVISORIO - aguarda aprovacao

Sheet 08_MPBA_003.9.198543.2025
A1: 08 - Drenagem da Rua Jardim Alice (Banco da Vitória)
A2: PROVISORIO - aguarda aprovacao
A4: Grupo-objeto | B4: MPBA_003.9.198543.2025
A5: Levantamento | B5: MP
A6: Origem | B6: MPBA
A7: Categoria | B7: drenagem
A8: Local | B8: Rua Jardim Alice, Banco da Vitória (conforme planilhas da SEINFRA)
A9: Fonte das quantidades | B9: demanda-tipo (escopo a confirmar)
A10: Preços | B10: SINAPI/CAIXA ref. 08/2026, BA, não desonerado (código de cada item na coluna B)
A11: BDI aplicado | B11: vias e drenagem (Acórdão 2.622/2013, rodovias e ferrovias)
A12: Premissas | B12: Rua Jardim Alice (Banco da Vitória), segundo as planilhas da SEINFRA; trecho de 150/250/400 m.
B13: A NF fala em saneamento; o escopo de drenagem precisa ser confirmado.
B14: Microdrenagem em via existente: vala com largura DN + 0,6 m e profundidade DN + 1,0 m, PV a cada 40 m, 2 bocas de lobo a cada 40 m, recomposição de base (20 cm) e CBUQ (5 cm) na faixa da vala, bota-fora a 10 km.
A16: Macroetapa | B16: Código SINAPI | C16: Tipo | D16: Descrição | E16: Unid. | F16: Preço unit. (R$) | G16: Qtd. mínimo | H16: Qtd. provável | I16: Qtd. máximo | J16: Total mínimo (R$) | K16: Total provável (R$) | L16: Total máximo (R$) | M16: Memória de cálculo
A17: 1. Serviços preliminares | B17: 103689 | C17: SINAPI composição | D17: FORNECIMENTO E INSTALAÇÃO DE PLACA DE OBRA COM CHAPA GALVANIZADA E ESTRUTURA DE MADEIRA. AF_03/2022_PS | E17: M2 | F17: 454.97 | G17: 6 | H17: 6 | I17: 6 | J17: =F17*G17 -> 2729.82 | K17: =F17*H17 -> 2729.82 | L17: =F17*I17 -> 2729.82 | M17: placa de obra 3 m x 2 m
A18: 2. Drenagem | B18: 90082 | C18: SINAPI composição | D18: ESCAVAÇÃO MECANIZADA DE VALA COM PROF. ATÉ 1,5 M (MÉDIA MONTANTE E JUSANTE/UMA COMPOSIÇÃO POR TRECHO), ESCAVADEIRA (0,8 M3), LARG. DE 1,5 M A 2,5 M, EM SOLO DE 1A CATEGORIA, EM LOCAIS COM ALTO NÍVEL DE INTERFERÊNCIA. AF_09/2024 | E18: M3 | F18: 10.58 | G18: 288 | H18: 0 | I18: 0 | J18: =F18*G18 -> 3047.04 | K18: =F18*H18 -> 0 | L18: =F18*I18 -> 0 | M18: vala 1.20 m x 1.60 m x L 150 m
A19: 2. Drenagem | B19: 92212 | C19: SINAPI composição | D19: TUBO DE CONCRETO PARA REDES COLETORAS DE ÁGUAS PLUVIAIS, DIÂMETRO DE 600 MM, JUNTA RÍGIDA, INSTALADO EM LOCAL COM BAIXO NÍVEL DE INTERFERÊNCIAS - FORNECIMENTO E ASSENTAMENTO. AF_03/2024 | E19: M | F19: 351.67 | G19: 150 | H19: 250 | I19: 0 | J19: =F19*G19 -> 52750.5 | K19: =F19*H19 -> 87917.5 | L19: =F19*I19 -> 0 | M19: rede DN 600 mm ao longo de L
A20: 2. Drenagem | B20: 93369 | C20: SINAPI composição | D20: REATERRO MECANIZADO DE VALA COM ESCAVADEIRA HIDRÁULICA (CAPACIDADE DA CAÇAMBA: 0,8 M³/POTÊNCIA: 111 HP), LARGURA 1,5 A 2,5 M, PROFUNDIDADE 1,5 A 3,0 M, COM SOLO (SEM SUBSTITUIÇÃO) DE 1ª CATEGORIA, COM COMPACTADOR DE SOLOS DE PERCUSSÃO. AF_08/2023 | E20: M3 | F20: 20.26 | G20: 230.27 | H20: 383.79 | I20: 753.53 | J20: =F20*G20 -> 4665.2702 | K20: =F20*H20 -> 7775.5854 | L20: =F20*I20 -> 15266.518 | M20: volume da vala - volume externo do tubo
A21: 2. Drenagem | B21: 99285 | C21: SINAPI composição | D21: BASE PARA POÇO DE VISITA CIRCULAR PARA DRENAGEM, EM CONCRETO PRÉ-MOLDADO, DIÂMETRO INTERNO = 1,0 M, PROFUNDIDADE = 1,35 M, EXCLUINDO TAMPÃO. AF_05/2018 | E21: UN | F21: 1613.82 | G21: 5 | H21: 8 | I21: 0 | J21: =F21*G21 -> 8069.1 | K21: =F21*H21 -> 12910.56 | L21: =F21*I21 -> 0 | M21: PV a cada 40 m + 1
A22: 2. Drenagem | B22: 99288 | C22: SINAPI composição | D22: ACRÉSCIMO PARA POÇO DE VISITA CIRCULAR PARA DRENAGEM, EM CONCRETO PRÉ-MOLDADO, DIÂMETRO INTERNO = 1 M. AF_12/2020 | E22: M | F22: 634.89 | G22: 2.5 | H22: 4 | I22: 0 | J22: =F22*G22 -> 1587.225 | K22: =F22*H22 -> 2539.56 | L22: =F22*I22 -> 0 | M22: acréscimo médio de 0,5 m de profundidade por PV
A23: 2. Drenagem | B23: 97956 | C23: SINAPI composição | D23: CAIXA PARA BOCA DE LOBO SIMPLES RETANGULAR, EM ALVENARIA COM BLOCOS DE CONCRETO, DIMENSÕES INTERNAS: 0,6X1X1,2 M. AF_12/2020 | E23: UN | F23: 1812.94 | G23: 8 | H23: 14 | I23: 20 | J23: =F23*G23 -> 14503.52 | K23: =F23*H23 -> 25381.16 | L23: =F23*I23 -> 36258.8 | M23: boca de lobo simples, 2 a cada 40 m
A24: 2. Drenagem | B24: 92210 | C24: SINAPI composição | D24: TUBO DE CONCRETO PARA REDES COLETORAS DE ÁGUAS PLUVIAIS, DIÂMETRO DE 400 MM, JUNTA RÍGIDA, INSTALADO EM LOCAL COM BAIXO NÍVEL DE INTERFERÊNCIAS - FORNECIMENTO E ASSENTAMENTO. AF_03/2024 | E24: M | F24: 188.74 | G24: 32 | H24: 56 | I24: 80 | J24: =F24*G24 -> 6039.68 | K24: =F24*H24 -> 10569.44 | L24: =F24*I24 -> 15099.2 | M24: ligação BL-PV em DN 400 mm, 4 m por boca de lobo
A25: 2. Drenagem | B25: 100982 | C25: SINAPI composição | D25: CARGA, MANOBRA E DESCARGA DE ENTULHO EM CAMINHÃO BASCULANTE 10 M³ - CARGA COM ESCAVADEIRA HIDRÁULICA (CAÇAMBA DE 0,80 M³ / 111 HP) E DESCARGA LIVRE (UNIDADE: M3). AF_02/2026 | E25: M3 | F25: 9.88 | G25: 57.73 | H25: 96.21 | I25: 254.47 | J25: =F25*G25 -> 570.3724 | K25: =F25*H25 -> 950.5548 | L25: =F25*I25 -> 2514.1636 | M25: carga do solo excedente (volume do tubo)
A26: 2. Drenagem | B26: 95875 | C26: SINAPI composição | D26: TRANSPORTE COM CAMINHÃO BASCULANTE DE 10 M³, EM VIA URBANA PAVIMENTADA, DMT ATÉ 30 KM (UNIDADE: M3XKM). AF_02/2026 | E26: M3XKM | F26: 2.83 | G26: 577.27 | H26: 962.11 | I26: 2544.69 | J26: =F26*G26 -> 1633.6741 | K26: =F26*H26 -> 2722.7713 | L26: =F26*I26 -> 7201.4727 | M26: transporte do excedente, DMT 10 km
A27: 3. Recomposição do pavimento | B27: 101849 | C27: SINAPI composição | D27: RECOMPOSIÇÃO DE BASE E OU SUB-BASE PARA FECHAMENTO DE VALAS DE BRITA GRADUADA SIMPLES - INCLUSO RETIRADA E COLOCAÇÃO DO MATERIAL. AF_12/2020 | E27: M3 | F27: 232.27 | G27: 42 | H27: 70 | I27: 0 | J27: =F27*G27 -> 9755.34 | K27: =F27*H27 -> 16258.9 | L27: =F27*I27 -> 0 | M27: base de brita graduada 20 cm na faixa da vala (1.40 m)
A28: 3. Recomposição do pavimento | B28: 102098 | C28: SINAPI composição | D28: RECOMPOSIÇÃO DE REVESTIMENTO EM CONCRETO ASFÁLTICO (AQUISIÇÃO EM USINA), PARA O FECHAMENTO DE VALAS - INCLUSO DEMOLIÇÃO DO PAVIMENTO. AF_12/2020 | E28: M3 | F28: 2136.03 | G28: 10.5 | H28: 17.5 | I28: 32 | J28: =F28*G28 -> 22428.315 | K28: =F28*H28 -> 37380.525 | L28: =F28*I28 -> 68352.96 | M28: revestimento em CBUQ 5 cm na faixa da vala (inclui demolição)
... A34: 3. Recomposição do pavimento | B34: 101849 | C34: SINAPI composição | D34: RECOMPOSIÇÃO DE BASE E OU SUB-BASE PARA FECHAMENTO DE VALAS DE BRITA GRADUADA SIMPLES - INCLUSO RETIRADA E COLOCAÇÃO DO MATERIAL. AF_12/2020 | E34: M3 | F34: 232.27 | G34: 0 | H34: 0 | I34: 128 | J34: =F34*G34 -> 0 | K34: =F34*H34 -> 0 | L34: =F34*I34 -> 29730.56 | M34: base de brita graduada 20 cm na faixa da vala (1.60 m)
I35: Custo direto | J35: =SUM(J17:J34) -> 127779.86 | K35: =SUM(K17:K34) -> 212214.78 | L35: =SUM(L17:L34) -> 441740.93
I36: BDI | J36: =PARAMETROS!$B$7 -> 0.196 | K36: =PARAMETROS!$C$7 -> 0.2097 | L36: =PARAMETROS!$D$7 -> 0.2423
I37: Contingência | J37: =PARAMETROS!$B$8 -> 0.05 | K37: =PARAMETROS!$C$8 -> 0.1 | L37: =PARAMETROS!$D$8 -> 0.15
I38: Fator regional | J38: =PARAMETROS!$B$9 -> 1 | K38: =PARAMETROS!$C$9 -> 1 | L38: =PARAMETROS!$D$9 -> 1.1
I39: TOTAL ESTIMADO (R$) | J39: =J35*(1+J36)*(1+J37)*J38 -> 160465.94 | K39: =K35*(1+K36)*(1+K37)*K38 -> 282387.84 | L39: =L35*(1+L36)*(1+L37)*L38 -> 694200.07
A41: Estimativa preliminar paramétrica, não vinculante, para planejamento orçamentário. Não substitui o orçamento detalhado do projeto. PROVISORIO - aguarda aprovacao

Sheet 09_MPBA_003.9.476383.2022
A1: 09 - Drenagem da Rua Praia Dourada
A2: PROVISORIO - aguarda aprovacao
A4: Grupo-objeto | B4: MPBA_003.9.476383.2022
A5: Levantamento | B5: MP
A6: Origem | B6: MPBA
A7: Categoria | B7: drenagem
A8: Local | B8: Rua Praia Dourada (bairro não informado)
A9: Fonte das quantidades | B9: demanda-tipo (rua-tipo)
A10: Preços | B10: SINAPI/CAIXA ref. 08/2026, BA, não desonerado (código de cada item na coluna B)
A11: BDI aplicado | B11: vias e drenagem (Acórdão 2.622/2013, rodovias e ferrovias)
A12: Premissas | B12: Rua Praia Dourada (nome só na lista de controle); comprimento de 150/250/400 m (premissa).
B13: O esgoto cabe à EMBASA e não está incluído.
B14: Rua-tipo: pista 5/6/7 m, passeios 1,2/1,5/2,0 m, base+sub-base 15/20/30 cm, CBUQ 4/5/5 cm, rede DN 600/600/800 mm, PV a cada 40 m, 2 bocas de lobo a cada 40 m, DMT da brita 20/20/40 km e do CBUQ 30/30/60 km (mín/prov/máx).
A16: Macroetapa | B16: Código SINAPI | C16: Tipo | D16: Descrição | E16: Unid. | F16: Preço unit. (R$) | G16: Qtd. mínimo | H16: Qtd. provável | I16: Qtd. máximo | J16: Total mínimo (R$) | K16: Total provável (R$) | L16: Total máximo (R$) | M16: Memória de cálculo
A17: 1. Serviços preliminares | B17: 103689 | C17: SINAPI composição | D17: FORNECIMENTO E INSTALAÇÃO DE PLACA DE OBRA COM CHAPA GALVANIZADA E ESTRUTURA DE MADEIRA. AF_03/2022_PS | E17: M2 | F17: 454.97 | G17: 6 | H17: 6 | I17: 6 | J17: =F17*G17 -> 2729.82 | K17: =F17*H17 -> 2729.82 | L17: =F17*I17 -> 2729.82 | M17: placa de obra 3 m x 2 m
A18: 1. Serviços preliminares | B18: 98525 | C18: SINAPI composição | D18: LIMPEZA MECANIZADA DE CAMADA VEGETAL, VEGETAÇÃO E PEQUENAS ÁRVORES (DIÂMETRO DE TRONCO MENOR QUE 0,20 M), COM TRATOR DE ESTEIRAS. AF_03/2024 | E18: M2 | F18: 0.76 | G18: 1110 | H18: 2250 | I18: 4400 | J18: =F18*G18 -> 843.6 | K18: =F18*H18 -> 1710 | L18: =F18*I18 -> 3344 | M18: limpeza da faixa: L x (pista + 2 passeios)
A19: 2. Drenagem | B19: 90082 | C19: SINAPI composição | D19: ESCAVAÇÃO MECANIZADA DE VALA COM PROF. ATÉ 1,5 M (MÉDIA MONTANTE E JUSANTE/UMA COMPOSIÇÃO POR TRECHO), ESCAVADEIRA (0,8 M3), LARG. DE 1,5 M A 2,5 M, EM SOLO DE 1A CATEGORIA, EM LOCAIS COM ALTO NÍVEL DE INTERFERÊNCIA. AF_09/2024 | E19: M3 | F19: 10.58 | G19: 288 | H19: 0 | I19: 0 | J19: =F19*G19 -> 3047.04 | K19: =F19*H19 -> 0 | L19: =F19*I19 -> 0 | M19: vala 1.20 m x 1.60 m x L 150 m
A20: 2. Drenagem | B20: 92212 | C20: SINAPI composição | D20: TUBO DE CONCRETO PARA REDES COLETORAS DE ÁGUAS PLUVIAIS, DIÂMETRO DE 600 MM, JUNTA RÍGIDA, INSTALADO EM LOCAL COM BAIXO NÍVEL DE INTERFERÊNCIAS - FORNECIMENTO E ASSENTAMENTO. AF_03/2024 | E20: M | F20: 351.67 | G20: 150 | H20: 250 | I20: 0 | J20: =F20*G20 -> 52750.5 | K20: =F20*H20 -> 87917.5 | L20: =F20*I20 -> 0 | M20: rede DN 600 mm ao longo de L
A21: 2. Drenagem | B21: 93369 | C21: SINAPI composição | D21: REATERRO MECANIZADO DE VALA COM ESCAVADEIRA HIDRÁULICA (CAPACIDADE DA CAÇAMBA: 0,8 M³/POTÊNCIA: 111 HP), LARGURA 1,5 A 2,5 M, PROFUNDIDADE 1,5 A 3,0 M, COM SOLO (SEM SUBSTITUIÇÃO) DE 1ª CATEGORIA, COM COMPACTADOR DE SOLOS DE PERCUSSÃO. AF_08/2023 | E21: M3 | F21: 20.26 | G21: 230.27 | H21: 383.79 | I21: 753.53 | J21: =F21*G21 -> 4665.2702 | K21: =F21*H21 -> 7775.5854 | L21: =F21*I21 -> 15266.518 | M21: volume da vala - volume externo do tubo
A22: 2. Drenagem | B22: 99285 | C22: SINAPI composição | D22: BASE PARA POÇO DE VISITA CIRCULAR PARA DRENAGEM, EM CONCRETO PRÉ-MOLDADO, DIÂMETRO INTERNO = 1,0 M, PROFUNDIDADE = 1,35 M, EXCLUINDO TAMPÃO. AF_05/2018 | E22: UN | F22: 1613.82 | G22: 5 | H22: 8 | I22: 0 | J22: =F22*G22 -> 8069.1 | K22: =F22*H22 -> 12910.56 | L22: =F22*I22 -> 0 | M22: PV a cada 40 m + 1
A23: 2. Drenagem | B23: 99288 | C23: SINAPI composição | D23: ACRÉSCIMO PARA POÇO DE VISITA CIRCULAR PARA DRENAGEM, EM CONCRETO PRÉ-MOLDADO, DIÂMETRO INTERNO = 1 M. AF_12/2020 | E23: M | F23: 634.89 | G23: 2.5 | H23: 4 | I23: 0 | J23: =F23*G23 -> 1587.225 | K23: =F23*H23 -> 2539.56 | L23: =F23*I23 -> 0 | M23: acréscimo médio de 0,5 m de profundidade por PV
A24: 2. Drenagem | B24: 97956 | C24: SINAPI composição | D24: CAIXA PARA BOCA DE LOBO SIMPLES RETANGULAR, EM ALVENARIA COM BLOCOS DE CONCRETO, DIMENSÕES INTERNAS: 0,6X1X1,2 M. AF_12/2020 | E24: UN | F24: 1812.94 | G24: 8 | H24: 14 | I24: 20 | J24: =F24*G24 -> 14503.52 | K24: =F24*H24 -> 25381.16 | L24: =F24*I24 -> 36258.8 | M24: boca de lobo simples, 2 a cada 40 m
A25: 2. Drenagem | B25: 92210 | C25: SINAPI composição | D25: TUBO DE CONCRETO PARA REDES COLETORAS DE ÁGUAS PLUVIAIS, DIÂMETRO DE 400 MM, JUNTA RÍGIDA, INSTALADO EM LOCAL COM BAIXO NÍVEL DE INTERFERÊNCIAS - FORNECIMENTO E ASSENTAMENTO. AF_03/2024 | E25: M | F25: 188.74 | G25: 32 | H25: 56 | I25: 80 | J25: =F25*G25 -> 6039.68 | K25: =F25*H25 -> 10569.44 | L25: =F25*I25 -> 15099.2 | M25: ligação BL-PV em DN 400 mm, 4 m por boca de lobo
A26: 2. Drenagem | B26: 100982 | C26: SINAPI composição | D26: CARGA, MANOBRA E DESCARGA DE ENTULHO EM CAMINHÃO BASCULANTE 10 M³ - CARGA COM ESCAVADEIRA HIDRÁULICA (CAÇAMBA DE 0,80 M³ / 111 HP) E DESCARGA LIVRE (UNIDADE: M3). AF_02/2026 | E26: M3 | F26: 9.88 | G26: 57.73 | H26: 96.21 | I26: 254.47 | J26: =F26*G26 -> 570.3724 | K26: =F26*H26 -> 950.5548 | L26: =F26*I26 -> 2514.1636 | M26: carga do solo excedente (volume do tubo)
A27: 2. Drenagem | B27: 95875 | C27: SINAPI composição | D27: TRANSPORTE COM CAMINHÃO BASCULANTE DE 10 M³, EM VIA URBANA PAVIMENTADA, DMT ATÉ 30 KM (UNIDADE: M3XKM). AF_02/2026 | E27: M3XKM | F27: 2.83 | G27: 577.27 | H27: 962.11 | I27: 2544.69 | J27: =F27*G27 -> 1633.6741 | K27: =F27*H27 -> 2722.7713 | L27: =F27*I27 -> 7201.4727 | M27: transporte do excedente, DMT 10 km
A28: 3. Pavimentação | B28: 100576 | C28: SINAPI composição | D28: REGULARIZAÇÃO E COMPACTAÇÃO DE SUBLEITO DE SOLO PREDOMINANTEMENTE ARGILOSO, PARA OBRAS DE CONSTRUÇÃO DE PAVIMENTOS. AF_09/2024 | E28: M2 | F28: 3.35 | G28: 750 | H28: 1500 | I28: 2800 | J28: =F28*G28 -> 2512.5 | K28: =F28*H28 -> 5025 | L28: =F28*I28 -> 9380 | M28: regularização do subleito: L x pista
... A47: 3. Pavimentação | B47: 95875 | C47: SINAPI composição | D47: TRANSPORTE COM CAMINHÃO BASCULANTE DE 10 M³, EM VIA URBANA PAVIMENTADA, DMT ATÉ 30 KM (UNIDADE: M3XKM). AF_02/2026 | E47: M3XKM | F47: 2.83 | G47: 0 | H47: 0 | I47: 8400 | J47: =F47*G47 -> 0 | K47: =F47*H47 -> 0 | L47: =F47*I47 -> 23772 | M47: transporte do CBUQ, DMT 60 km
I48: Custo direto | J48: =SUM(J17:J47) -> 245007.84 | K48: =SUM(K17:K47) -> 495649.98 | L48: =SUM(L17:L47) -> 1112932.2
I49: BDI | J49: =PARAMETROS!$B$7 -> 0.196 | K49: =PARAMETROS!$C$7 -> 0.2097 | L49: =PARAMETROS!$D$7 -> 0.2423
I50: Contingência | J50: =PARAMETROS!$B$8 -> 0.05 | K50: =PARAMETROS!$C$8 -> 0.1 | L50: =PARAMETROS!$D$8 -> 0.15
I51: Fator regional | J51: =PARAMETROS!$B$9 -> 1 | K51: =PARAMETROS!$C$9 -> 1 | L51: =PARAMETROS!$D$9 -> 1.1
I52: TOTAL ESTIMADO (R$) | J52: =J48*(1+J49)*(1+J50)*J51 -> 307680.85 | K52: =K48*(1+K49)*(1+K50)*K51 -> 659546.56 | L52: =L48*(1+L49)*(1+L50)*L51 -> 1748983.5
A54: Estimativa preliminar paramétrica, não vinculante, para planejamento orçamentário. Não substitui o orçamento detalhado do projeto. PROVISORIO - aguarda aprovacao

Sheet 10_MPF_.000105-2023
A1: 10 - Contenção de encosta da Rua Alto do Socorro (Conquista)
A2: PROVISORIO - aguarda aprovacao
A4: Grupo-objeto | B4: MPF_1.14.001.000105-2023
A5: Levantamento | B5: MP
A6: Origem | B6: MPF
A7: Categoria | B7: encosta/contenção
A8: Local | B8: Rua Alto do Socorro, bairro Conquista
A9: Fonte das quantidades | B9: documento (1.368,32 m², Meta 13 do Novo PAC)
A10: Preços | B10: SINAPI/CAIXA ref. 08/2026, BA, não desonerado (código de cada item na coluna B)
A11: BDI aplicado | B11: edificações (Acórdão 2.622/2013, construção de edifícios)
A12: Premissas | B12: Área de 1.368,32 m² da Meta 13 (Alto do Socorro, trecho 02), citada na resposta ao MPF no PA 1.14.001.000254/2022-91.
B13: Solução-tipo: solo grampeado com concreto projetado e drenagem. Grampos 2,0/1,5/1,25 m com 6/8/12 m; concreto 10/10/15 cm.
B14: Altura média da encosta de 8 m (premissa). A solução real depende de sondagem e projeto geotécnico.
B15: Referência no documento: Meta 13 orçada em R$ 2.682.472,20 no Novo PAC (fora da CP 006/2026).
A17: Macroetapa | B17: Código SINAPI | C17: Tipo | D17: Descrição | E17: Unid. | F17: Preço unit. (R$) | G17: Qtd. mínimo | H17: Qtd. provável | I17: Qtd. máximo | J17: Total mínimo (R$) | K17: Total provável (R$) | L17: Total máximo (R$) | M17: Memória de cálculo
A18: 1. Serviços preliminares | B18: 103689 | C18: SINAPI composição | D18: FORNECIMENTO E INSTALAÇÃO DE PLACA DE OBRA COM CHAPA GALVANIZADA E ESTRUTURA DE MADEIRA. AF_03/2022_PS | E18: M2 | F18: 454.97 | G18: 6 | H18: 6 | I18: 6 | J18: =F18*G18 -> 2729.82 | K18: =F18*H18 -> 2729.82 | L18: =F18*I18 -> 2729.82 | M18: placa de obra
A19: 1. Serviços preliminares | B19: 98525 | C19: SINAPI composição | D19: LIMPEZA MECANIZADA DE CAMADA VEGETAL, VEGETAÇÃO E PEQUENAS ÁRVORES (DIÂMETRO DE TRONCO MENOR QUE 0,20 M), COM TRATOR DE ESTEIRAS. AF_03/2024 | E19: M2 | F19: 0.76 | G19: 1778.82 | H19: 1778.82 | I19: 1778.82 | J19: =F19*G19 -> 1351.9032 | K19: =F19*H19 -> 1351.9032 | L19: =F19*I19 -> 1351.9032 | M19: limpeza e supressão vegetal: face + 30% de entorno
A20: 2. Contenção | B20: 93957 | C20: SINAPI composição | D20: EXECUÇÃO DE GRAMPO PARA SOLO GRAMPEADO COM COMPRIMENTO MENOR OU IGUAL A 6 M, DIÂMETRO DE 10 CM, PERFURAÇÃO COM EQUIPAMENTO MANUAL E ARMADURA COM DIÂMETRO DE 20 MM. AF_07/2024 | E20: M | F20: 351.86 | G20: 2052.48 | H20: 0 | I20: 0 | J20: =F20*G20 -> 722185.61 | K20: =F20*H20 -> 0 | L20: =F20*I20 -> 0 | M20: grampos em malha 2.0 m x 2.0 m, comprimento 6 m
A21: 2. Contenção | B21: 107269 | C21: SINAPI composição | D21: EXECUÇÃO DE CORTINA DE CONCRETO PROJETADO COM ESPESSURA DE 10 CM, FCK MAIOR OU IGUAL A 30 MPA. AF_07/2026 | E21: M2 | F21: 185.2 | G21: 1368.32 | H21: 1368.32 | I21: 0 | J21: =F21*G21 -> 253412.86 | K21: =F21*H21 -> 253412.86 | L21: =F21*I21 -> 0 | M21: cortina de concreto projetado 10 cm na face
A22: 3. Drenagem da encosta | B22: 106545 | C22: SINAPI composição | D22: ASSENTAMENTO DE TUBO DRENO DE PEAD CORRUGADO EM GEOCOMPOSTO, DN 100 MM - FORNECIMENTO E INSTALAÇÃO. AF_01/2026 | E22: M | F22: 10.8 | G22: 820.99 | H22: 820.99 | I22: 820.99 | J22: =F22*G22 -> 8866.692 | K22: =F22*H22 -> 8866.692 | L22: =F22*I22 -> 8866.692 | M22: drenos sub-horizontais/barbacãs, 0,6 m por m² de face
A23: 3. Drenagem da encosta | B23: 102991 | C23: SINAPI composição | D23: CANALETA MEIA CANA PRÉ-MOLDADA DE CONCRETO (D = 40 CM) - FORNECIMENTO E INSTALAÇÃO. AF_05/2025 | E23: M | F23: 74.22 | G23: 342.08 | H23: 342.08 | I23: 342.08 | J23: =F23*G23 -> 25389.178 | K23: =F23*H23 -> 25389.178 | L23: =F23*I23 -> 25389.178 | M23: canaletas de crista e de pé (A / altura média 8 m, 2 linhas)
A24: 3. Drenagem da encosta | B24: 103933 | C24: SINAPI composição | D24: DESCIDA D'ÁGUA RÁPIDA (DAR 03), EM CONCRETO USINADO, FCK = 20 MPA, LANÇADO COM BOMBA, INCLUINDO ARMAÇÃO, MATERIAIS E FÔRMAS (2 UTILIZAÇÕES). AF_08/2022 | E24: M3 | F24: 1827.4 | G24: 17.1 | H24: 17.1 | I24: 17.1 | J24: =F24*G24 -> 31248.54 | K24: =F24*H24 -> 31248.54 | L24: =F24*I24 -> 31248.54 | M24: descidas d'água em concreto (0,0125 m³ por m² de face)
A25: 4. Proteção superficial | B25: 98504 | C25: SINAPI composição | D25: PLANTIO DE GRAMA BATATAIS EM PLACAS. AF_07/2024 | E25: M2 | F25: 15.04 | G25: 410.5 | H25: 410.5 | I25: 410.5 | J25: =F25*G25 -> 6173.92 | K25: =F25*H25 -> 6173.92 | L25: =F25*I25 -> 6173.92 | M25: grama em placas em 30% da área (bermas/entorno)
A26: 2. Contenção | B26: 93959 | C26: SINAPI composição | D26: EXECUÇÃO DE GRAMPO PARA SOLO GRAMPEADO COM COMPRIMENTO MAIOR QUE 6 M E MENOR OU IGUAL A 10 M, DIÂMETRO DE 10 CM, PERFURAÇÃO COM EQUIPAMENTO MANUAL E ARMADURA COM DIÂMETRO DE 20 MM. AF_07/2024 | E26: M | F26: 283.12 | G26: 0 | H26: 4865.14 | I26: 0 | J26: =F26*G26 -> 0 | K26: =F26*H26 -> 1377418.4 | L26: =F26*I26 -> 0 | M26: grampos em malha 1.5 m x 1.5 m, comprimento 8 m
A27: 2. Contenção | B27: 93961 | C27: SINAPI composição | D27: EXECUÇÃO DE GRAMPO PARA SOLO GRAMPEADO COM COMPRIMENTO MAIOR QUE 10 M, DIÂMETRO DE 10 CM, PERFURAÇÃO COM EQUIPAMENTO MANUAL E ARMADURA COM DIÂMETRO DE 20 MM. AF_07/2024 | E27: M | F27: 254.2 | G27: 0 | H27: 0 | I27: 10508.7 | J27: =F27*G27 -> 0 | K27: =F27*H27 -> 0 | L27: =F27*I27 -> 2671311.5 | M27: grampos em malha 1.25 m x 1.25 m, comprimento 12 m
A28: 2. Contenção | B28: 107270 | C28: SINAPI composição | D28: EXECUÇÃO DE CORTINA DE CONCRETO PROJETADO COM ESPESSURA DE 15 CM, FCK MAIOR OU IGUAL A 30 MPA. AF_07/2026 | E28: M2 | F28: 225.64 | G28: 0 | H28: 0 | I28: 1368.32 | J28: =F28*G28 -> 0 | K28: =F28*H28 -> 0 | L28: =F28*I28 -> 308747.72 | M28: cortina de concreto projetado 15 cm na face
I29: Custo direto | J29: =SUM(J18:J28) -> 1051358.5 | K29: =SUM(K18:K28) -> 1706591.4 | L29: =SUM(L18:L28) -> 3055819.3
I30: BDI | J30: =PARAMETROS!$B$6 -> 0.2034 | K30: =PARAMETROS!$C$6 -> 0.2212 | L30: =PARAMETROS!$D$6 -> 0.25
I31: Contingência | J31: =PARAMETROS!$B$8 -> 0.05 | K31: =PARAMETROS!$C$8 -> 0.1 | L31: =PARAMETROS!$D$8 -> 0.15
I32: Fator regional | J32: =PARAMETROS!$B$9 -> 1 | K32: =PARAMETROS!$C$9 -> 1 | L32: =PARAMETROS!$D$9 -> 1.1
I33: TOTAL ESTIMADO (R$) | J33: =J29*(1+J30)*(1+J31)*J32 -> 1328465.1 | K33: =K29*(1+K30)*(1+K31)*K32 -> 2292498.3 | L33: =L29*(1+L30)*(1+L31)*L32 -> 4832014.3
A35: Estimativa preliminar paramétrica, não vinculante, para planejamento orçamentário. Não substitui o orçamento detalhado do projeto. PROVISORIO - aguarda aprovacao

Sheet 11_MPF_.000183-2023
A1: 11 - 96 casas e parques lineares pós-chuvas de 2021 (Salobrinho, Banco da Vitória e Vila Cachoeira)
A2: PROVISORIO - aguarda aprovacao
A4: Grupo-objeto | B4: MPF_1.14.001.000183-2023
A5: Levantamento | B5: MP
A6: Origem | B6: MPF
A7: Categoria | B7: habitação
A8: Local | B8: Salobrinho, Banco da Vitória (margem da Rodovia Jorge Amado/BR-415) e distrito de Vila Cachoeira
A9: Fonte das quantidades | B9: documento (96 casas e 5 parques lineares)
A10: Preços | B10: SINAPI/CAIXA ref. 08/2026, BA, não desonerado (código de cada item na coluna B)
A11: BDI aplicado | B11: edificações (Acórdão 2.622/2013, construção de edifícios)
A12: Premissas | B12: 96 casas e 5 parques lineares citados no Processo MIDR 59053.005916/2022-05.
B13: Casa térrea de 40/42/45 m²; parque de 1.500/2.000/3.000 m² com gramado e passeios.
B14: Não inclui infraestrutura do conjunto, terreno nem trabalho social.
B15: Referências no documento: projeto de R$ 17.156.213,45; contrapartida municipal de R$ 4.549.844,04.
B16: Edificação térrea-tipo por m²: concreto 0,12 m³/m², aço 10 kg/m², fôrma 1,1 m²/m², alvenaria 1,5 m²/m², cobertura em telha cerâmica (1,25 m²/m²), forro de PVC, piso cerâmico, 1 porta a cada 15 m², janelas 0,15 m²/m², instalações simplificadas.
A18: Macroetapa | B18: Código SINAPI | C18: Tipo | D18: Descrição | E18: Unid. | F18: Preço unit. (R$) | G18: Qtd. mínimo | H18: Qtd. provável | I18: Qtd. máximo | J18: Total mínimo (R$) | K18: Total provável (R$) | L18: Total máximo (R$) | M18: Memória de cálculo
A19: Casas - 1. Serviços preliminares | B19: 99059 | C19: SINAPI composição | D19: LOCAÇÃO CONVENCIONAL DE OBRA, UTILIZANDO GABARITO DE TÁBUAS CORRIDAS PONTALETADAS A CADA 2,00M - 2 UTILIZAÇÕES. AF_03/2024 | E19: M | F19: 75.94 | G19: 960 | H19: 1008 | I19: 1080 | J19: =F19*G19 -> 72902.4 | K19: =F19*H19 -> 76547.52 | L19: =F19*I19 -> 82015.2 | M19: locação de obra, 0,25 m de gabarito por m²
A20: Casas - 2. Fundação e estrutura | B20: 93358 | C20: SINAPI composição | D20: ESCAVAÇÃO MANUAL DE VALA. AF_09/2024 | E20: M3 | F20: 103.4 | G20: 307.2 | H20: 322.56 | I20: 345.6 | J20: =F20*G20 -> 31764.48 | K20: =F20*H20 -> 33352.704 | L20: =F20*I20 -> 35735.04 | M20: escavação manual, 0,08 m³/m²
A21: Casas - 2. Fundação e estrutura | B21: 103672 | C21: SINAPI composição | D21: CONCRETAGEM DE PILARES, FCK = 25 MPA, COM USO DE BOMBA - LANÇAMENTO, ADENSAMENTO E ACABAMENTO. AF_02/2022_PS | E21: M3 | F21: 828.32 | G21: 460.8 | H21: 483.84 | I21: 518.4 | J21: =F21*G21 -> 381689.86 | K21: =F21*H21 -> 400774.35 | L21: =F21*I21 -> 429401.09 | M21: concreto estrutural fck 25 MPa, 0,12 m³/m²
A22: Casas - 2. Fundação e estrutura | B22: 92762 | C22: SINAPI composição | D22: ARMAÇÃO DE PILAR OU VIGA DE ESTRUTURA CONVENCIONAL DE CONCRETO ARMADO UTILIZANDO AÇO CA-50 DE 10,0 MM - MONTAGEM. AF_06/2022 | E22: KG | F22: 10.41 | G22: 38400 | H22: 40320 | I22: 43200 | J22: =F22*G22 -> 399744 | K22: =F22*H22 -> 419731.2 | L22: =F22*I22 -> 449712 | M22: armação CA-50, 10 kg/m²
A23: Casas - 2. Fundação e estrutura | B23: 92421 | C23: SINAPI composição | D23: MONTAGEM E DESMONTAGEM DE FÔRMA DE PILARES RETANGULARES E ESTRUTURAS SIMILARES, PÉ-DIREITO DUPLO, EM CHAPA DE MADEIRA COMPENSADA RESINADA, 4 UTILIZAÇÕES. AF_09/2020 | E23: M2 | F23: 122.64 | G23: 4224 | H23: 4435.2 | I23: 4752 | J23: =F23*G23 -> 518031.36 | K23: =F23*H23 -> 543932.93 | L23: =F23*I23 -> 582785.28 | M23: fôrmas, 1,1 m²/m²
A24: Casas - 3. Vedação e revestimentos | B24: 103328 | C24: SINAPI composição | D24: ALVENARIA DE VEDAÇÃO DE BLOCOS CERÂMICOS FURADOS NA HORIZONTAL DE 9X19X19 CM (ESPESSURA 9 CM) E ARGAMASSA DE ASSENTAMENTO COM PREPARO EM BETONEIRA. AF_08/2026 | E24: M2 | F24: 119.54 | G24: 5760 | H24: 6048 | I24: 6480 | J24: =F24*G24 -> 688550.4 | K24: =F24*H24 -> 722977.92 | L24: =F24*I24 -> 774619.2 | M24: alvenaria de vedação, 1,5 m²/m²
A25: Casas - 3. Vedação e revestimentos | B25: 87879 | C25: SINAPI composição | D25: CHAPISCO APLICADO EM ALVENARIAS E ESTRUTURAS DE CONCRETO INTERNAS, COM COLHER DE PEDREIRO. ARGAMASSA TRAÇO 1:3 COM PREPARO EM BETONEIRA 400L. AF_10/2022 | E25: M2 | F25: 6.03 | G25: 11520 | H25: 12096 | I25: 12960 | J25: =F25*G25 -> 69465.6 | K25: =F25*H25 -> 72938.88 | L25: =F25*I25 -> 78148.8 | M25: chapisco nas duas faces
A26: Casas - 3. Vedação e revestimentos | B26: 104958 | C26: SINAPI composição | D26: MASSA ÚNICA, EM ARGAMASSA TRAÇO 1:2:8 PREPARO MECÂNICO, APLICADA MANUALMENTE EM PAREDES INTERNAS DE AMBIENTES COM ÁREA MAIOR QUE 10M², E = 10MM, COM TALISCAS. AF_03/2024 | E26: M2 | F26: 31.79 | G26: 9216 | H26: 9676.8 | I26: 10368 | J26: =F26*G26 -> 292976.64 | K26: =F26*H26 -> 307625.47 | L26: =F26*I26 -> 329598.72 | M26: massa única interna
A27: Casas - 3. Vedação e revestimentos | B27: 104235 | C27: SINAPI composição | D27: EMBOÇO OU MASSA ÚNICA EM ARGAMASSA INDUSTRIALIZADA, PREPARO MECÂNICA E APLICAÇÃO COM EQUIPAMENTO DE MISTURA E PROJEÇÃO DE 1,5 M3/H DE ARGAMASSA EM PANOS DE FACHADA SEM PRESENÇA DE VÃOS, ESPESSURA DE 25 MM, ACESSO POR ANDAIME. AF_08/2022 | E27: M2 | F27: 83.28 | G27: 2304 | H27: 2419.2 | I27: 2592 | J27: =F27*G27 -> 191877.12 | K27: =F27*H27 -> 201470.98 | L27: =F27*I27 -> 215861.76 | M27: emboço externo
A28: Casas - 3. Vedação e revestimentos | B28: 87265 | C28: SINAPI composição | D28: REVESTIMENTO CERÂMICO PARA PAREDES INTERNAS COM PLACAS TIPO ESMALTADA DE DIMENSÕES 20X20 CM APLICADAS NA ALTURA INTEIRA DAS PAREDES. AF_02/2023_PE | E28: M2 | F28: 59.3 | G28: 1152 | H28: 1209.6 | I28: 1296 | J28: =F28*G28 -> 68313.6 | K28: =F28*H28 -> 71729.28 | L28: =F28*I28 -> 76852.8 | M28: revestimento cerâmico em áreas molhadas
A29: Casas - 4. Pisos | B29: 95241 | C29: SINAPI composição | D29: LASTRO DE CONCRETO MAGRO, APLICADO EM PISOS, LAJES SOBRE SOLO OU RADIERS, ESPESSURA DE 5 CM. AF_01/2024 | E29: M2 | F29: 48.41 | G29: 3840 | H29: 4032 | I29: 4320 | J29: =F29*G29 -> 185894.4 | K29: =F29*H29 -> 195189.12 | L29: =F29*I29 -> 209131.2 | M29: lastro de concreto magro 5 cm
A30: Casas - 4. Pisos | B30: 98680 | C30: SINAPI composição | D30: PISO CIMENTADO, TRAÇO 1:5 (CIMENTO E AREIA), ACABAMENTO LISO, ESPESSURA 3,0 CM, PREPARO MECÂNICO DA ARGAMASSA. AF_02/2026 | E30: M2 | F30: 58.19 | G30: 3840 | H30: 4032 | I30: 4320 | J30: =F30*G30 -> 223449.6 | K30: =F30*H30 -> 234622.08 | L30: =F30*I30 -> 251380.8 | M30: regularização/contrapiso cimentado 3 cm
... A52: Parques lineares - 2. Passeios | B52: 94992 | C52: SINAPI composição | D52: EXECUÇÃO DE PASSEIO (CALÇADA) OU PISO DE CONCRETO COM CONCRETO MOLDADO IN LOCO, FEITO EM OBRA, ACABAMENTO CONVENCIONAL, ESPESSURA 6 CM, ARMADO. AF_08/2022 | E52: M2 | F52: 91.17 | G52: 1500 | H52: 2000 | I52: 3000 | J52: =F52*G52 -> 136755 | K52: =F52*H52 -> 182340 | L52: =F52*I52 -> 273510 | M52: passeios de concreto em 20% da área
I53: Custo direto | J53: =SUM(J19:J52) -> 5904797.2 | K53: =SUM(K19:K52) -> 6248444.7 | L53: =SUM(L19:L52) -> 6799868.4
I54: BDI | J54: =PARAMETROS!$B$6 -> 0.2034 | K54: =PARAMETROS!$C$6 -> 0.2212 | L54: =PARAMETROS!$D$6 -> 0.25
I55: Contingência | J55: =PARAMETROS!$B$8 -> 0.05 | K55: =PARAMETROS!$C$8 -> 0.1 | L55: =PARAMETROS!$D$8 -> 0.15
I56: Fator regional | J56: =PARAMETROS!$B$9 -> 1 | K56: =PARAMETROS!$C$9 -> 1 | L56: =PARAMETROS!$D$9 -> 1.1
I57: TOTAL ESTIMADO (R$) | J57: =J53*(1+J54)*(1+J55)*J56 -> 7461124.6 | K57: =K53*(1+K54)*(1+K55)*K56 -> 8393660.7 | L57: =L53*(1+L54)*(1+L55)*L56 -> 10752292
A59: Estimativa preliminar paramétrica, não vinculante, para planejamento orçamentário. Não substitui o orçamento detalhado do projeto. PROVISORIO - aguarda aprovacao

Sheet 12_SN_MPF_FNDE_2023
A1: 12 - Obras FNDE: Escola Vila Lídia, Quadra do Vilela e Creche Nossa Senhora da Vitória
A2: PROVISORIO - aguarda aprovacao
A4: Grupo-objeto | B4: SN_MPF-OBRAS_FNDE_2023
A5: Levantamento | B5: MP
A6: Origem | B6: MPF
A7: Categoria | B7: escola/creche
A8: Local | B8: Escola Vila Lídia; Quadra Themístocles Andrade (Vilela); Creche Nossa Senhora da Vitória
A9: Fonte das quantidades | B9: demanda-tipo (situação das obras não informada)
A10: Preços | B10: SINAPI/CAIXA ref. 08/2026, BA, não desonerado (código de cada item na coluna B)
A11: BDI aplicado | B11: edificações (Acórdão 2.622/2013, construção de edifícios)
A12: Premissas | B12: Três obras do FNDE citadas na resposta ao MPF: Escola Vila Lídia (remanescente), Quadra Themístocles Andrade e Creche N. Sra. da Vitória.
B13: Escola de 900 m², creche de 1.000 m² e quadra coberta-tipo, com remanescente de 30/50/70% (premissa).
B14: Edificação térrea-tipo por m²: concreto 0,12 m³/m², aço 10 kg/m², fôrma 1,1 m²/m², alvenaria 1,5 m²/m², cobertura em telha cerâmica (1,25 m²/m²), forro de PVC, piso cerâmico, 1 porta a cada 15 m², janelas 0,15 m²/m², instalações simplificadas.
A16: Macroetapa | B16: Código SINAPI | C16: Tipo | D16: Descrição | E16: Unid. | F16: Preço unit. (R$) | G16: Qtd. mínimo | H16: Qtd. provável | I16: Qtd. máximo | J16: Total mínimo (R$) | K16: Total provável (R$) | L16: Total máximo (R$) | M16: Memória de cálculo
A17: Escola Vila Lídia - 1. Serviços preliminares | B17: 99059 | C17: SINAPI composição | D17: LOCAÇÃO CONVENCIONAL DE OBRA, UTILIZANDO GABARITO DE TÁBUAS CORRIDAS PONTALETADAS A CADA 2,00M - 2 UTILIZAÇÕES. AF_03/2024 | E17: M | F17: 75.94 | G17: 67.5 | H17: 112.5 | I17: 157.5 | J17: =F17*G17 -> 5125.95 | K17: =F17*H17 -> 8543.25 | L17: =F17*I17 -> 11960.55 | M17: locação de obra, 0,25 m de gabarito por m²
A18: Escola Vila Lídia - 2. Fundação e estrutura | B18: 93358 | C18: SINAPI composição | D18: ESCAVAÇÃO MANUAL DE VALA. AF_09/2024 | E18: M3 | F18: 103.4 | G18: 21.6 | H18: 36 | I18: 50.4 | J18: =F18*G18 -> 2233.44 | K18: =F18*H18 -> 3722.4 | L18: =F18*I18 -> 5211.36 | M18: escavação manual, 0,08 m³/m²
A19: Escola Vila Lídia - 2. Fundação e estrutura | B19: 103672 | C19: SINAPI composição | D19: CONCRETAGEM DE PILARES, FCK = 25 MPA, COM USO DE BOMBA - LANÇAMENTO, ADENSAMENTO E ACABAMENTO. AF_02/2022_PS | E19: M3 | F19: 828.32 | G19: 32.4 | H19: 54 | I19: 75.6 | J19: =F19*G19 -> 26837.568 | K19: =F19*H19 -> 44729.28 | L19: =F19*I19 -> 62620.992 | M19: concreto estrutural fck 25 MPa, 0,12 m³/m²
A20: Escola Vila Lídia - 2. Fundação e estrutura | B20: 92762 | C20: SINAPI composição | D20: ARMAÇÃO DE PILAR OU VIGA DE ESTRUTURA CONVENCIONAL DE CONCRETO ARMADO UTILIZANDO AÇO CA-50 DE 10,0 MM - MONTAGEM. AF_06/2022 | E20: KG | F20: 10.41 | G20: 2700 | H20: 4500 | I20: 6300 | J20: =F20*G20 -> 28107 | K20: =F20*H20 -> 46845 | L20: =F20*I20 -> 65583 | M20: armação CA-50, 10 kg/m²
A21: Escola Vila Lídia - 2. Fundação e estrutura | B21: 92421 | C21: SINAPI composição | D21: MONTAGEM E DESMONTAGEM DE FÔRMA DE PILARES RETANGULARES E ESTRUTURAS SIMILARES, PÉ-DIREITO DUPLO, EM CHAPA DE MADEIRA COMPENSADA RESINADA, 4 UTILIZAÇÕES. AF_09/2020 | E21: M2 | F21: 122.64 | G21: 297 | H21: 495 | I21: 693 | J21: =F21*G21 -> 36424.08 | K21: =F21*H21 -> 60706.8 | L21: =F21*I21 -> 84989.52 | M21: fôrmas, 1,1 m²/m²
A22: Escola Vila Lídia - 3. Vedação e revestimentos | B22: 103328 | C22: SINAPI composição | D22: ALVENARIA DE VEDAÇÃO DE BLOCOS CERÂMICOS FURADOS NA HORIZONTAL DE 9X19X19 CM (ESPESSURA 9 CM) E ARGAMASSA DE ASSENTAMENTO COM PREPARO EM BETONEIRA. AF_08/2026 | E22: M2 | F22: 119.54 | G22: 405 | H22: 675 | I22: 945 | J22: =F22*G22 -> 48413.7 | K22: =F22*H22 -> 80689.5 | L22: =F22*I22 -> 112965.3 | M22: alvenaria de vedação, 1,5 m²/m²
A23: Escola Vila Lídia - 3. Vedação e revestimentos | B23: 87879 | C23: SINAPI composição | D23: CHAPISCO APLICADO EM ALVENARIAS E ESTRUTURAS DE CONCRETO INTERNAS, COM COLHER DE PEDREIRO. ARGAMASSA TRAÇO 1:3 COM PREPARO EM BETONEIRA 400L. AF_10/2022 | E23: M2 | F23: 6.03 | G23: 810 | H23: 1350 | I23: 1890 | J23: =F23*G23 -> 4884.3 | K23: =F23*H23 -> 8140.5 | L23: =F23*I23 -> 11396.7 | M23: chapisco nas duas faces
A24: Escola Vila Lídia - 3. Vedação e revestimentos | B24: 104958 | C24: SINAPI composição | D24: MASSA ÚNICA, EM ARGAMASSA TRAÇO 1:2:8 PREPARO MECÂNICO, APLICADA MANUALMENTE EM PAREDES INTERNAS DE AMBIENTES COM ÁREA MAIOR QUE 10M², E = 10MM, COM TALISCAS. AF_03/2024 | E24: M2 | F24: 31.79 | G24: 648 | H24: 1080 | I24: 1512 | J24: =F24*G24 -> 20599.92 | K24: =F24*H24 -> 34333.2 | L24: =F24*I24 -> 48066.48 | M24: massa única interna
A25: Escola Vila Lídia - 3. Vedação e revestimentos | B25: 104235 | C25: SINAPI composição | D25: EMBOÇO OU MASSA ÚNICA EM ARGAMASSA INDUSTRIALIZADA, PREPARO MECÂNICA E APLICAÇÃO COM EQUIPAMENTO DE MISTURA E PROJEÇÃO DE 1,5 M3/H DE ARGAMASSA EM PANOS DE FACHADA SEM PRESENÇA DE VÃOS, ESPESSURA DE 25 MM, ACESSO POR ANDAIME. AF_08/2022 | E25: M2 | F25: 83.28 | G25: 162 | H25: 270 | I25: 378 | J25: =F25*G25 -> 13491.36 | K25: =F25*H25 -> 22485.6 | L25: =F25*I25 -> 31479.84 | M25: emboço externo
A26: Escola Vila Lídia - 3. Vedação e revestimentos | B26: 87265 | C26: SINAPI composição | D26: REVESTIMENTO CERÂMICO PARA PAREDES INTERNAS COM PLACAS TIPO ESMALTADA DE DIMENSÕES 20X20 CM APLICADAS NA ALTURA INTEIRA DAS PAREDES. AF_02/2023_PE | E26: M2 | F26: 59.3 | G26: 81 | H26: 135 | I26: 189 | J26: =F26*G26 -> 4803.3 | K26: =F26*H26 -> 8005.5 | L26: =F26*I26 -> 11207.7 | M26: revestimento cerâmico em áreas molhadas
A27: Escola Vila Lídia - 4. Pisos | B27: 95241 | C27: SINAPI composição | D27: LASTRO DE CONCRETO MAGRO, APLICADO EM PISOS, LAJES SOBRE SOLO OU RADIERS, ESPESSURA DE 5 CM. AF_01/2024 | E27: M2 | F27: 48.41 | G27: 270 | H27: 450 | I27: 630 | J27: =F27*G27 -> 13070.7 | K27: =F27*H27 -> 21784.5 | L27: =F27*I27 -> 30498.3 | M27: lastro de concreto magro 5 cm
A28: Escola Vila Lídia - 4. Pisos | B28: 98680 | C28: SINAPI composição | D28: PISO CIMENTADO, TRAÇO 1:5 (CIMENTO E AREIA), ACABAMENTO LISO, ESPESSURA 3,0 CM, PREPARO MECÂNICO DA ARGAMASSA. AF_02/2026 | E28: M2 | F28: 58.19 | G28: 270 | H28: 450 | I28: 630 | J28: =F28*G28 -> 15711.3 | K28: =F28*H28 -> 26185.5 | L28: =F28*I28 -> 36659.7 | M28: regularização/contrapiso cimentado 3 cm
... A133: Quadra Themístocles Andrade - Vestiário - 10. Prevenção contra incêndio | B133: 37556 | C133: SINAPI insumo | D133: PLACA DE SINALIZACAO DE SEGURANCA CONTRA INCENDIO, FOTOLUMINESCENTE, QUADRADA, *20 X 20* CM, EM PVC *2* MM ANTI-CHAMAS (SIMBOLOS, CORES E PICTOGRAMAS CONFORME NBR 16820) | E133: UN | F133: 20.47 | G133: 1 | H133: 1 | I133: 1 | J133: =F133*G133 -> 20.47 | K133: =F133*H133 -> 20.47 | L133: =F133*I133 -> 20.47 | M133: placa fotoluminescente de rota de fuga
I134: Custo direto | J134: =SUM(J17:J133) -> 1021345.4 | K134: =SUM(K17:K133) -> 1700750.2 | L134: =SUM(L17:L133) -> 2380227.3
I135: BDI | J135: =PARAMETROS!$B$6 -> 0.2034 | K135: =PARAMETROS!$C$6 -> 0.2212 | L135: =PARAMETROS!$D$6 -> 0.25
I136: Contingência | J136: =PARAMETROS!$B$8 -> 0.05 | K136: =PARAMETROS!$C$8 -> 0.1 | L136: =PARAMETROS!$D$8 -> 0.15
I137: Fator regional | J137: =PARAMETROS!$B$9 -> 1 | K137: =PARAMETROS!$C$9 -> 1 | L137: =PARAMETROS!$D$9 -> 1.1
I138: TOTAL ESTIMADO (R$) | J138: =J134*(1+J135)*(1+J136)*J137 -> 1290541.4 | K138: =K134*(1+K135)*(1+K136)*K137 -> 2284651.8 | L138: =L134*(1+L135)*(1+L136)*L137 -> 3763734.4
A140: Estimativa preliminar paramétrica, não vinculante, para planejamento orçamentário. Não substitui o orçamento detalhado do projeto. PROVISORIO - aguarda aprovacao

Sheet 13_MPT_000120.2022
A1: 13 - Condições de trabalho e reforma do prédio do SAMU de Ilhéus
A2: PROVISORIO - aguarda aprovacao
A4: Grupo-objeto | B4: MPT_000120.2022.05.001.7
A5: Levantamento | B5: MP
A6: Origem | B6: MPT
A7: Categoria | B7: outro
A8: Local | B8: SAMU de Ilhéus (endereço não informado)
A9: Fonte das quantidades | B9: demanda-tipo (área a confirmar)
A10: Preços | B10: SINAPI/CAIXA ref. 08/2026, BA, não desonerado (código de cada item na coluna B)
A11: BDI aplicado | B11: edificações (Acórdão 2.622/2013, construção de edifícios)
A12: Premissas | B12: Base do SAMU de 200/300/400 m² (premissa; endereço e escopo não informados).
B13: Reforma-tipo por m²: fração refeita de cobertura/forro/piso/reboco/esquadrias/instalações = 20/20/10/10/10/20% (mín), 50/50/30/30/30/50% (prov) e 100/100/60/60/60/100% (máx); pintura integral; extintores, emergência e sinalização de rota de fuga.
A15: Macroetapa | B15: Código SINAPI | C15: Tipo | D15: Descrição | E15: Unid. | F15: Preço unit. (R$) | G15: Qtd. mínimo | H15: Qtd. provável | I15: Qtd. máximo | J15: Total mínimo (R$) | K15: Total provável (R$) | L15: Total máximo (R$) | M15: Memória de cálculo
A16: 1. Serviços preliminares | B16: 103689 | C16: SINAPI composição | D16: FORNECIMENTO E INSTALAÇÃO DE PLACA DE OBRA COM CHAPA GALVANIZADA E ESTRUTURA DE MADEIRA. AF_03/2022_PS | E16: M2 | F16: 454.97 | G16: 6 | H16: 6 | I16: 6 | J16: =F16*G16 -> 2729.82 | K16: =F16*H16 -> 2729.82 | L16: =F16*I16 -> 2729.82 | M16: placa de obra
A17: 2. Demolições e retiradas | B17: 97647 | C17: SINAPI composição | D17: REMOÇÃO DE TELHAS DE FIBROCIMENTO METÁLICA E CERÂMICA, DE FORMA MANUAL, SEM REAPROVEITAMENTO. AF_09/2023 | E17: M2 | F17: 4.43 | G17: 50 | H17: 187.5 | I17: 500 | J17: =F17*G17 -> 221.5 | K17: =F17*H17 -> 830.625 | L17: =F17*I17 -> 2215 | M17: remoção de telhas
A18: 2. Demolições e retiradas | B18: 97650 | C18: SINAPI composição | D18: REMOÇÃO DE TRAMA DE MADEIRA PARA COBERTURA, DE FORMA MANUAL, SEM REAPROVEITAMENTO. AF_09/2023 | E18: M2 | F18: 9.56 | G18: 25 | H18: 93.75 | I18: 250 | J18: =F18*G18 -> 239 | K18: =F18*H18 -> 896.25 | L18: =F18*I18 -> 2390 | M18: remoção de trama de madeira (metade da área refeita)
A19: 2. Demolições e retiradas | B19: 97640 | C19: SINAPI composição | D19: REMOÇÃO DE FORROS DE DRYWALL, PVC E FIBROMINERAL, DE FORMA MANUAL, SEM REAPROVEITAMENTO. AF_09/2023 | E19: M2 | F19: 2.58 | G19: 40 | H19: 150 | I19: 400 | J19: =F19*G19 -> 103.2 | K19: =F19*H19 -> 387 | L19: =F19*I19 -> 1032 | M19: remoção de forro
A20: 2. Demolições e retiradas | B20: 97634 | C20: SINAPI composição | D20: DEMOLIÇÃO DE REVESTIMENTO CERÂMICO, DE FORMA MECANIZADA COM MARTELETE, SEM REAPROVEITAMENTO. AF_09/2023 | E20: M2 | F20: 10.04 | G20: 20 | H20: 90 | I20: 240 | J20: =F20*G20 -> 200.8 | K20: =F20*H20 -> 903.6 | L20: =F20*I20 -> 2409.6 | M20: demolição de piso cerâmico
A21: 2. Demolições e retiradas | B21: 97633 | C21: SINAPI composição | D21: DEMOLIÇÃO DE REVESTIMENTO CERÂMICO, DE FORMA MANUAL, SEM REAPROVEITAMENTO. AF_09/2023 | E21: M2 | F21: 28.42 | G21: 6 | H21: 27 | I21: 72 | J21: =F21*G21 -> 170.52 | K21: =F21*H21 -> 767.34 | L21: =F21*I21 -> 2046.24 | M21: demolição de revestimento de parede
A22: 2. Demolições e retiradas | B22: 97645 | C22: SINAPI composição | D22: REMOÇÃO DE JANELAS, DE FORMA MANUAL, SEM REAPROVEITAMENTO. AF_09/2023 | E22: M2 | F22: 30.78 | G22: 3 | H22: 13.5 | I22: 36 | J22: =F22*G22 -> 92.34 | K22: =F22*H22 -> 415.53 | L22: =F22*I22 -> 1108.08 | M22: remoção de janelas
A23: 3. Cobertura e forro | B23: 92539 | C23: SINAPI composição | D23: TRAMA DE MADEIRA COMPOSTA POR RIPAS, CAIBROS E TERÇAS PARA TELHADOS DE ATÉ 2 ÁGUAS PARA TELHA CERÂMICA OU DE CONCRETO, INCLUSO TRANSPORTE VERTICAL. AF_10/2025 | E23: M2 | F23: 101.54 | G23: 25 | H23: 93.75 | I23: 250 | J23: =F23*G23 -> 2538.5 | K23: =F23*H23 -> 9519.375 | L23: =F23*I23 -> 25385 | M23: trama de madeira nova
A24: 3. Cobertura e forro | B24: 94440 | C24: SINAPI composição | D24: TELHAMENTO COM TELHA CERÂMICA DE ENCAIXE, TIPO FRANCESA, COM ATÉ 2 ÁGUAS, INCLUSO TRANSPORTE VERTICAL. AF_06/2026 | E24: M2 | F24: 42.42 | G24: 50 | H24: 187.5 | I24: 500 | J24: =F24*G24 -> 2121 | K24: =F24*H24 -> 7953.75 | L24: =F24*I24 -> 21210 | M24: telha cerâmica nova
A25: 3. Cobertura e forro | B25: 96116 | C25: SINAPI composição | D25: FORRO EM RÉGUAS DE PVC, FRISADO, PARA AMBIENTES COMERCIAIS, INCLUSIVE ESTRUTURA BIDIRECIONAL DE FIXAÇÃO. AF_08/2023_PS | E25: M2 | F25: 73.2 | G25: 40 | H25: 150 | I25: 400 | J25: =F25*G25 -> 2928 | K25: =F25*H25 -> 10980 | L25: =F25*I25 -> 29280 | M25: forro de PVC novo
A26: 4. Revestimentos e pisos | B26: 87879 | C26: SINAPI composição | D26: CHAPISCO APLICADO EM ALVENARIAS E ESTRUTURAS DE CONCRETO INTERNAS, COM COLHER DE PEDREIRO. ARGAMASSA TRAÇO 1:3 COM PREPARO EM BETONEIRA 400L. AF_10/2022 | E26: M2 | F26: 6.03 | G26: 48 | H26: 216 | I26: 576 | J26: =F26*G26 -> 289.44 | K26: =F26*H26 -> 1302.48 | L26: =F26*I26 -> 3473.28 | M26: chapisco em paredes recuperadas
A27: 4. Revestimentos e pisos | B27: 104958 | C27: SINAPI composição | D27: MASSA ÚNICA, EM ARGAMASSA TRAÇO 1:2:8 PREPARO MECÂNICO, APLICADA MANUALMENTE EM PAREDES INTERNAS DE AMBIENTES COM ÁREA MAIOR QUE 10M², E = 10MM, COM TALISCAS. AF_03/2024 | E27: M2 | F27: 31.79 | G27: 48 | H27: 216 | I27: 576 | J27: =F27*G27 -> 1525.92 | K27: =F27*H27 -> 6866.64 | L27: =F27*I27 -> 18311.04 | M27: massa única em paredes recuperadas
... A47: 9. Entulho | B47: 95875 | C47: SINAPI composição | D47: TRANSPORTE COM CAMINHÃO BASCULANTE DE 10 M³, EM VIA URBANA PAVIMENTADA, DMT ATÉ 30 KM (UNIDADE: M3XKM). AF_02/2026 | E47: M3XKM | F47: 2.83 | G47: 100 | H47: 150 | I47: 200 | J47: =F47*G47 -> 283 | K47: =F47*H47 -> 424.5 | L47: =F47*I47 -> 566 | M47: transporte de entulho, DMT 10 km
I48: Custo direto | J48: =SUM(J16:J47) -> 34227.721 | K48: =SUM(K16:K47) -> 103659.65 | L48: =SUM(L16:L47) -> 253413.94
I49: BDI | J49: =PARAMETROS!$B$6 -> 0.2034 | K49: =PARAMETROS!$C$6 -> 0.2212 | L49: =PARAMETROS!$D$6 -> 0.25
I50: Contingência | J50: =PARAMETROS!$B$8 -> 0.05 | K50: =PARAMETROS!$C$8 -> 0.1 | L50: =PARAMETROS!$D$8 -> 0.15
I51: Fator regional | J51: =PARAMETROS!$B$9 -> 1 | K51: =PARAMETROS!$C$9 -> 1 | L51: =PARAMETROS!$D$9 -> 1.1
I52: TOTAL ESTIMADO (R$) | J52: =J48*(1+J49)*(1+J50)*J51 -> 43249.122 | K52: =K48*(1+K49)*(1+K50)*K51 -> 139248.08 | L52: =L48*(1+L49)*(1+L50)*L51 -> 400710.8
A54: Estimativa preliminar paramétrica, não vinculante, para planejamento orçamentário. Não substitui o orçamento detalhado do projeto. PROVISORIO - aguarda aprovacao

Sheet 14_MPT_000252.2024
A1: 14 - Condições do prédio do Arquivo Público Municipal
A2: PROVISORIO - aguarda aprovacao
A4: Grupo-objeto | B4: MPT_000252.2024.05.001.5
A5: Levantamento | B5: MP
A6: Origem | B6: MPT
A7: Categoria | B7: outro
A8: Local | B8: Arquivo Público Municipal de Ilhéus (endereço não informado)
A9: Fonte das quantidades | B9: demanda-tipo (área a confirmar)
A10: Preços | B10: SINAPI/CAIXA ref. 08/2026, BA, não desonerado (código de cada item na coluna B)
A11: BDI aplicado | B11: edificações (Acórdão 2.622/2013, construção de edifícios)
A12: Premissas | B12: Prédio do Arquivo Público de 300/500/800 m² (premissa).
B13: Laudos estrutural e elétrico com ART e projeto de incêndio estão na contingência (projetos e laudos).
B14: Reforma-tipo por m²: fração refeita de cobertura/forro/piso/reboco/esquadrias/instalações = 20/20/10/10/10/20% (mín), 50/50/30/30/30/50% (prov) e 100/100/60/60/60/100% (máx); pintura integral; extintores, emergência e sinalização de rota de fuga.
A16: Macroetapa | B16: Código SINAPI | C16: Tipo | D16: Descrição | E16: Unid. | F16: Preço unit. (R$) | G16: Qtd. mínimo | H16: Qtd. provável | I16: Qtd. máximo | J16: Total mínimo (R$) | K16: Total provável (R$) | L16: Total máximo (R$) | M16: Memória de cálculo
A17: 1. Serviços preliminares | B17: 103689 | C17: SINAPI composição | D17: FORNECIMENTO E INSTALAÇÃO DE PLACA DE OBRA COM CHAPA GALVANIZADA E ESTRUTURA DE MADEIRA. AF_03/2022_PS | E17: M2 | F17: 454.97 | G17: 6 | H17: 6 | I17: 6 | J17: =F17*G17 -> 2729.82 | K17: =F17*H17 -> 2729.82 | L17: =F17*I17 -> 2729.82 | M17: placa de obra
A18: 2. Demolições e retiradas | B18: 97647 | C18: SINAPI composição | D18: REMOÇÃO DE TELHAS DE FIBROCIMENTO METÁLICA E CERÂMICA, DE FORMA MANUAL, SEM REAPROVEITAMENTO. AF_09/2023 | E18: M2 | F18: 4.43 | G18: 75 | H18: 312.5 | I18: 1000 | J18: =F18*G18 -> 332.25 | K18: =F18*H18 -> 1384.375 | L18: =F18*I18 -> 4430 | M18: remoção de telhas
A19: 2. Demolições e retiradas | B19: 97650 | C19: SINAPI composição | D19: REMOÇÃO DE TRAMA DE MADEIRA PARA COBERTURA, DE FORMA MANUAL, SEM REAPROVEITAMENTO. AF_09/2023 | E19: M2 | F19: 9.56 | G19: 37.5 | H19: 156.25 | I19: 500 | J19: =F19*G19 -> 358.5 | K19: =F19*H19 -> 1493.75 | L19: =F19*I19 -> 4780 | M19: remoção de trama de madeira (metade da área refeita)
A20: 2. Demolições e retiradas | B20: 97640 | C20: SINAPI composição | D20: REMOÇÃO DE FORROS DE DRYWALL, PVC E FIBROMINERAL, DE FORMA MANUAL, SEM REAPROVEITAMENTO. AF_09/2023 | E20: M2 | F20: 2.58 | G20: 60 | H20: 250 | I20: 800 | J20: =F20*G20 -> 154.8 | K20: =F20*H20 -> 645 | L20: =F20*I20 -> 2064 | M20: remoção de forro
A21: 2. Demolições e retiradas | B21: 97634 | C21: SINAPI composição | D21: DEMOLIÇÃO DE REVESTIMENTO CERÂMICO, DE FORMA MECANIZADA COM MARTELETE, SEM REAPROVEITAMENTO. AF_09/2023 | E21: M2 | F21: 10.04 | G21: 30 | H21: 150 | I21: 480 | J21: =F21*G21 -> 301.2 | K21: =F21*H21 -> 1506 | L21: =F21*I21 -> 4819.2 | M21: demolição de piso cerâmico
A22: 2. Demolições e retiradas | B22: 97633 | C22: SINAPI composição | D22: DEMOLIÇÃO DE REVESTIMENTO CERÂMICO, DE FORMA MANUAL, SEM REAPROVEITAMENTO. AF_09/2023 | E22: M2 | F22: 28.42 | G22: 9 | H22: 45 | I22: 144 | J22: =F22*G22 -> 255.78 | K22: =F22*H22 -> 1278.9 | L22: =F22*I22 -> 4092.48 | M22: demolição de revestimento de parede
A23: 2. Demolições e retiradas | B23: 97645 | C23: SINAPI composição | D23: REMOÇÃO DE JANELAS, DE FORMA MANUAL, SEM REAPROVEITAMENTO. AF_09/2023 | E23: M2 | F23: 30.78 | G23: 4.5 | H23: 22.5 | I23: 72 | J23: =F23*G23 -> 138.51 | K23: =F23*H23 -> 692.55 | L23: =F23*I23 -> 2216.16 | M23: remoção de janelas
A24: 3. Cobertura e forro | B24: 92539 | C24: SINAPI composição | D24: TRAMA DE MADEIRA COMPOSTA POR RIPAS, CAIBROS E TERÇAS PARA TELHADOS DE ATÉ 2 ÁGUAS PARA TELHA CERÂMICA OU DE CONCRETO, INCLUSO TRANSPORTE VERTICAL. AF_10/2025 | E24: M2 | F24: 101.54 | G24: 37.5 | H24: 156.25 | I24: 500 | J24: =F24*G24 -> 3807.75 | K24: =F24*H24 -> 15865.625 | L24: =F24*I24 -> 50770 | M24: trama de madeira nova
A25: 3. Cobertura e forro | B25: 94440 | C25: SINAPI composição | D25: TELHAMENTO COM TELHA CERÂMICA DE ENCAIXE, TIPO FRANCESA, COM ATÉ 2 ÁGUAS, INCLUSO TRANSPORTE VERTICAL. AF_06/2026 | E25: M2 | F25: 42.42 | G25: 75 | H25: 312.5 | I25: 1000 | J25: =F25*G25 -> 3181.5 | K25: =F25*H25 -> 13256.25 | L25: =F25*I25 -> 42420 | M25: telha cerâmica nova
A26: 3. Cobertura e forro | B26: 96116 | C26: SINAPI composição | D26: FORRO EM RÉGUAS DE PVC, FRISADO, PARA AMBIENTES COMERCIAIS, INCLUSIVE ESTRUTURA BIDIRECIONAL DE FIXAÇÃO. AF_08/2023_PS | E26: M2 | F26: 73.2 | G26: 60 | H26: 250 | I26: 800 | J26: =F26*G26 -> 4392 | K26: =F26*H26 -> 18300 | L26: =F26*I26 -> 58560 | M26: forro de PVC novo
A27: 4. Revestimentos e pisos | B27: 87879 | C27: SINAPI composição | D27: CHAPISCO APLICADO EM ALVENARIAS E ESTRUTURAS DE CONCRETO INTERNAS, COM COLHER DE PEDREIRO. ARGAMASSA TRAÇO 1:3 COM PREPARO EM BETONEIRA 400L. AF_10/2022 | E27: M2 | F27: 6.03 | G27: 72 | H27: 360 | I27: 1152 | J27: =F27*G27 -> 434.16 | K27: =F27*H27 -> 2170.8 | L27: =F27*I27 -> 6946.56 | M27: chapisco em paredes recuperadas
A28: 4. Revestimentos e pisos | B28: 104958 | C28: SINAPI composição | D28: MASSA ÚNICA, EM ARGAMASSA TRAÇO 1:2:8 PREPARO MECÂNICO, APLICADA MANUALMENTE EM PAREDES INTERNAS DE AMBIENTES COM ÁREA MAIOR QUE 10M², E = 10MM, COM TALISCAS. AF_03/2024 | E28: M2 | F28: 31.79 | G28: 72 | H28: 360 | I28: 1152 | J28: =F28*G28 -> 2288.88 | K28: =F28*H28 -> 11444.4 | L28: =F28*I28 -> 36622.08 | M28: massa única em paredes recuperadas
... A48: 9. Entulho | B48: 95875 | C48: SINAPI composição | D48: TRANSPORTE COM CAMINHÃO BASCULANTE DE 10 M³, EM VIA URBANA PAVIMENTADA, DMT ATÉ 30 KM (UNIDADE: M3XKM). AF_02/2026 | E48: M3XKM | F48: 2.83 | G48: 150 | H48: 250 | I48: 400 | J48: =F48*G48 -> 424.5 | K48: =F48*H48 -> 707.5 | L48: =F48*I48 -> 1132 | M48: transporte de entulho, DMT 10 km
I49: Custo direto | J49: =SUM(J17:J48) -> 49672.095 | K49: =SUM(K17:K48) -> 170947.5 | L49: =SUM(L17:L48) -> 504088.42
I50: BDI | J50: =PARAMETROS!$B$6 -> 0.2034 | K50: =PARAMETROS!$C$6 -> 0.2212 | L50: =PARAMETROS!$D$6 -> 0.25
I51: Contingência | J51: =PARAMETROS!$B$8 -> 0.05 | K51: =PARAMETROS!$C$8 -> 0.1 | L51: =PARAMETROS!$D$8 -> 0.15
I52: Fator regional | J52: =PARAMETROS!$B$9 -> 1 | K52: =PARAMETROS!$C$9 -> 1 | L52: =PARAMETROS!$D$9 -> 1.1
I53: TOTAL ESTIMADO (R$) | J53: =J49*(1+J50)*(1+J51)*J52 -> 62764.169 | K53: =K49*(1+K50)*(1+K51)*K52 -> 229637.2 | L53: =L49*(1+L50)*(1+L51)*L52 -> 797089.81
A55: Estimativa preliminar paramétrica, não vinculante, para planejamento orçamentário. Não substitui o orçamento detalhado do projeto. PROVISORIO - aguarda aprovacao

Sheet 15_MPT_000282.2023
A1: 15 - Condições estruturais da Clínica Municipal de Atendimento Especializado - CMAE (Av. Canavieiras)
A2: PROVISORIO - aguarda aprovacao
A4: Grupo-objeto | B4: MPT_000282.2023.05.001.4
A5: Levantamento | B5: MP
A6: Origem | B6: MPT
A7: Categoria | B7: outro
A8: Local | B8: Av. Canavieiras
A9: Fonte das quantidades | B9: demanda-tipo (área a confirmar)
A10: Preços | B10: SINAPI/CAIXA ref. 08/2026, BA, não desonerado (código de cada item na coluna B)
A11: BDI aplicado | B11: edificações (Acórdão 2.622/2013, construção de edifícios)
A12: Premissas | B12: Clínica (CMAE) de 300/450/600 m² (premissa). A mudança para outro imóvel pode dispensar a reforma.
B13: Reforma-tipo por m²: fração refeita de cobertura/forro/piso/reboco/esquadrias/instalações = 20/20/10/10/10/20% (mín), 50/50/30/30/30/50% (prov) e 100/100/60/60/60/100% (máx); pintura integral; extintores, emergência e sinalização de rota de fuga.
A15: Macroetapa | B15: Código SINAPI | C15: Tipo | D15: Descrição | E15: Unid. | F15: Preço unit. (R$) | G15: Qtd. mínimo | H15: Qtd. provável | I15: Qtd. máximo | J15: Total mínimo (R$) | K15: Total provável (R$) | L15: Total máximo (R$) | M15: Memória de cálculo
A16: 1. Serviços preliminares | B16: 103689 | C16: SINAPI composição | D16: FORNECIMENTO E INSTALAÇÃO DE PLACA DE OBRA COM CHAPA GALVANIZADA E ESTRUTURA DE MADEIRA. AF_03/2022_PS | E16: M2 | F16: 454.97 | G16: 6 | H16: 6 | I16: 6 | J16: =F16*G16 -> 2729.82 | K16: =F16*H16 -> 2729.82 | L16: =F16*I16 -> 2729.82 | M16: placa de obra
A17: 2. Demolições e retiradas | B17: 97647 | C17: SINAPI composição | D17: REMOÇÃO DE TELHAS DE FIBROCIMENTO METÁLICA E CERÂMICA, DE FORMA MANUAL, SEM REAPROVEITAMENTO. AF_09/2023 | E17: M2 | F17: 4.43 | G17: 75 | H17: 281.25 | I17: 750 | J17: =F17*G17 -> 332.25 | K17: =F17*H17 -> 1245.9375 | L17: =F17*I17 -> 3322.5 | M17: remoção de telhas
A18: 2. Demolições e retiradas | B18: 97650 | C18: SINAPI composição | D18: REMOÇÃO DE TRAMA DE MADEIRA PARA COBERTURA, DE FORMA MANUAL, SEM REAPROVEITAMENTO. AF_09/2023 | E18: M2 | F18: 9.56 | G18: 37.5 | H18: 140.62 | I18: 375 | J18: =F18*G18 -> 358.5 | K18: =F18*H18 -> 1344.3272 | L18: =F18*I18 -> 3585 | M18: remoção de trama de madeira (metade da área refeita)
A19: 2. Demolições e retiradas | B19: 97640 | C19: SINAPI composição | D19: REMOÇÃO DE FORROS DE DRYWALL, PVC E FIBROMINERAL, DE FORMA MANUAL, SEM REAPROVEITAMENTO. AF_09/2023 | E19: M2 | F19: 2.58 | G19: 60 | H19: 225 | I19: 600 | J19: =F19*G19 -> 154.8 | K19: =F19*H19 -> 580.5 | L19: =F19*I19 -> 1548 | M19: remoção de forro
A20: 2. Demolições e retiradas | B20: 97634 | C20: SINAPI composição | D20: DEMOLIÇÃO DE REVESTIMENTO CERÂMICO, DE FORMA MECANIZADA COM MARTELETE, SEM REAPROVEITAMENTO. AF_09/2023 | E20: M2 | F20: 10.04 | G20: 30 | H20: 135 | I20: 360 | J20: =F20*G20 -> 301.2 | K20: =F20*H20 -> 1355.4 | L20: =F20*I20 -> 3614.4 | M20: demolição de piso cerâmico
A21: 2. Demolições e retiradas | B21: 97633 | C21: SINAPI composição | D21: DEMOLIÇÃO DE REVESTIMENTO CERÂMICO, DE FORMA MANUAL, SEM REAPROVEITAMENTO. AF_09/2023 | E21: M2 | F21: 28.42 | G21: 9 | H21: 40.5 | I21: 108 | J21: =F21*G21 -> 255.78 | K21: =F21*H21 -> 1151.01 | L21: =F21*I21 -> 3069.36 | M21: demolição de revestimento de parede
A22: 2. Demolições e retiradas | B22: 97645 | C22: SINAPI composição | D22: REMOÇÃO DE JANELAS, DE FORMA MANUAL, SEM REAPROVEITAMENTO. AF_09/2023 | E22: M2 | F22: 30.78 | G22: 4.5 | H22: 20.25 | I22: 54 | J22: =F22*G22 -> 138.51 | K22: =F22*H22 -> 623.295 | L22: =F22*I22 -> 1662.12 | M22: remoção de janelas
A23: 3. Cobertura e forro | B23: 92539 | C23: SINAPI composição | D23: TRAMA DE MADEIRA COMPOSTA POR RIPAS, CAIBROS E TERÇAS PARA TELHADOS DE ATÉ 2 ÁGUAS PARA TELHA CERÂMICA OU DE CONCRETO, INCLUSO TRANSPORTE VERTICAL. AF_10/2025 | E23: M2 | F23: 101.54 | G23: 37.5 | H23: 140.62 | I23: 375 | J23: =F23*G23 -> 3807.75 | K23: =F23*H23 -> 14278.555 | L23: =F23*I23 -> 38077.5 | M23: trama de madeira nova
A24: 3. Cobertura e forro | B24: 94440 | C24: SINAPI composição | D24: TELHAMENTO COM TELHA CERÂMICA DE ENCAIXE, TIPO FRANCESA, COM ATÉ 2 ÁGUAS, INCLUSO TRANSPORTE VERTICAL. AF_06/2026 | E24: M2 | F24: 42.42 | G24: 75 | H24: 281.25 | I24: 750 | J24: =F24*G24 -> 3181.5 | K24: =F24*H24 -> 11930.625 | L24: =F24*I24 -> 31815 | M24: telha cerâmica nova
A25: 3. Cobertura e forro | B25: 96116 | C25: SINAPI composição | D25: FORRO EM RÉGUAS DE PVC, FRISADO, PARA AMBIENTES COMERCIAIS, INCLUSIVE ESTRUTURA BIDIRECIONAL DE FIXAÇÃO. AF_08/2023_PS | E25: M2 | F25: 73.2 | G25: 60 | H25: 225 | I25: 600 | J25: =F25*G25 -> 4392 | K25: =F25*H25 -> 16470 | L25: =F25*I25 -> 43920 | M25: forro de PVC novo
A26: 4. Revestimentos e pisos | B26: 87879 | C26: SINAPI composição | D26: CHAPISCO APLICADO EM ALVENARIAS E ESTRUTURAS DE CONCRETO INTERNAS, COM COLHER DE PEDREIRO. ARGAMASSA TRAÇO 1:3 COM PREPARO EM BETONEIRA 400L. AF_10/2022 | E26: M2 | F26: 6.03 | G26: 72 | H26: 324 | I26: 864 | J26: =F26*G26 -> 434.16 | K26: =F26*H26 -> 1953.72 | L26: =F26*I26 -> 5209.92 | M26: chapisco em paredes recuperadas
A27: 4. Revestimentos e pisos | B27: 104958 | C27: SINAPI composição | D27: MASSA ÚNICA, EM ARGAMASSA TRAÇO 1:2:8 PREPARO MECÂNICO, APLICADA MANUALMENTE EM PAREDES INTERNAS DE AMBIENTES COM ÁREA MAIOR QUE 10M², E = 10MM, COM TALISCAS. AF_03/2024 | E27: M2 | F27: 31.79 | G27: 72 | H27: 324 | I27: 864 | J27: =F27*G27 -> 2288.88 | K27: =F27*H27 -> 10299.96 | L27: =F27*I27 -> 27466.56 | M27: massa única em paredes recuperadas
... A47: 9. Entulho | B47: 95875 | C47: SINAPI composição | D47: TRANSPORTE COM CAMINHÃO BASCULANTE DE 10 M³, EM VIA URBANA PAVIMENTADA, DMT ATÉ 30 KM (UNIDADE: M3XKM). AF_02/2026 | E47: M3XKM | F47: 2.83 | G47: 150 | H47: 225 | I47: 300 | J47: =F47*G47 -> 424.5 | K47: =F47*H47 -> 636.75 | L47: =F47*I47 -> 849 | M47: transporte de entulho, DMT 10 km
I48: Custo direto | J48: =SUM(J16:J47) -> 49672.095 | K48: =SUM(K16:K47) -> 154118.86 | L48: =SUM(L16:L47) -> 378751.18
I49: BDI | J49: =PARAMETROS!$B$6 -> 0.2034 | K49: =PARAMETROS!$C$6 -> 0.2212 | L49: =PARAMETROS!$D$6 -> 0.25
I50: Contingência | J50: =PARAMETROS!$B$8 -> 0.05 | K50: =PARAMETROS!$C$8 -> 0.1 | L50: =PARAMETROS!$D$8 -> 0.15
I51: Fator regional | J51: =PARAMETROS!$B$9 -> 1 | K51: =PARAMETROS!$C$9 -> 1 | L51: =PARAMETROS!$D$9 -> 1.1
I52: TOTAL ESTIMADO (R$) | J52: =J48*(1+J49)*(1+J50)*J51 -> 62764.169 | K52: =K48*(1+K49)*(1+K50)*K51 -> 207030.95 | L52: =L48*(1+L49)*(1+L50)*L51 -> 598900.3
A54: Estimativa preliminar paramétrica, não vinculante, para planejamento orçamentário. Não substitui o orçamento detalhado do projeto. PROVISORIO - aguarda aprovacao

Sheet 16_MPT_000393.2023
A1: 16 - Cozinhas e áreas de limpeza das escolas municipais (saúde e segurança do trabalho)
A2: PROVISORIO - aguarda aprovacao
A4: Grupo-objeto | B4: MPT_000393.2023.05.001.6
A5: Levantamento | B5: MP
A6: Origem | B6: MPT
A7: Categoria | B7: escola/creche
A8: Local | B8: Escolas da rede municipal (unidades não nomeadas)
A9: Fonte das quantidades | B9: demanda-tipo (unidades não listadas)
A10: Preços | B10: SINAPI/CAIXA ref. 08/2026, BA, não desonerado (código de cada item na coluna B)
A11: BDI aplicado | B11: edificações (Acórdão 2.622/2013, construção de edifícios)
A12: Premissas | B12: Adequação-tipo de cozinha escolar: abrigo de GLP, ventilação, revestimentos, caixa de gordura e bancada.
B13: 5/10/20 cozinhas (premissa; a SEDUC ainda não enviou a lista).
B14: Exaustores não têm preço no SINAPI-BA usado e não estão incluídos. PGR, PCMSO, exames, EPIs e treinamentos cabem à SEDUC.
A16: Macroetapa | B16: Código SINAPI | C16: Tipo | D16: Descrição | E16: Unid. | F16: Preço unit. (R$) | G16: Qtd. mínimo | H16: Qtd. provável | I16: Qtd. máximo | J16: Total mínimo (R$) | K16: Total provável (R$) | L16: Total máximo (R$) | M16: Memória de cálculo
A17: 1. Abrigo de GLP | B17: 103328 | C17: SINAPI composição | D17: ALVENARIA DE VEDAÇÃO DE BLOCOS CERÂMICOS FURADOS NA HORIZONTAL DE 9X19X19 CM (ESPESSURA 9 CM) E ARGAMASSA DE ASSENTAMENTO COM PREPARO EM BETONEIRA. AF_08/2026 | E17: M2 | F17: 119.54 | G17: 30 | H17: 60 | I17: 120 | J17: =F17*G17 -> 3586.2 | K17: =F17*H17 -> 7172.4 | L17: =F17*I17 -> 14344.8 | M17: alvenaria do abrigo, 6 m² por unidade
A18: 1. Abrigo de GLP | B18: 99861 | C18: SINAPI composição | D18: GRADIL EM AÇO FIXADO EM VÃOS DE JANELAS, FORMADO POR BARRAS CHATAS DE 25X4,8 MM. AF_10/2025 | E18: M2 | F18: 581.71 | G18: 7.5 | H18: 15 | I18: 30 | J18: =F18*G18 -> 4362.825 | K18: =F18*H18 -> 8725.65 | L18: =F18*I18 -> 17451.3 | M18: porta em gradil de aço
A19: 1. Abrigo de GLP | B19: 98680 | C19: SINAPI composição | D19: PISO CIMENTADO, TRAÇO 1:5 (CIMENTO E AREIA), ACABAMENTO LISO, ESPESSURA 3,0 CM, PREPARO MECÂNICO DA ARGAMASSA. AF_02/2026 | E19: M2 | F19: 58.19 | G19: 10 | H19: 20 | I19: 40 | J19: =F19*G19 -> 581.9 | K19: =F19*H19 -> 1163.8 | L19: =F19*I19 -> 2327.6 | M19: piso cimentado
A20: 2. Ventilação e revestimentos da cozinha | B20: 94570 | C20: SINAPI composição | D20: JANELA DE ALUMÍNIO DE CORRER COM 2 FOLHAS PARA VIDROS (VIDROS INCLUSOS), BATENTE/ REQUADRO 6 A 14 CM, ACABAMENTO COM ACETATO OU BRILHANTE, FIXAÇÃO COM PARAFUSO, SEM GUARNIÇÃO/ ALIZAR, DIMENSÕES 100X120 CM, VEDAÇÃO COM SILICONE, EXCLUSIVE CONTRAMARCO - FORNECIMENTO E INSTALAÇÃO. AF_11/2024 | E20: M2 | F20: 223.25 | G20: 7.5 | H20: 15 | I20: 30 | J20: =F20*G20 -> 1674.375 | K20: =F20*H20 -> 3348.75 | L20: =F20*I20 -> 6697.5 | M20: janela adicional para ventilação
A21: 2. Ventilação e revestimentos da cozinha | B21: 97633 | C21: SINAPI composição | D21: DEMOLIÇÃO DE REVESTIMENTO CERÂMICO, DE FORMA MANUAL, SEM REAPROVEITAMENTO. AF_09/2023 | E21: M2 | F21: 28.42 | G21: 75 | H21: 150 | I21: 300 | J21: =F21*G21 -> 2131.5 | K21: =F21*H21 -> 4263 | L21: =F21*I21 -> 8526 | M21: demolição de revestimento de parede
A22: 2. Ventilação e revestimentos da cozinha | B22: 87265 | C22: SINAPI composição | D22: REVESTIMENTO CERÂMICO PARA PAREDES INTERNAS COM PLACAS TIPO ESMALTADA DE DIMENSÕES 20X20 CM APLICADAS NA ALTURA INTEIRA DAS PAREDES. AF_02/2023_PE | E22: M2 | F22: 59.3 | G22: 75 | H22: 150 | I22: 300 | J22: =F22*G22 -> 4447.5 | K22: =F22*H22 -> 8895 | L22: =F22*I22 -> 17790 | M22: revestimento cerâmico de parede
A23: 2. Ventilação e revestimentos da cozinha | B23: 97634 | C23: SINAPI composição | D23: DEMOLIÇÃO DE REVESTIMENTO CERÂMICO, DE FORMA MECANIZADA COM MARTELETE, SEM REAPROVEITAMENTO. AF_09/2023 | E23: M2 | F23: 10.04 | G23: 75 | H23: 150 | I23: 300 | J23: =F23*G23 -> 753 | K23: =F23*H23 -> 1506 | L23: =F23*I23 -> 3012 | M23: demolição de piso
A24: 2. Ventilação e revestimentos da cozinha | B24: 87248 | C24: SINAPI composição | D24: REVESTIMENTO CERÂMICO PARA PISO COM PLACAS TIPO ESMALTADA DE DIMENSÕES 35X35 CM APLICADA EM AMBIENTES DE ÁREA MAIOR QUE 10 M2. AF_02/2023_PE | E24: M2 | F24: 50.14 | G24: 75 | H24: 150 | I24: 300 | J24: =F24*G24 -> 3760.5 | K24: =F24*H24 -> 7521 | L24: =F24*I24 -> 15042 | M24: piso cerâmico
A25: 3. Instalações e equipamentos | B25: 98108 | C25: SINAPI composição | D25: CAIXA DE GORDURA DUPLA (CAPACIDADE: 126 L), RETANGULAR, EM ALVENARIA COM BLOCOS DE CONCRETO, DIMENSÕES INTERNAS = 0,4X0,7 M, ALTURA INTERNA = 0,8 M. AF_12/2020 | E25: UN | F25: 599.14 | G25: 5 | H25: 10 | I25: 20 | J25: =F25*G25 -> 2995.7 | K25: =F25*H25 -> 5991.4 | L25: =F25*I25 -> 11982.8 | M25: caixa de gordura dupla
A26: 3. Instalações e equipamentos | B26: 93441 | C26: SINAPI composição | D26: BANCADA GRANITO CINZA 150 X 60 CM, COM CUBA DE EMBUTIR DE AÇO, VÁLVULA AMERICANA EM METAL, SIFÃO FLEXÍVEL EM PVC, ENGATE FLEXÍVEL 30 CM, TORNEIRA CROMADA LONGA, DE PAREDE, 1/2" OU 3/4", P/ COZINHA, PADRÃO POPULAR - FORNEC. E INSTALAÇÃO. AF_02/2026 | E26: UN | F26: 1134.94 | G26: 5 | H26: 10 | I26: 20 | J26: =F26*G26 -> 5674.7 | K26: =F26*H26 -> 11349.4 | L26: =F26*I26 -> 22698.8 | M26: bancada de granito com cuba de aço
A27: 3. Instalações e equipamentos | B27: 92023 | C27: SINAPI composição | D27: INTERRUPTOR SIMPLES (1 MÓDULO) COM 1 TOMADA DE EMBUTIR 2P+T 10 A, INCLUINDO SUPORTE E PLACA - FORNECIMENTO E INSTALAÇÃO. AF_03/2023 | E27: UN | F27: 53.69 | G27: 20 | H27: 40 | I27: 80 | J27: =F27*G27 -> 1073.8 | K27: =F27*H27 -> 2147.6 | L27: =F27*I27 -> 4295.2 | M27: pontos elétricos
A28: 3. Instalações e equipamentos | B28: 103782 | C28: SINAPI composição | D28: LUMINÁRIA TIPO PLAFON CIRCULAR, DE SOBREPOR, COM LED DE 12/13 W - FORNECIMENTO E INSTALAÇÃO. AF_09/2024 | E28: UN | F28: 30.86 | G28: 15 | H28: 30 | I28: 60 | J28: =F28*G28 -> 462.9 | K28: =F28*H28 -> 925.8 | L28: =F28*I28 -> 1851.6 | M28: luminárias
A29: 3. Instalações e equipamentos | B29: 101909 | C29: SINAPI composição | D29: EXTINTOR DE INCÊNDIO PORTÁTIL COM CARGA DE PQS DE 6 KG, CLASSE BC - FORNECIMENTO E INSTALAÇÃO. AF_01/2026_PE | E29: UN | F29: 288.1 | G29: 5 | H29: 10 | I29: 20 | J29: =F29*G29 -> 1440.5 | K29: =F29*H29 -> 2881 | L29: =F29*I29 -> 5762 | M29: extintor
I30: Custo direto | J30: =SUM(J17:J29) -> 32945.4 | K30: =SUM(K17:K29) -> 65890.8 | L30: =SUM(L17:L29) -> 131781.6
I31: BDI | J31: =PARAMETROS!$B$6 -> 0.2034 | K31: =PARAMETROS!$C$6 -> 0.2212 | L31: =PARAMETROS!$D$6 -> 0.25
I32: Contingência | J32: =PARAMETROS!$B$8 -> 0.05 | K32: =PARAMETROS!$C$8 -> 0.1 | L32: =PARAMETROS!$D$8 -> 0.15
I33: Fator regional | J33: =PARAMETROS!$B$9 -> 1 | K33: =PARAMETROS!$C$9 -> 1 | L33: =PARAMETROS!$D$9 -> 1.1
I34: TOTAL ESTIMADO (R$) | J34: =J30*(1+J31)*(1+J32)*J33 -> 41628.819 | K34: =K30*(1+K31)*(1+K32)*K33 -> 88512.429 | L34: =L30*(1+L31)*(1+L32)*L33 -> 208379.65
A36: Estimativa preliminar paramétrica, não vinculante, para planejamento orçamentário. Não substitui o orçamento detalhado do projeto. PROVISORIO - aguarda aprovacao

Sheet 17_TJBA_0006323-71.2012
A1: 17 - Requalificação do Estádio Municipal Mário Pessoa (Cidade Nova) – TAC
A2: PROVISORIO - aguarda aprovacao
A4: Grupo-objeto | B4: JUSTICA_0006323-71.2012.8.05.0103
A5: Levantamento | B5: MP
A6: Origem | B6: Justiça
A7: Categoria | B7: quadra/esporte
A8: Local | B8: Estádio Municipal Mário Pessoa, Praça Guadalajara, s/nº, Cidade Nova
A9: Fonte das quantidades | B9: demanda-tipo (itens do TAC)
A10: Preços | B10: SINAPI/CAIXA ref. 08/2026, BA, não desonerado (código de cada item na coluna B)
A11: BDI aplicado | B11: edificações (Acórdão 2.622/2013, construção de edifícios)
A12: Premissas | B12: Itens do TAC de 2012: extintores, guarda-corpos, sinalização de saídas, casas de força, alarme e SPDA.
B13: Quantidades-tipo para estádio de pequeno porte (premissa; o relatório técnico pedido pela PGM deve confirmar).
B14: Central de alarme e acionadores não têm preço no SINAPI-BA usado e não estão incluídos.
A16: Macroetapa | B16: Código SINAPI | C16: Tipo | D16: Descrição | E16: Unid. | F16: Preço unit. (R$) | G16: Qtd. mínimo | H16: Qtd. provável | I16: Qtd. máximo | J16: Total mínimo (R$) | K16: Total provável (R$) | L16: Total máximo (R$) | M16: Memória de cálculo
A17: 1. Segurança contra incêndio e pânico | B17: 101911 | C17: SINAPI composição | D17: EXTINTOR DE INCÊNDIO PORTÁTIL COM CARGA DE PQS DE 12 KG, CLASSE BC - FORNECIMENTO E INSTALAÇÃO. AF_01/2026_PE | E17: UN | F17: 388.09 | G17: 15 | H17: 20 | I17: 30 | J17: =F17*G17 -> 5821.35 | K17: =F17*H17 -> 7761.8 | L17: =F17*I17 -> 11642.7 | M17: extintores PQS 12 kg
A18: 1. Segurança contra incêndio e pânico | B18: 97599 | C18: SINAPI composição | D18: LUMINÁRIA DE EMERGÊNCIA, COM 30 LÂMPADAS LED DE 2 W, SEM REATOR - FORNECIMENTO E INSTALAÇÃO. AF_09/2024 | E18: UN | F18: 17.96 | G18: 40 | H18: 60 | I18: 90 | J18: =F18*G18 -> 718.4 | K18: =F18*H18 -> 1077.6 | L18: =F18*I18 -> 1616.4 | M18: luminárias de emergência
A19: 1. Segurança contra incêndio e pânico | B19: 37558 | C19: SINAPI insumo | D19: PLACA DE SINALIZACAO DE SEGURANCA CONTRA INCENDIO, FOTOLUMINESCENTE, RETANGULAR, *20 X 40* CM, EM PVC *2* MM ANTI-CHAMAS (SIMBOLOS, CORES E PICTOGRAMAS CONFORME NBR 16820) | E19: UN | F19: 33 | G19: 40 | H19: 60 | I19: 90 | J19: =F19*G19 -> 1320 | K19: =F19*H19 -> 1980 | L19: =F19*I19 -> 2970 | M19: placas de saída de emergência
A20: 2. Guarda-corpos | B20: 99844 | C20: SINAPI composição | D20: GUARDA-CORPO DE AÇO GALVANIZADO DE 1,10M, MONTANTES TUBULARES DE 1.1/2" ESPAÇADOS 1,20M, TRAVESSA SUPERIOR DE 2", GRADIL FORMADO POR BARRAS CHATAS DE 32X4,8MM, FIXADO COM ADESIVO ESTRUTURAL EPOXI. AF_10/2025 | E20: M | F20: 474.61 | G20: 200 | H20: 300 | I20: 450 | J20: =F20*G20 -> 94922 | K20: =F20*H20 -> 142383 | L20: =F20*I20 -> 213574.5 | M20: guarda-corpo de aço galvanizado 1,10 m
A21: 3. SPDA | B21: 96989 | C21: SINAPI composição | D21: CAPTOR TIPO FRANKLIN PARA SPDA - FORNECIMENTO E INSTALAÇÃO. AF_08/2023 | E21: UN | F21: 148.57 | G21: 6 | H21: 8 | I21: 12 | J21: =F21*G21 -> 891.42 | K21: =F21*H21 -> 1188.56 | L21: =F21*I21 -> 1782.84 | M21: captores tipo Franklin
A22: 3. SPDA | B22: 96974 | C22: SINAPI composição | D22: CORDOALHA DE COBRE NU 50 MM², NÃO ENTERRADA, COM ISOLADOR - FORNECIMENTO E INSTALAÇÃO. AF_08/2023 | E22: M | F22: 111.74 | G22: 300 | H22: 400 | I22: 600 | J22: =F22*G22 -> 33522 | K22: =F22*H22 -> 44696 | L22: =F22*I22 -> 67044 | M22: cordoalha de cobre nu 50 mm²
A23: 4. Arquibancadas e acessibilidade | B23: 104642 | C23: SINAPI composição | D23: PINTURA LÁTEX ACRÍLICA STANDARD, APLICAÇÃO MANUAL EM PAREDES, DUAS DEMÃOS. AF_04/2023 | E23: M2 | F23: 12.33 | G23: 1500 | H23: 2000 | I23: 3000 | J23: =F23*G23 -> 18495 | K23: =F23*H23 -> 24660 | L23: =F23*I23 -> 36990 | M23: pintura das arquibancadas e muros
A24: 4. Arquibancadas e acessibilidade | B24: 105004 | C24: SINAPI composição | D24: RAMPA DE ACESSIBILIDADE EM CONCRETO MOLDADO IN LOCO, EM CALÇADA NOVA COM LARGURA MENOR À 3,00 M, FCK 25MPA, COM PISO PODOTÁTIL. AF_03/2024 | E24: M2 | F24: 154.44 | G24: 10 | H24: 20 | I24: 30 | J24: =F24*G24 -> 1544.4 | K24: =F24*H24 -> 3088.8 | L24: =F24*I24 -> 4633.2 | M24: rampas de acessibilidade
A25: Casas de força, vestiários e áreas cobertas - 1. Serviços preliminares | B25: 103689 | C25: SINAPI composição | D25: FORNECIMENTO E INSTALAÇÃO DE PLACA DE OBRA COM CHAPA GALVANIZADA E ESTRUTURA DE MADEIRA. AF_03/2022_PS | E25: M2 | F25: 454.97 | G25: 6 | H25: 6 | I25: 6 | J25: =F25*G25 -> 2729.82 | K25: =F25*H25 -> 2729.82 | L25: =F25*I25 -> 2729.82 | M25: placa de obra
A26: Casas de força, vestiários e áreas cobertas - 2. Demolições e retiradas | B26: 97647 | C26: SINAPI composição | D26: REMOÇÃO DE TELHAS DE FIBROCIMENTO METÁLICA E CERÂMICA, DE FORMA MANUAL, SEM REAPROVEITAMENTO. AF_09/2023 | E26: M2 | F26: 4.43 | G26: 100 | H26: 375 | I26: 1125 | J26: =F26*G26 -> 443 | K26: =F26*H26 -> 1661.25 | L26: =F26*I26 -> 4983.75 | M26: remoção de telhas
A27: Casas de força, vestiários e áreas cobertas - 2. Demolições e retiradas | B27: 97650 | C27: SINAPI composição | D27: REMOÇÃO DE TRAMA DE MADEIRA PARA COBERTURA, DE FORMA MANUAL, SEM REAPROVEITAMENTO. AF_09/2023 | E27: M2 | F27: 9.56 | G27: 50 | H27: 187.5 | I27: 562.5 | J27: =F27*G27 -> 478 | K27: =F27*H27 -> 1792.5 | L27: =F27*I27 -> 5377.5 | M27: remoção de trama de madeira (metade da área refeita)
A28: Casas de força, vestiários e áreas cobertas - 2. Demolições e retiradas | B28: 97640 | C28: SINAPI composição | D28: REMOÇÃO DE FORROS DE DRYWALL, PVC E FIBROMINERAL, DE FORMA MANUAL, SEM REAPROVEITAMENTO. AF_09/2023 | E28: M2 | F28: 2.58 | G28: 80 | H28: 300 | I28: 900 | J28: =F28*G28 -> 206.4 | K28: =F28*H28 -> 774 | L28: =F28*I28 -> 2322 | M28: remoção de forro
... A56: Casas de força, vestiários e áreas cobertas - 9. Entulho | B56: 95875 | C56: SINAPI composição | D56: TRANSPORTE COM CAMINHÃO BASCULANTE DE 10 M³, EM VIA URBANA PAVIMENTADA, DMT ATÉ 30 KM (UNIDADE: M3XKM). AF_02/2026 | E56: M3XKM | F56: 2.83 | G56: 200 | H56: 300 | I56: 450 | J56: =F56*G56 -> 566 | K56: =F56*H56 -> 849 | L56: =F56*I56 -> 1273.5 | M56: transporte de entulho, DMT 10 km
I57: Custo direto | J57: =SUM(J17:J56) -> 222351.04 | K57: =SUM(K17:K56) -> 431425.24 | L57: =SUM(L17:L56) -> 907015.5
I58: BDI | J58: =PARAMETROS!$B$6 -> 0.2034 | K58: =PARAMETROS!$C$6 -> 0.2212 | L58: =PARAMETROS!$D$6 -> 0.25
I59: Contingência | J59: =PARAMETROS!$B$8 -> 0.05 | K59: =PARAMETROS!$C$8 -> 0.1 | L59: =PARAMETROS!$D$8 -> 0.15
I60: Fator regional | J60: =PARAMETROS!$B$9 -> 1 | K60: =PARAMETROS!$C$9 -> 1 | L60: =PARAMETROS!$D$9 -> 1.1
I61: TOTAL ESTIMADO (R$) | J61: =J57*(1+J58)*(1+J59)*J60 -> 280956.1 | K61: =K57*(1+K58)*(1+K59)*K60 -> 579542.15 | L61: =L57*(1+L58)*(1+L59)*L60 -> 1434218.3
A63: Estimativa preliminar paramétrica, não vinculante, para planejamento orçamentário. Não substitui o orçamento detalhado do projeto. PROVISORIO - aguarda aprovacao

Sheet 18_TJBA_8003152-18.2022
A1: 18 - Drenagem pluvial e alagamentos nas Ruas Castro Alves e Barão do Rio Branco (Pontal)
A2: PROVISORIO - aguarda aprovacao
A4: Grupo-objeto | B4: JUSTICA_8003152-18.2022.8.05.0103
A5: Levantamento | B5: MP
A6: Origem | B6: Justiça
A7: Categoria | B7: drenagem
A8: Local | B8: Ruas Castro Alves e Barão do Rio Branco, bairro Pontal
A9: Fonte das quantidades | B9: demanda-tipo (duas ruas)
A10: Preços | B10: SINAPI/CAIXA ref. 08/2026, BA, não desonerado (código de cada item na coluna B)
A11: BDI aplicado | B11: vias e drenagem (Acórdão 2.622/2013, rodovias e ferrovias)
A12: Premissas | B12: Ruas Castro Alves e Barão do Rio Branco (Pontal): 2 ruas de 150/250/400 m (premissa).
B13: A EMBASA é corré: parte do custo pode caber à concessionária.
B14: Microdrenagem em via existente: vala com largura DN + 0,6 m e profundidade DN + 1,0 m, PV a cada 40 m, 2 bocas de lobo a cada 40 m, recomposição de base (20 cm) e CBUQ (5 cm) na faixa da vala, bota-fora a 10 km.
A16: Macroetapa | B16: Código SINAPI | C16: Tipo | D16: Descrição | E16: Unid. | F16: Preço unit. (R$) | G16: Qtd. mínimo | H16: Qtd. provável | I16: Qtd. máximo | J16: Total mínimo (R$) | K16: Total provável (R$) | L16: Total máximo (R$) | M16: Memória de cálculo
A17: 1. Serviços preliminares | B17: 103689 | C17: SINAPI composição | D17: FORNECIMENTO E INSTALAÇÃO DE PLACA DE OBRA COM CHAPA GALVANIZADA E ESTRUTURA DE MADEIRA. AF_03/2022_PS | E17: M2 | F17: 454.97 | G17: 6 | H17: 6 | I17: 6 | J17: =F17*G17 -> 2729.82 | K17: =F17*H17 -> 2729.82 | L17: =F17*I17 -> 2729.82 | M17: placa de obra 3 m x 2 m
A18: 2. Drenagem | B18: 90082 | C18: SINAPI composição | D18: ESCAVAÇÃO MECANIZADA DE VALA COM PROF. ATÉ 1,5 M (MÉDIA MONTANTE E JUSANTE/UMA COMPOSIÇÃO POR TRECHO), ESCAVADEIRA (0,8 M3), LARG. DE 1,5 M A 2,5 M, EM SOLO DE 1A CATEGORIA, EM LOCAIS COM ALTO NÍVEL DE INTERFERÊNCIA. AF_09/2024 | E18: M3 | F18: 10.58 | G18: 576 | H18: 0 | I18: 0 | J18: =F18*G18 -> 6094.08 | K18: =F18*H18 -> 0 | L18: =F18*I18 -> 0 | M18: vala 1.20 m x 1.60 m x L 300 m
A19: 2. Drenagem | B19: 92212 | C19: SINAPI composição | D19: TUBO DE CONCRETO PARA REDES COLETORAS DE ÁGUAS PLUVIAIS, DIÂMETRO DE 600 MM, JUNTA RÍGIDA, INSTALADO EM LOCAL COM BAIXO NÍVEL DE INTERFERÊNCIAS - FORNECIMENTO E ASSENTAMENTO. AF_03/2024 | E19: M | F19: 351.67 | G19: 300 | H19: 500 | I19: 0 | J19: =F19*G19 -> 105501 | K19: =F19*H19 -> 175835 | L19: =F19*I19 -> 0 | M19: rede DN 600 mm ao longo de L
A20: 2. Drenagem | B20: 93369 | C20: SINAPI composição | D20: REATERRO MECANIZADO DE VALA COM ESCAVADEIRA HIDRÁULICA (CAPACIDADE DA CAÇAMBA: 0,8 M³/POTÊNCIA: 111 HP), LARGURA 1,5 A 2,5 M, PROFUNDIDADE 1,5 A 3,0 M, COM SOLO (SEM SUBSTITUIÇÃO) DE 1ª CATEGORIA, COM COMPACTADOR DE SOLOS DE PERCUSSÃO. AF_08/2023 | E20: M3 | F20: 20.26 | G20: 460.55 | H20: 767.58 | I20: 1507.06 | J20: =F20*G20 -> 9330.743 | K20: =F20*H20 -> 15551.171 | L20: =F20*I20 -> 30533.036 | M20: volume da vala - volume externo do tubo
A21: 2. Drenagem | B21: 99285 | C21: SINAPI composição | D21: BASE PARA POÇO DE VISITA CIRCULAR PARA DRENAGEM, EM CONCRETO PRÉ-MOLDADO, DIÂMETRO INTERNO = 1,0 M, PROFUNDIDADE = 1,35 M, EXCLUINDO TAMPÃO. AF_05/2018 | E21: UN | F21: 1613.82 | G21: 9 | H21: 14 | I21: 0 | J21: =F21*G21 -> 14524.38 | K21: =F21*H21 -> 22593.48 | L21: =F21*I21 -> 0 | M21: PV a cada 40 m + 1
A22: 2. Drenagem | B22: 99288 | C22: SINAPI composição | D22: ACRÉSCIMO PARA POÇO DE VISITA CIRCULAR PARA DRENAGEM, EM CONCRETO PRÉ-MOLDADO, DIÂMETRO INTERNO = 1 M. AF_12/2020 | E22: M | F22: 634.89 | G22: 4.5 | H22: 7 | I22: 0 | J22: =F22*G22 -> 2857.005 | K22: =F22*H22 -> 4444.23 | L22: =F22*I22 -> 0 | M22: acréscimo médio de 0,5 m de profundidade por PV
A23: 2. Drenagem | B23: 97956 | C23: SINAPI composição | D23: CAIXA PARA BOCA DE LOBO SIMPLES RETANGULAR, EM ALVENARIA COM BLOCOS DE CONCRETO, DIMENSÕES INTERNAS: 0,6X1X1,2 M. AF_12/2020 | E23: UN | F23: 1812.94 | G23: 16 | H23: 26 | I23: 40 | J23: =F23*G23 -> 29007.04 | K23: =F23*H23 -> 47136.44 | L23: =F23*I23 -> 72517.6 | M23: boca de lobo simples, 2 a cada 40 m
A24: 2. Drenagem | B24: 92210 | C24: SINAPI composição | D24: TUBO DE CONCRETO PARA REDES COLETORAS DE ÁGUAS PLUVIAIS, DIÂMETRO DE 400 MM, JUNTA RÍGIDA, INSTALADO EM LOCAL COM BAIXO NÍVEL DE INTERFERÊNCIAS - FORNECIMENTO E ASSENTAMENTO. AF_03/2024 | E24: M | F24: 188.74 | G24: 64 | H24: 104 | I24: 160 | J24: =F24*G24 -> 12079.36 | K24: =F24*H24 -> 19628.96 | L24: =F24*I24 -> 30198.4 | M24: ligação BL-PV em DN 400 mm, 4 m por boca de lobo
A25: 2. Drenagem | B25: 100982 | C25: SINAPI composição | D25: CARGA, MANOBRA E DESCARGA DE ENTULHO EM CAMINHÃO BASCULANTE 10 M³ - CARGA COM ESCAVADEIRA HIDRÁULICA (CAÇAMBA DE 0,80 M³ / 111 HP) E DESCARGA LIVRE (UNIDADE: M3). AF_02/2026 | E25: M3 | F25: 9.88 | G25: 115.45 | H25: 192.42 | I25: 508.94 | J25: =F25*G25 -> 1140.646 | K25: =F25*H25 -> 1901.1096 | L25: =F25*I25 -> 5028.3272 | M25: carga do solo excedente (volume do tubo)
A26: 2. Drenagem | B26: 95875 | C26: SINAPI composição | D26: TRANSPORTE COM CAMINHÃO BASCULANTE DE 10 M³, EM VIA URBANA PAVIMENTADA, DMT ATÉ 30 KM (UNIDADE: M3XKM). AF_02/2026 | E26: M3XKM | F26: 2.83 | G26: 1154.54 | H26: 1924.23 | I26: 5089.38 | J26: =F26*G26 -> 3267.3482 | K26: =F26*H26 -> 5445.5709 | L26: =F26*I26 -> 14402.945 | M26: transporte do excedente, DMT 10 km
A27: 3. Recomposição do pavimento | B27: 101849 | C27: SINAPI composição | D27: RECOMPOSIÇÃO DE BASE E OU SUB-BASE PARA FECHAMENTO DE VALAS DE BRITA GRADUADA SIMPLES - INCLUSO RETIRADA E COLOCAÇÃO DO MATERIAL. AF_12/2020 | E27: M3 | F27: 232.27 | G27: 84 | H27: 140 | I27: 0 | J27: =F27*G27 -> 19510.68 | K27: =F27*H27 -> 32517.8 | L27: =F27*I27 -> 0 | M27: base de brita graduada 20 cm na faixa da vala (1.40 m)
A28: 3. Recomposição do pavimento | B28: 102098 | C28: SINAPI composição | D28: RECOMPOSIÇÃO DE REVESTIMENTO EM CONCRETO ASFÁLTICO (AQUISIÇÃO EM USINA), PARA O FECHAMENTO DE VALAS - INCLUSO DEMOLIÇÃO DO PAVIMENTO. AF_12/2020 | E28: M3 | F28: 2136.03 | G28: 21 | H28: 35 | I28: 64 | J28: =F28*G28 -> 44856.63 | K28: =F28*H28 -> 74761.05 | L28: =F28*I28 -> 136705.92 | M28: revestimento em CBUQ 5 cm na faixa da vala (inclui demolição)
... A34: 3. Recomposição do pavimento | B34: 101849 | C34: SINAPI composição | D34: RECOMPOSIÇÃO DE BASE E OU SUB-BASE PARA FECHAMENTO DE VALAS DE BRITA GRADUADA SIMPLES - INCLUSO RETIRADA E COLOCAÇÃO DO MATERIAL. AF_12/2020 | E34: M3 | F34: 232.27 | G34: 0 | H34: 0 | I34: 256 | J34: =F34*G34 -> 0 | K34: =F34*H34 -> 0 | L34: =F34*I34 -> 59461.12 | M34: base de brita graduada 20 cm na faixa da vala (1.60 m)
I35: Custo direto | J35: =SUM(J17:J34) -> 250898.73 | K35: =SUM(K17:K34) -> 412701.43 | L35: =SUM(L17:L34) -> 878321.25
I36: BDI | J36: =PARAMETROS!$B$7 -> 0.196 | K36: =PARAMETROS!$C$7 -> 0.2097 | L36: =PARAMETROS!$D$7 -> 0.2423
I37: Contingência | J37: =PARAMETROS!$B$8 -> 0.05 | K37: =PARAMETROS!$C$8 -> 0.1 | L37: =PARAMETROS!$D$8 -> 0.15
I38: Fator regional | J38: =PARAMETROS!$B$9 -> 1 | K38: =PARAMETROS!$C$9 -> 1 | L38: =PARAMETROS!$D$9 -> 1.1
I39: TOTAL ESTIMADO (R$) | J39: =J35*(1+J36)*(1+J37)*J38 -> 315078.63 | K39: =K35*(1+K36)*(1+K37)*K38 -> 549169.41 | L39: =L35*(1+L36)*(1+L37)*L38 -> 1380290.2
A41: Estimativa preliminar paramétrica, não vinculante, para planejamento orçamentário. Não substitui o orçamento detalhado do projeto. PROVISORIO - aguarda aprovacao

Sheet 19_TJBA_8005263-04.2024
A1: 19 - Drenagem e pavimentação da Rua Aracuã (Nossa Senhora das Vitórias)
A2: PROVISORIO - aguarda aprovacao
A4: Grupo-objeto | B4: JUSTICA_8005263-04.2024.8.05.0103
A5: Levantamento | B5: MP
A6: Origem | B6: Justiça
A7: Categoria | B7: drenagem+pavimentação
A8: Local | B8: Rua Aracuã, bairro Nossa Senhora das Vitórias
A9: Fonte das quantidades | B9: demanda-tipo (rua-tipo)
A10: Preços | B10: SINAPI/CAIXA ref. 08/2026, BA, não desonerado (código de cada item na coluna B)
A11: BDI aplicado | B11: vias e drenagem (Acórdão 2.622/2013, rodovias e ferrovias)
A12: Premissas | B12: Rua Aracuã: comprimento de 150/250/400 m (premissa; medir).
B13: Verificar se a rua está no escopo do Termo de Compromisso 969321/2024 (Novo PAC).
B14: Rua-tipo: pista 5/6/7 m, passeios 1,2/1,5/2,0 m, base+sub-base 15/20/30 cm, CBUQ 4/5/5 cm, rede DN 600/600/800 mm, PV a cada 40 m, 2 bocas de lobo a cada 40 m, DMT da brita 20/20/40 km e do CBUQ 30/30/60 km (mín/prov/máx).
A16: Macroetapa | B16: Código SINAPI | C16: Tipo | D16: Descrição | E16: Unid. | F16: Preço unit. (R$) | G16: Qtd. mínimo | H16: Qtd. provável | I16: Qtd. máximo | J16: Total mínimo (R$) | K16: Total provável (R$) | L16: Total máximo (R$) | M16: Memória de cálculo
A17: 1. Serviços preliminares | B17: 103689 | C17: SINAPI composição | D17: FORNECIMENTO E INSTALAÇÃO DE PLACA DE OBRA COM CHAPA GALVANIZADA E ESTRUTURA DE MADEIRA. AF_03/2022_PS | E17: M2 | F17: 454.97 | G17: 6 | H17: 6 | I17: 6 | J17: =F17*G17 -> 2729.82 | K17: =F17*H17 -> 2729.82 | L17: =F17*I17 -> 2729.82 | M17: placa de obra 3 m x 2 m
A18: 1. Serviços preliminares | B18: 98525 | C18: SINAPI composição | D18: LIMPEZA MECANIZADA DE CAMADA VEGETAL, VEGETAÇÃO E PEQUENAS ÁRVORES (DIÂMETRO DE TRONCO MENOR QUE 0,20 M), COM TRATOR DE ESTEIRAS. AF_03/2024 | E18: M2 | F18: 0.76 | G18: 1110 | H18: 2250 | I18: 4400 | J18: =F18*G18 -> 843.6 | K18: =F18*H18 -> 1710 | L18: =F18*I18 -> 3344 | M18: limpeza da faixa: L x (pista + 2 passeios)
A19: 2. Drenagem | B19: 90082 | C19: SINAPI composição | D19: ESCAVAÇÃO MECANIZADA DE VALA COM PROF. ATÉ 1,5 M (MÉDIA MONTANTE E JUSANTE/UMA COMPOSIÇÃO POR TRECHO), ESCAVADEIRA (0,8 M3), LARG. DE 1,5 M A 2,5 M, EM SOLO DE 1A CATEGORIA, EM LOCAIS COM ALTO NÍVEL DE INTERFERÊNCIA. AF_09/2024 | E19: M3 | F19: 10.58 | G19: 288 | H19: 0 | I19: 0 | J19: =F19*G19 -> 3047.04 | K19: =F19*H19 -> 0 | L19: =F19*I19 -> 0 | M19: vala 1.20 m x 1.60 m x L 150 m
A20: 2. Drenagem | B20: 92212 | C20: SINAPI composição | D20: TUBO DE CONCRETO PARA REDES COLETORAS DE ÁGUAS PLUVIAIS, DIÂMETRO DE 600 MM, JUNTA RÍGIDA, INSTALADO EM LOCAL COM BAIXO NÍVEL DE INTERFERÊNCIAS - FORNECIMENTO E ASSENTAMENTO. AF_03/2024 | E20: M | F20: 351.67 | G20: 150 | H20: 250 | I20: 0 | J20: =F20*G20 -> 52750.5 | K20: =F20*H20 -> 87917.5 | L20: =F20*I20 -> 0 | M20: rede DN 600 mm ao longo de L
A21: 2. Drenagem | B21: 93369 | C21: SINAPI composição | D21: REATERRO MECANIZADO DE VALA COM ESCAVADEIRA HIDRÁULICA (CAPACIDADE DA CAÇAMBA: 0,8 M³/POTÊNCIA: 111 HP), LARGURA 1,5 A 2,5 M, PROFUNDIDADE 1,5 A 3,0 M, COM SOLO (SEM SUBSTITUIÇÃO) DE 1ª CATEGORIA, COM COMPACTADOR DE SOLOS DE PERCUSSÃO. AF_08/2023 | E21: M3 | F21: 20.26 | G21: 230.27 | H21: 383.79 | I21: 753.53 | J21: =F21*G21 -> 4665.2702 | K21: =F21*H21 -> 7775.5854 | L21: =F21*I21 -> 15266.518 | M21: volume da vala - volume externo do tubo
A22: 2. Drenagem | B22: 99285 | C22: SINAPI composição | D22: BASE PARA POÇO DE VISITA CIRCULAR PARA DRENAGEM, EM CONCRETO PRÉ-MOLDADO, DIÂMETRO INTERNO = 1,0 M, PROFUNDIDADE = 1,35 M, EXCLUINDO TAMPÃO. AF_05/2018 | E22: UN | F22: 1613.82 | G22: 5 | H22: 8 | I22: 0 | J22: =F22*G22 -> 8069.1 | K22: =F22*H22 -> 12910.56 | L22: =F22*I22 -> 0 | M22: PV a cada 40 m + 1
A23: 2. Drenagem | B23: 99288 | C23: SINAPI composição | D23: ACRÉSCIMO PARA POÇO DE VISITA CIRCULAR PARA DRENAGEM, EM CONCRETO PRÉ-MOLDADO, DIÂMETRO INTERNO = 1 M. AF_12/2020 | E23: M | F23: 634.89 | G23: 2.5 | H23: 4 | I23: 0 | J23: =F23*G23 -> 1587.225 | K23: =F23*H23 -> 2539.56 | L23: =F23*I23 -> 0 | M23: acréscimo médio de 0,5 m de profundidade por PV
A24: 2. Drenagem | B24: 97956 | C24: SINAPI composição | D24: CAIXA PARA BOCA DE LOBO SIMPLES RETANGULAR, EM ALVENARIA COM BLOCOS DE CONCRETO, DIMENSÕES INTERNAS: 0,6X1X1,2 M. AF_12/2020 | E24: UN | F24: 1812.94 | G24: 8 | H24: 14 | I24: 20 | J24: =F24*G24 -> 14503.52 | K24: =F24*H24 -> 25381.16 | L24: =F24*I24 -> 36258.8 | M24: boca de lobo simples, 2 a cada 40 m
A25: 2. Drenagem | B25: 92210 | C25: SINAPI composição | D25: TUBO DE CONCRETO PARA REDES COLETORAS DE ÁGUAS PLUVIAIS, DIÂMETRO DE 400 MM, JUNTA RÍGIDA, INSTALADO EM LOCAL COM BAIXO NÍVEL DE INTERFERÊNCIAS - FORNECIMENTO E ASSENTAMENTO. AF_03/2024 | E25: M | F25: 188.74 | G25: 32 | H25: 56 | I25: 80 | J25: =F25*G25 -> 6039.68 | K25: =F25*H25 -> 10569.44 | L25: =F25*I25 -> 15099.2 | M25: ligação BL-PV em DN 400 mm, 4 m por boca de lobo
A26: 2. Drenagem | B26: 100982 | C26: SINAPI composição | D26: CARGA, MANOBRA E DESCARGA DE ENTULHO EM CAMINHÃO BASCULANTE 10 M³ - CARGA COM ESCAVADEIRA HIDRÁULICA (CAÇAMBA DE 0,80 M³ / 111 HP) E DESCARGA LIVRE (UNIDADE: M3). AF_02/2026 | E26: M3 | F26: 9.88 | G26: 57.73 | H26: 96.21 | I26: 254.47 | J26: =F26*G26 -> 570.3724 | K26: =F26*H26 -> 950.5548 | L26: =F26*I26 -> 2514.1636 | M26: carga do solo excedente (volume do tubo)
A27: 2. Drenagem | B27: 95875 | C27: SINAPI composição | D27: TRANSPORTE COM CAMINHÃO BASCULANTE DE 10 M³, EM VIA URBANA PAVIMENTADA, DMT ATÉ 30 KM (UNIDADE: M3XKM). AF_02/2026 | E27: M3XKM | F27: 2.83 | G27: 577.27 | H27: 962.11 | I27: 2544.69 | J27: =F27*G27 -> 1633.6741 | K27: =F27*H27 -> 2722.7713 | L27: =F27*I27 -> 7201.4727 | M27: transporte do excedente, DMT 10 km
A28: 3. Pavimentação | B28: 100576 | C28: SINAPI composição | D28: REGULARIZAÇÃO E COMPACTAÇÃO DE SUBLEITO DE SOLO PREDOMINANTEMENTE ARGILOSO, PARA OBRAS DE CONSTRUÇÃO DE PAVIMENTOS. AF_09/2024 | E28: M2 | F28: 3.35 | G28: 750 | H28: 1500 | I28: 2800 | J28: =F28*G28 -> 2512.5 | K28: =F28*H28 -> 5025 | L28: =F28*I28 -> 9380 | M28: regularização do subleito: L x pista
... A47: 3. Pavimentação | B47: 95875 | C47: SINAPI composição | D47: TRANSPORTE COM CAMINHÃO BASCULANTE DE 10 M³, EM VIA URBANA PAVIMENTADA, DMT ATÉ 30 KM (UNIDADE: M3XKM). AF_02/2026 | E47: M3XKM | F47: 2.83 | G47: 0 | H47: 0 | I47: 8400 | J47: =F47*G47 -> 0 | K47: =F47*H47 -> 0 | L47: =F47*I47 -> 23772 | M47: transporte do CBUQ, DMT 60 km
I48: Custo direto | J48: =SUM(J17:J47) -> 245007.84 | K48: =SUM(K17:K47) -> 495649.98 | L48: =SUM(L17:L47) -> 1112932.2
I49: BDI | J49: =PARAMETROS!$B$7 -> 0.196 | K49: =PARAMETROS!$C$7 -> 0.2097 | L49: =PARAMETROS!$D$7 -> 0.2423
I50: Contingência | J50: =PARAMETROS!$B$8 -> 0.05 | K50: =PARAMETROS!$C$8 -> 0.1 | L50: =PARAMETROS!$D$8 -> 0.15
I51: Fator regional | J51: =PARAMETROS!$B$9 -> 1 | K51: =PARAMETROS!$C$9 -> 1 | L51: =PARAMETROS!$D$9 -> 1.1
I52: TOTAL ESTIMADO (R$) | J52: =J48*(1+J49)*(1+J50)*J51 -> 307680.85 | K52: =K48*(1+K49)*(1+K50)*K51 -> 659546.56 | L52: =L48*(1+L49)*(1+L50)*L51 -> 1748983.5
A54: Estimativa preliminar paramétrica, não vinculante, para planejamento orçamentário. Não substitui o orçamento detalhado do projeto. PROVISORIO - aguarda aprovacao

Sheet 20_TJBA_8005837-61.2023
A1: 20 - Abrigos de ônibus da Rodovia Jorge Amado (BR-415), perto do IFBA
A2: PROVISORIO - aguarda aprovacao
A4: Grupo-objeto | B4: JUSTICA_8005837-61.2023.8.05.0103
A5: Levantamento | B5: MP
A6: Origem | B6: Justiça
A7: Categoria | B7: outro
A8: Local | B8: Rodovia Jorge Amado (BR-415), sentido Ilhéus–Itabuna, nas proximidades do IFBA
A9: Fonte das quantidades | B9: demanda-tipo (abrigo-tipo)
A10: Preços | B10: SINAPI/CAIXA ref. 08/2026, BA, não desonerado (código de cada item na coluna B)
A11: BDI aplicado | B11: edificações (Acórdão 2.622/2013, construção de edifícios)
A12: Premissas | B12: Abrigo de passageiros-tipo de 4 m x 3 m com estrutura metálica, telha termoacústica, piso, banco e piso podotátil.
B13: 2/3/4 abrigos (a sentença fala em "novos abrigos", sem número).
A15: Macroetapa | B15: Código SINAPI | C15: Tipo | D15: Descrição | E15: Unid. | F15: Preço unit. (R$) | G15: Qtd. mínimo | H15: Qtd. provável | I15: Qtd. máximo | J15: Total mínimo (R$) | K15: Total provável (R$) | L15: Total máximo (R$) | M15: Memória de cálculo
A16: 1. Fundação | B16: 93358 | C16: SINAPI composição | D16: ESCAVAÇÃO MANUAL DE VALA. AF_09/2024 | E16: M3 | F16: 103.4 | G16: 2 | H16: 3 | I16: 4 | J16: =F16*G16 -> 206.8 | K16: =F16*H16 -> 310.2 | L16: =F16*I16 -> 413.6 | M16: escavação, 1 m³ por abrigo
A17: 1. Fundação | B17: 103669 | C17: SINAPI composição | D17: CONCRETAGEM DE PILARES, FCK = 25 MPA, COM USO DE BALDES - LANÇAMENTO, ADENSAMENTO E ACABAMENTO. AF_02/2022 | E17: M3 | F17: 1194.23 | G17: 1.6 | H17: 2.4 | I17: 3.2 | J17: =F17*G17 -> 1910.768 | K17: =F17*H17 -> 2866.152 | L17: =F17*I17 -> 3821.536 | M17: concreto de fundação, 0,8 m³ por abrigo
A18: 1. Fundação | B18: 92762 | C18: SINAPI composição | D18: ARMAÇÃO DE PILAR OU VIGA DE ESTRUTURA CONVENCIONAL DE CONCRETO ARMADO UTILIZANDO AÇO CA-50 DE 10,0 MM - MONTAGEM. AF_06/2022 | E18: KG | F18: 10.41 | G18: 80 | H18: 120 | I18: 160 | J18: =F18*G18 -> 832.8 | K18: =F18*H18 -> 1249.2 | L18: =F18*I18 -> 1665.6 | M18: armação, 40 kg por abrigo
A19: 2. Estrutura e cobertura | B19: 104314 | C19: SINAPI composição | D19: TRAMA DE AÇO COMPOSTA POR TERÇAS PARA TELHADOS DE ATÉ 2 ÁGUAS PARA TELHA ONDULADA DE FIBROCIMENTO, METÁLICA, PLÁSTICA OU TERMOACÚSTICA, INCLUSO TRANSPORTE VERTICAL (EM KG). EXCLUSIVE PINTURA. AF_10/2025_PS | E19: KG | F19: 13.77 | G19: 600 | H19: 900 | I19: 1200 | J19: =F19*G19 -> 8262 | K19: =F19*H19 -> 12393 | L19: =F19*I19 -> 16524 | M19: estrutura de aço, 300 kg por abrigo
A20: 2. Estrutura e cobertura | B20: 94216 | C20: SINAPI composição | D20: TELHAMENTO COM TELHA METÁLICA TERMOACÚSTICA E = 30 MM, COM ATÉ 2 ÁGUAS, INCLUSO IÇAMENTO. AF_06/2026 | E20: M2 | F20: 192.73 | G20: 24 | H20: 36 | I20: 48 | J20: =F20*G20 -> 4625.52 | K20: =F20*H20 -> 6938.28 | L20: =F20*I20 -> 9251.04 | M20: telha metálica termoacústica, 12 m² por abrigo
A21: 3. Piso, banco e acessibilidade | B21: 94995 | C21: SINAPI composição | D21: EXECUÇÃO DE PASSEIO (CALÇADA) OU PISO DE CONCRETO COM CONCRETO MOLDADO IN LOCO, USINADO, ACABAMENTO CONVENCIONAL, ESPESSURA 8 CM, ARMADO. AF_08/2022 | E21: M2 | F21: 103.21 | G21: 24 | H21: 36 | I21: 48 | J21: =F21*G21 -> 2477.04 | K21: =F21*H21 -> 3715.56 | L21: =F21*I21 -> 4954.08 | M21: piso de concreto 8 cm, 12 m² por abrigo
A22: 3. Piso, banco e acessibilidade | B22: 103669 | C22: SINAPI composição | D22: CONCRETAGEM DE PILARES, FCK = 25 MPA, COM USO DE BALDES - LANÇAMENTO, ADENSAMENTO E ACABAMENTO. AF_02/2022 | E22: M3 | F22: 1194.23 | G22: 0.6 | H22: 0.9 | I22: 1.2 | J22: =F22*G22 -> 716.538 | K22: =F22*H22 -> 1074.807 | L22: =F22*I22 -> 1433.076 | M22: banco em concreto, 0,3 m³ por abrigo
A23: 3. Piso, banco e acessibilidade | B23: 104658 | C23: SINAPI composição | D23: PISO PODOTÁTIL DE ALERTA OU DIRECIONAL, DE CONCRETO, ASSENTADO SOBRE ARGAMASSA. AF_03/2024 | E23: M2 | F23: 171.51 | G23: 8 | H23: 12 | I23: 16 | J23: =F23*G23 -> 1372.08 | K23: =F23*H23 -> 2058.12 | L23: =F23*I23 -> 2744.16 | M23: piso podotátil, 4 m² por abrigo
I24: Custo direto | J24: =SUM(J16:J23) -> 20403.546 | K24: =SUM(K16:K23) -> 30605.319 | L24: =SUM(L16:L23) -> 40807.092
I25: BDI | J25: =PARAMETROS!$B$6 -> 0.2034 | K25: =PARAMETROS!$C$6 -> 0.2212 | L25: =PARAMETROS!$D$6 -> 0.25
I26: Contingência | J26: =PARAMETROS!$B$8 -> 0.05 | K26: =PARAMETROS!$C$8 -> 0.1 | L26: =PARAMETROS!$D$8 -> 0.15
I27: Fator regional | J27: =PARAMETROS!$B$9 -> 1 | K27: =PARAMETROS!$C$9 -> 1 | L27: =PARAMETROS!$D$9 -> 1.1
I28: TOTAL ESTIMADO (R$) | J28: =J24*(1+J25)*(1+J26)*J27 -> 25781.309 | K28: =K24*(1+K25)*(1+K26)*K27 -> 41112.737 | L28: =L24*(1+L25)*(1+L26)*L27 -> 64526.214
A30: Estimativa preliminar paramétrica, não vinculante, para planejamento orçamentário. Não substitui o orçamento detalhado do projeto. PROVISORIO - aguarda aprovacao

Sheet 21_TCM_03973e23
A1: 21 - Creche Municipal Padrão de 6 salas da Rua Genésio Santos (Teotônio Vilela)
A2: PROVISORIO - aguarda aprovacao
A4: Grupo-objeto | B4: TCM_03973e23-CRECHE_TEOTONIO_VILELA
A5: Levantamento | B5: MP
A6: Origem | B6: TCM
A7: Categoria | B7: escola/creche
A8: Local | B8: Rua Genésio Santos, s/n, bairro Teotônio Vilela
A9: Fonte das quantidades | B9: documento (6 salas) + demanda-tipo
A10: Preços | B10: SINAPI/CAIXA ref. 08/2026, BA, não desonerado (código de cada item na coluna B)
A11: BDI aplicado | B11: edificações (Acórdão 2.622/2013, construção de edifícios)
A12: Premissas | B12: Creche padrão de 6 salas (documento) com 700/800/900 m² e remanescente de 30/50/70% (premissa).
B13: Situação atual da obra e do contrato não informada (último documento de 2023).
B14: Edificação térrea-tipo por m²: concreto 0,12 m³/m², aço 10 kg/m², fôrma 1,1 m²/m², alvenaria 1,5 m²/m², cobertura em telha cerâmica (1,25 m²/m²), forro de PVC, piso cerâmico, 1 porta a cada 15 m², janelas 0,15 m²/m², instalações simplificadas.
A16: Macroetapa | B16: Código SINAPI | C16: Tipo | D16: Descrição | E16: Unid. | F16: Preço unit. (R$) | G16: Qtd. mínimo | H16: Qtd. provável | I16: Qtd. máximo | J16: Total mínimo (R$) | K16: Total provável (R$) | L16: Total máximo (R$) | M16: Memória de cálculo
A17: 1. Serviços preliminares | B17: 99059 | C17: SINAPI composição | D17: LOCAÇÃO CONVENCIONAL DE OBRA, UTILIZANDO GABARITO DE TÁBUAS CORRIDAS PONTALETADAS A CADA 2,00M - 2 UTILIZAÇÕES. AF_03/2024 | E17: M | F17: 75.94 | G17: 52.5 | H17: 100 | I17: 157.5 | J17: =F17*G17 -> 3986.85 | K17: =F17*H17 -> 7594 | L17: =F17*I17 -> 11960.55 | M17: locação de obra, 0,25 m de gabarito por m²
A18: 2. Fundação e estrutura | B18: 93358 | C18: SINAPI composição | D18: ESCAVAÇÃO MANUAL DE VALA. AF_09/2024 | E18: M3 | F18: 103.4 | G18: 16.8 | H18: 32 | I18: 50.4 | J18: =F18*G18 -> 1737.12 | K18: =F18*H18 -> 3308.8 | L18: =F18*I18 -> 5211.36 | M18: escavação manual, 0,08 m³/m²
A19: 2. Fundação e estrutura | B19: 103672 | C19: SINAPI composição | D19: CONCRETAGEM DE PILARES, FCK = 25 MPA, COM USO DE BOMBA - LANÇAMENTO, ADENSAMENTO E ACABAMENTO. AF_02/2022_PS | E19: M3 | F19: 828.32 | G19: 25.2 | H19: 48 | I19: 75.6 | J19: =F19*G19 -> 20873.664 | K19: =F19*H19 -> 39759.36 | L19: =F19*I19 -> 62620.992 | M19: concreto estrutural fck 25 MPa, 0,12 m³/m²
A20: 2. Fundação e estrutura | B20: 92762 | C20: SINAPI composição | D20: ARMAÇÃO DE PILAR OU VIGA DE ESTRUTURA CONVENCIONAL DE CONCRETO ARMADO UTILIZANDO AÇO CA-50 DE 10,0 MM - MONTAGEM. AF_06/2022 | E20: KG | F20: 10.41 | G20: 2100 | H20: 4000 | I20: 6300 | J20: =F20*G20 -> 21861 | K20: =F20*H20 -> 41640 | L20: =F20*I20 -> 65583 | M20: armação CA-50, 10 kg/m²
A21: 2. Fundação e estrutura | B21: 92421 | C21: SINAPI composição | D21: MONTAGEM E DESMONTAGEM DE FÔRMA DE PILARES RETANGULARES E ESTRUTURAS SIMILARES, PÉ-DIREITO DUPLO, EM CHAPA DE MADEIRA COMPENSADA RESINADA, 4 UTILIZAÇÕES. AF_09/2020 | E21: M2 | F21: 122.64 | G21: 231 | H21: 440 | I21: 693 | J21: =F21*G21 -> 28329.84 | K21: =F21*H21 -> 53961.6 | L21: =F21*I21 -> 84989.52 | M21: fôrmas, 1,1 m²/m²
A22: 3. Vedação e revestimentos | B22: 103328 | C22: SINAPI composição | D22: ALVENARIA DE VEDAÇÃO DE BLOCOS CERÂMICOS FURADOS NA HORIZONTAL DE 9X19X19 CM (ESPESSURA 9 CM) E ARGAMASSA DE ASSENTAMENTO COM PREPARO EM BETONEIRA. AF_08/2026 | E22: M2 | F22: 119.54 | G22: 315 | H22: 600 | I22: 945 | J22: =F22*G22 -> 37655.1 | K22: =F22*H22 -> 71724 | L22: =F22*I22 -> 112965.3 | M22: alvenaria de vedação, 1,5 m²/m²
A23: 3. Vedação e revestimentos | B23: 87879 | C23: SINAPI composição | D23: CHAPISCO APLICADO EM ALVENARIAS E ESTRUTURAS DE CONCRETO INTERNAS, COM COLHER DE PEDREIRO. ARGAMASSA TRAÇO 1:3 COM PREPARO EM BETONEIRA 400L. AF_10/2022 | E23: M2 | F23: 6.03 | G23: 630 | H23: 1200 | I23: 1890 | J23: =F23*G23 -> 3798.9 | K23: =F23*H23 -> 7236 | L23: =F23*I23 -> 11396.7 | M23: chapisco nas duas faces
A24: 3. Vedação e revestimentos | B24: 104958 | C24: SINAPI composição | D24: MASSA ÚNICA, EM ARGAMASSA TRAÇO 1:2:8 PREPARO MECÂNICO, APLICADA MANUALMENTE EM PAREDES INTERNAS DE AMBIENTES COM ÁREA MAIOR QUE 10M², E = 10MM, COM TALISCAS. AF_03/2024 | E24: M2 | F24: 31.79 | G24: 504 | H24: 960 | I24: 1512 | J24: =F24*G24 -> 16022.16 | K24: =F24*H24 -> 30518.4 | L24: =F24*I24 -> 48066.48 | M24: massa única interna
A25: 3. Vedação e revestimentos | B25: 104235 | C25: SINAPI composição | D25: EMBOÇO OU MASSA ÚNICA EM ARGAMASSA INDUSTRIALIZADA, PREPARO MECÂNICA E APLICAÇÃO COM EQUIPAMENTO DE MISTURA E PROJEÇÃO DE 1,5 M3/H DE ARGAMASSA EM PANOS DE FACHADA SEM PRESENÇA DE VÃOS, ESPESSURA DE 25 MM, ACESSO POR ANDAIME. AF_08/2022 | E25: M2 | F25: 83.28 | G25: 126 | H25: 240 | I25: 378 | J25: =F25*G25 -> 10493.28 | K25: =F25*H25 -> 19987.2 | L25: =F25*I25 -> 31479.84 | M25: emboço externo
A26: 3. Vedação e revestimentos | B26: 87265 | C26: SINAPI composição | D26: REVESTIMENTO CERÂMICO PARA PAREDES INTERNAS COM PLACAS TIPO ESMALTADA DE DIMENSÕES 20X20 CM APLICADAS NA ALTURA INTEIRA DAS PAREDES. AF_02/2023_PE | E26: M2 | F26: 59.3 | G26: 63 | H26: 120 | I26: 189 | J26: =F26*G26 -> 3735.9 | K26: =F26*H26 -> 7116 | L26: =F26*I26 -> 11207.7 | M26: revestimento cerâmico em áreas molhadas
A27: 4. Pisos | B27: 95241 | C27: SINAPI composição | D27: LASTRO DE CONCRETO MAGRO, APLICADO EM PISOS, LAJES SOBRE SOLO OU RADIERS, ESPESSURA DE 5 CM. AF_01/2024 | E27: M2 | F27: 48.41 | G27: 210 | H27: 400 | I27: 630 | J27: =F27*G27 -> 10166.1 | K27: =F27*H27 -> 19364 | L27: =F27*I27 -> 30498.3 | M27: lastro de concreto magro 5 cm
A28: 4. Pisos | B28: 98680 | C28: SINAPI composição | D28: PISO CIMENTADO, TRAÇO 1:5 (CIMENTO E AREIA), ACABAMENTO LISO, ESPESSURA 3,0 CM, PREPARO MECÂNICO DA ARGAMASSA. AF_02/2026 | E28: M2 | F28: 58.19 | G28: 210 | H28: 400 | I28: 630 | J28: =F28*G28 -> 12219.9 | K28: =F28*H28 -> 23276 | L28: =F28*I28 -> 36659.7 | M28: regularização/contrapiso cimentado 3 cm
... A50: 10. Prevenção contra incêndio | B50: 37556 | C50: SINAPI insumo | D50: PLACA DE SINALIZACAO DE SEGURANCA CONTRA INCENDIO, FOTOLUMINESCENTE, QUADRADA, *20 X 20* CM, EM PVC *2* MM ANTI-CHAMAS (SIMBOLOS, CORES E PICTOGRAMAS CONFORME NBR 16820) | E50: UN | F50: 20.47 | G50: 4.2 | H50: 8 | I50: 12.6 | J50: =F50*G50 -> 85.974 | K50: =F50*H50 -> 163.76 | L50: =F50*I50 -> 257.922 | M50: placa fotoluminescente de rota de fuga
I51: Custo direto | J51: =SUM(J17:J50) -> 305423.38 | K51: =SUM(K17:K50) -> 581577.22 | L51: =SUM(L17:L50) -> 915970.15
I52: BDI | J52: =PARAMETROS!$B$6 -> 0.2034 | K52: =PARAMETROS!$C$6 -> 0.2212 | L52: =PARAMETROS!$D$6 -> 0.25
I53: Contingência | J53: =PARAMETROS!$B$8 -> 0.05 | K53: =PARAMETROS!$C$8 -> 0.1 | L53: =PARAMETROS!$D$8 -> 0.15
I54: Fator regional | J54: =PARAMETROS!$B$9 -> 1 | K54: =PARAMETROS!$C$9 -> 1 | L54: =PARAMETROS!$D$9 -> 1.1
I55: TOTAL ESTIMADO (R$) | J55: =J51*(1+J52)*(1+J53)*J54 -> 385923.81 | K55: =K51*(1+K52)*(1+K53)*K54 -> 781244.32 | L55: =L51*(1+L52)*(1+L53)*L54 -> 1448377.8
A57: Estimativa preliminar paramétrica, não vinculante, para planejamento orçamentário. Não substitui o orçamento detalhado do projeto. PROVISORIO - aguarda aprovacao

Sheet 22_SN_CAMPO_DO_RODAO
A1: 22 - Requalificação e ampliação do Complexo Esportivo Campo do Rodão (Teotônio Vilela)
A2: PROVISORIO - aguarda aprovacao
A4: Grupo-objeto | B4: SN_COMPLEXO_ESPORTIVO_CAMPO_DO_RODAO
A5: Levantamento | B5: MP
A6: Origem | B6: outro
A7: Categoria | B7: quadra/esporte
A8: Local | B8: Complexo Esportivo Campo do Rodão, bairro Teotônio Vilela
A9: Fonte das quantidades | B9: demanda-tipo (campo-tipo)
A10: Preços | B10: SINAPI/CAIXA ref. 08/2026, BA, não desonerado (código de cada item na coluna B)
A11: BDI aplicado | B11: edificações (Acórdão 2.622/2013, construção de edifícios)
A12: Premissas | B12: Campo de futebol de 70x45 / 90x60 / 100x64 m com gramado, drenagem, alambrado, calçadas e vestiário de 60/80/120 m².
B13: Iluminação esportiva representada por refletores do SINAPI; o projeto luminotécnico pode elevar o custo.
A15: Macroetapa | B15: Código SINAPI | C15: Tipo | D15: Descrição | E15: Unid. | F15: Preço unit. (R$) | G15: Qtd. mínimo | H15: Qtd. provável | I15: Qtd. máximo | J15: Total mínimo (R$) | K15: Total provável (R$) | L15: Total máximo (R$) | M15: Memória de cálculo
A16: 1. Serviços preliminares | B16: 103689 | C16: SINAPI composição | D16: FORNECIMENTO E INSTALAÇÃO DE PLACA DE OBRA COM CHAPA GALVANIZADA E ESTRUTURA DE MADEIRA. AF_03/2022_PS | E16: M2 | F16: 454.97 | G16: 6 | H16: 6 | I16: 6 | J16: =F16*G16 -> 2729.82 | K16: =F16*H16 -> 2729.82 | L16: =F16*I16 -> 2729.82 | M16: placa de obra
A17: 2. Campo | B17: 100576 | C17: SINAPI composição | D17: REGULARIZAÇÃO E COMPACTAÇÃO DE SUBLEITO DE SOLO PREDOMINANTEMENTE ARGILOSO, PARA OBRAS DE CONSTRUÇÃO DE PAVIMENTOS. AF_09/2024 | E17: M2 | F17: 3.35 | G17: 3150 | H17: 0 | I17: 0 | J17: =F17*G17 -> 10552.5 | K17: =F17*H17 -> 0 | L17: =F17*I17 -> 0 | M17: regularização do campo 70 m x 45 m
A18: 2. Campo | B18: 106543 | C18: SINAPI composição | D18: ASSENTAMENTO DE TUBO DRENO DE PEAD CORRUGADO EM GEOCOMPOSTO, DN 160 MM - FORNECIMENTO E INSTALAÇÃO. AF_01/2026 | E18: M | F18: 22.2 | G18: 630 | H18: 1080 | I18: 1280 | J18: =F18*G18 -> 13986 | K18: =F18*H18 -> 23976 | L18: =F18*I18 -> 28416 | M18: drenos DN 160 mm a cada 5 m
A19: 2. Campo | B19: 98504 | C19: SINAPI composição | D19: PLANTIO DE GRAMA BATATAIS EM PLACAS. AF_07/2024 | E19: M2 | F19: 15.04 | G19: 3150 | H19: 5400 | I19: 6400 | J19: =F19*G19 -> 47376 | K19: =F19*H19 -> 81216 | L19: =F19*I19 -> 96256 | M19: gramado em placas
A20: 3. Fechamento e acessos | B20: 98522 | C20: SINAPI composição | D20: ALAMBRADO EM MOURÕES DE CONCRETO, COM TELA DE ARAME GALVANIZADO (INCLUSIVE MURETA EM CONCRETO). AF_12/2025 | E20: M | F20: 172.74 | G20: 250 | H20: 320 | I20: 348 | J20: =F20*G20 -> 43185 | K20: =F20*H20 -> 55276.8 | L20: =F20*I20 -> 60113.52 | M20: alambrado com mourões de concreto no perímetro + 20 m
A21: 3. Fechamento e acessos | B21: 94992 | C21: SINAPI composição | D21: EXECUÇÃO DE PASSEIO (CALÇADA) OU PISO DE CONCRETO COM CONCRETO MOLDADO IN LOCO, FEITO EM OBRA, ACABAMENTO CONVENCIONAL, ESPESSURA 6 CM, ARMADO. AF_08/2022 | E21: M2 | F21: 91.17 | G21: 150 | H21: 200 | I21: 300 | J21: =F21*G21 -> 13675.5 | K21: =F21*H21 -> 18234 | L21: =F21*I21 -> 27351 | M21: calçadas e acessos
A22: 3. Fechamento e acessos | B22: 39391 | C22: SINAPI insumo | D22: LUMINARIA LED REFLETOR RETANGULAR BIVOLT, LUZ BRANCA, 50 W | E22: UN | F22: 23.46 | G22: 20 | H22: 20 | I22: 20 | J22: =F22*G22 -> 469.2 | K22: =F22*H22 -> 469.2 | L22: =F22*I22 -> 469.2 | M22: refletores LED 50 W (insumo; iluminação esportiva a dimensionar)
A23: Vestiário - 1. Serviços preliminares | B23: 99059 | C23: SINAPI composição | D23: LOCAÇÃO CONVENCIONAL DE OBRA, UTILIZANDO GABARITO DE TÁBUAS CORRIDAS PONTALETADAS A CADA 2,00M - 2 UTILIZAÇÕES. AF_03/2024 | E23: M | F23: 75.94 | G23: 15 | H23: 20 | I23: 30 | J23: =F23*G23 -> 1139.1 | K23: =F23*H23 -> 1518.8 | L23: =F23*I23 -> 2278.2 | M23: locação de obra, 0,25 m de gabarito por m²
A24: Vestiário - 2. Fundação e estrutura | B24: 93358 | C24: SINAPI composição | D24: ESCAVAÇÃO MANUAL DE VALA. AF_09/2024 | E24: M3 | F24: 103.4 | G24: 4.8 | H24: 6.4 | I24: 9.6 | J24: =F24*G24 -> 496.32 | K24: =F24*H24 -> 661.76 | L24: =F24*I24 -> 992.64 | M24: escavação manual, 0,08 m³/m²
A25: Vestiário - 2. Fundação e estrutura | B25: 103672 | C25: SINAPI composição | D25: CONCRETAGEM DE PILARES, FCK = 25 MPA, COM USO DE BOMBA - LANÇAMENTO, ADENSAMENTO E ACABAMENTO. AF_02/2022_PS | E25: M3 | F25: 828.32 | G25: 7.2 | H25: 9.6 | I25: 14.4 | J25: =F25*G25 -> 5963.904 | K25: =F25*H25 -> 7951.872 | L25: =F25*I25 -> 11927.808 | M25: concreto estrutural fck 25 MPa, 0,12 m³/m²
A26: Vestiário - 2. Fundação e estrutura | B26: 92762 | C26: SINAPI composição | D26: ARMAÇÃO DE PILAR OU VIGA DE ESTRUTURA CONVENCIONAL DE CONCRETO ARMADO UTILIZANDO AÇO CA-50 DE 10,0 MM - MONTAGEM. AF_06/2022 | E26: KG | F26: 10.41 | G26: 600 | H26: 800 | I26: 1200 | J26: =F26*G26 -> 6246 | K26: =F26*H26 -> 8328 | L26: =F26*I26 -> 12492 | M26: armação CA-50, 10 kg/m²
A27: Vestiário - 2. Fundação e estrutura | B27: 92421 | C27: SINAPI composição | D27: MONTAGEM E DESMONTAGEM DE FÔRMA DE PILARES RETANGULARES E ESTRUTURAS SIMILARES, PÉ-DIREITO DUPLO, EM CHAPA DE MADEIRA COMPENSADA RESINADA, 4 UTILIZAÇÕES. AF_09/2020 | E27: M2 | F27: 122.64 | G27: 66 | H27: 88 | I27: 132 | J27: =F27*G27 -> 8094.24 | K27: =F27*H27 -> 10792.32 | L27: =F27*I27 -> 16188.48 | M27: fôrmas, 1,1 m²/m²
... A58: 2. Campo | B58: 100576 | C58: SINAPI composição | D58: REGULARIZAÇÃO E COMPACTAÇÃO DE SUBLEITO DE SOLO PREDOMINANTEMENTE ARGILOSO, PARA OBRAS DE CONSTRUÇÃO DE PAVIMENTOS. AF_09/2024 | E58: M2 | F58: 3.35 | G58: 0 | H58: 0 | I58: 6400 | J58: =F58*G58 -> 0 | K58: =F58*H58 -> 0 | L58: =F58*I58 -> 21440 | M58: regularização do campo 100 m x 64 m
I59: Custo direto | J59: =SUM(J16:J58) -> 220534.11 | K59: =SUM(K16:K58) -> 317368.84 | L59: =SUM(L16:L58) -> 411798.76
I60: BDI | J60: =PARAMETROS!$B$6 -> 0.2034 | K60: =PARAMETROS!$C$6 -> 0.2212 | L60: =PARAMETROS!$D$6 -> 0.25
I61: Contingência | J61: =PARAMETROS!$B$8 -> 0.05 | K61: =PARAMETROS!$C$8 -> 0.1 | L61: =PARAMETROS!$D$8 -> 0.15
I62: Fator regional | J62: =PARAMETROS!$B$9 -> 1 | K62: =PARAMETROS!$C$9 -> 1 | L62: =PARAMETROS!$D$9 -> 1.1
I63: TOTAL ESTIMADO (R$) | J63: =J59*(1+J60)*(1+J61)*J62 -> 278660.29 | K63: =K59*(1+K60)*(1+K61)*K62 -> 426327.92 | L63: =L59*(1+L60)*(1+L61)*L62 -> 651156.79
A65: Estimativa preliminar paramétrica, não vinculante, para planejamento orçamentário. Não substitui o orçamento detalhado do projeto. PROVISORIO - aguarda aprovacao

Sheet 23_TJBA_0001568-38.2011
A1: 23 - Infraestrutura básica do Loteamento Santa Cruz (cumprimento de sentença)
A2: PROVISORIO - aguarda aprovacao
A4: Grupo-objeto | B4: JUSTICA_0001568-38.2011.8.05.0103
A5: Levantamento | B5: Justiça
A6: Origem | B6: Justiça
A7: Categoria | B7: drenagem+pavimentação
A8: Local | B8: Loteamento Santa Cruz
A9: Fonte das quantidades | B9: demanda-tipo (extensão de vias a confirmar)
A10: Preços | B10: SINAPI/CAIXA ref. 08/2026, BA, não desonerado (código de cada item na coluna B)
A11: BDI aplicado | B11: vias e drenagem (Acórdão 2.622/2013, rodovias e ferrovias)
A12: Premissas | B12: Sentença: infraestrutura básica do Loteamento Santa Cruz (drenagem, esgoto, água, iluminação, pavimentação e meio-fio).
B13: Extensão total de vias de 600/1.000/1.600 m (premissa; a poligonal da sentença não consta do pacote).
B14: Infraestrutura básica por metro de via: via-tipo (drenagem, pavimentação, meio-fio, sarjeta, passeio e sinalização) + rede de água PVC DN 50 + rede de esgoto PVC DN 150 com PV a cada 60 m + luminária LED a cada 35 m em poste existente.
B15: Rua-tipo: pista 5/6/7 m, passeios 1,2/1,5/2,0 m, base+sub-base 15/20/30 cm, CBUQ 4/5/5 cm, rede DN 600/600/800 mm, PV a cada 40 m, 2 bocas de lobo a cada 40 m, DMT da brita 20/20/40 km e do CBUQ 30/30/60 km (mín/prov/máx).
B16: Ligações domiciliares, postes novos, estação elevatória e tratamento de esgoto não estão incluídos; parte da água e do esgoto pode caber à concessionária.
A18: Macroetapa | B18: Código SINAPI | C18: Tipo | D18: Descrição | E18: Unid. | F18: Preço unit. (R$) | G18: Qtd. mínimo | H18: Qtd. provável | I18: Qtd. máximo | J18: Total mínimo (R$) | K18: Total provável (R$) | L18: Total máximo (R$) | M18: Memória de cálculo
A19: 1. Serviços preliminares | B19: 103689 | C19: SINAPI composição | D19: FORNECIMENTO E INSTALAÇÃO DE PLACA DE OBRA COM CHAPA GALVANIZADA E ESTRUTURA DE MADEIRA. AF_03/2022_PS | E19: M2 | F19: 454.97 | G19: 6 | H19: 6 | I19: 6 | J19: =F19*G19 -> 2729.82 | K19: =F19*H19 -> 2729.82 | L19: =F19*I19 -> 2729.82 | M19: placa de obra 3 m x 2 m
A20: 1. Serviços preliminares | B20: 98525 | C20: SINAPI composição | D20: LIMPEZA MECANIZADA DE CAMADA VEGETAL, VEGETAÇÃO E PEQUENAS ÁRVORES (DIÂMETRO DE TRONCO MENOR QUE 0,20 M), COM TRATOR DE ESTEIRAS. AF_03/2024 | E20: M2 | F20: 0.76 | G20: 4440 | H20: 9000 | I20: 17600 | J20: =F20*G20 -> 3374.4 | K20: =F20*H20 -> 6840 | L20: =F20*I20 -> 13376 | M20: limpeza da faixa: L x (pista + 2 passeios)
A21: 2. Drenagem | B21: 90082 | C21: SINAPI composição | D21: ESCAVAÇÃO MECANIZADA DE VALA COM PROF. ATÉ 1,5 M (MÉDIA MONTANTE E JUSANTE/UMA COMPOSIÇÃO POR TRECHO), ESCAVADEIRA (0,8 M3), LARG. DE 1,5 M A 2,5 M, EM SOLO DE 1A CATEGORIA, EM LOCAIS COM ALTO NÍVEL DE INTERFERÊNCIA. AF_09/2024 | E21: M3 | F21: 10.58 | G21: 1152 | H21: 0 | I21: 0 | J21: =F21*G21 -> 12188.16 | K21: =F21*H21 -> 0 | L21: =F21*I21 -> 0 | M21: vala 1.20 m x 1.60 m x L 600 m
A22: 2. Drenagem | B22: 92212 | C22: SINAPI composição | D22: TUBO DE CONCRETO PARA REDES COLETORAS DE ÁGUAS PLUVIAIS, DIÂMETRO DE 600 MM, JUNTA RÍGIDA, INSTALADO EM LOCAL COM BAIXO NÍVEL DE INTERFERÊNCIAS - FORNECIMENTO E ASSENTAMENTO. AF_03/2024 | E22: M | F22: 351.67 | G22: 600 | H22: 1000 | I22: 0 | J22: =F22*G22 -> 211002 | K22: =F22*H22 -> 351670 | L22: =F22*I22 -> 0 | M22: rede DN 600 mm ao longo de L
A23: 2. Drenagem | B23: 93369 | C23: SINAPI composição | D23: REATERRO MECANIZADO DE VALA COM ESCAVADEIRA HIDRÁULICA (CAPACIDADE DA CAÇAMBA: 0,8 M³/POTÊNCIA: 111 HP), LARGURA 1,5 A 2,5 M, PROFUNDIDADE 1,5 A 3,0 M, COM SOLO (SEM SUBSTITUIÇÃO) DE 1ª CATEGORIA, COM COMPACTADOR DE SOLOS DE PERCUSSÃO. AF_08/2023 | E23: M3 | F23: 20.26 | G23: 921.09 | H23: 1535.15 | I23: 3014.12 | J23: =F23*G23 -> 18661.283 | K23: =F23*H23 -> 31102.139 | L23: =F23*I23 -> 61066.071 | M23: volume da vala - volume externo do tubo
A24: 2. Drenagem | B24: 99285 | C24: SINAPI composição | D24: BASE PARA POÇO DE VISITA CIRCULAR PARA DRENAGEM, EM CONCRETO PRÉ-MOLDADO, DIÂMETRO INTERNO = 1,0 M, PROFUNDIDADE = 1,35 M, EXCLUINDO TAMPÃO. AF_05/2018 | E24: UN | F24: 1613.82 | G24: 16 | H24: 26 | I24: 0 | J24: =F24*G24 -> 25821.12 | K24: =F24*H24 -> 41959.32 | L24: =F24*I24 -> 0 | M24: PV a cada 40 m + 1
A25: 2. Drenagem | B25: 99288 | C25: SINAPI composição | D25: ACRÉSCIMO PARA POÇO DE VISITA CIRCULAR PARA DRENAGEM, EM CONCRETO PRÉ-MOLDADO, DIÂMETRO INTERNO = 1 M. AF_12/2020 | E25: M | F25: 634.89 | G25: 8 | H25: 13 | I25: 0 | J25: =F25*G25 -> 5079.12 | K25: =F25*H25 -> 8253.57 | L25: =F25*I25 -> 0 | M25: acréscimo médio de 0,5 m de profundidade por PV
A26: 2. Drenagem | B26: 97956 | C26: SINAPI composição | D26: CAIXA PARA BOCA DE LOBO SIMPLES RETANGULAR, EM ALVENARIA COM BLOCOS DE CONCRETO, DIMENSÕES INTERNAS: 0,6X1X1,2 M. AF_12/2020 | E26: UN | F26: 1812.94 | G26: 30 | H26: 50 | I26: 80 | J26: =F26*G26 -> 54388.2 | K26: =F26*H26 -> 90647 | L26: =F26*I26 -> 145035.2 | M26: boca de lobo simples, 2 a cada 40 m
A27: 2. Drenagem | B27: 92210 | C27: SINAPI composição | D27: TUBO DE CONCRETO PARA REDES COLETORAS DE ÁGUAS PLUVIAIS, DIÂMETRO DE 400 MM, JUNTA RÍGIDA, INSTALADO EM LOCAL COM BAIXO NÍVEL DE INTERFERÊNCIAS - FORNECIMENTO E ASSENTAMENTO. AF_03/2024 | E27: M | F27: 188.74 | G27: 120 | H27: 200 | I27: 320 | J27: =F27*G27 -> 22648.8 | K27: =F27*H27 -> 37748 | L27: =F27*I27 -> 60396.8 | M27: ligação BL-PV em DN 400 mm, 4 m por boca de lobo
A28: 2. Drenagem | B28: 100982 | C28: SINAPI composição | D28: CARGA, MANOBRA E DESCARGA DE ENTULHO EM CAMINHÃO BASCULANTE 10 M³ - CARGA COM ESCAVADEIRA HIDRÁULICA (CAÇAMBA DE 0,80 M³ / 111 HP) E DESCARGA LIVRE (UNIDADE: M3). AF_02/2026 | E28: M3 | F28: 9.88 | G28: 230.91 | H28: 384.85 | I28: 1017.88 | J28: =F28*G28 -> 2281.3908 | K28: =F28*H28 -> 3802.318 | L28: =F28*I28 -> 10056.654 | M28: carga do solo excedente (volume do tubo)
A29: 2. Drenagem | B29: 95875 | C29: SINAPI composição | D29: TRANSPORTE COM CAMINHÃO BASCULANTE DE 10 M³, EM VIA URBANA PAVIMENTADA, DMT ATÉ 30 KM (UNIDADE: M3XKM). AF_02/2026 | E29: M3XKM | F29: 2.83 | G29: 2309.07 | H29: 3848.45 | I29: 10178.76 | J29: =F29*G29 -> 6534.6681 | K29: =F29*H29 -> 10891.113 | L29: =F29*I29 -> 28805.891 | M29: transporte do excedente, DMT 10 km
A30: 3. Pavimentação | B30: 100576 | C30: SINAPI composição | D30: REGULARIZAÇÃO E COMPACTAÇÃO DE SUBLEITO DE SOLO PREDOMINANTEMENTE ARGILOSO, PARA OBRAS DE CONSTRUÇÃO DE PAVIMENTOS. AF_09/2024 | E30: M2 | F30: 3.35 | G30: 3000 | H30: 6000 | I30: 11200 | J30: =F30*G30 -> 10050 | K30: =F30*H30 -> 20100 | L30: =F30*I30 -> 37520 | M30: regularização do subleito: L x pista
... A59: 3. Pavimentação | B59: 95875 | C59: SINAPI composição | D59: TRANSPORTE COM CAMINHÃO BASCULANTE DE 10 M³, EM VIA URBANA PAVIMENTADA, DMT ATÉ 30 KM (UNIDADE: M3XKM). AF_02/2026 | E59: M3XKM | F59: 2.83 | G59: 0 | H59: 0 | I59: 33600 | J59: =F59*G59 -> 0 | K59: =F59*H59 -> 0 | L59: =F59*I59 -> 95088 | M59: transporte do CBUQ, DMT 60 km
I60: Custo direto | J60: =SUM(J19:J59) -> 1074122.7 | K60: =SUM(K19:K59) -> 2138960.3 | L60: =SUM(L19:L59) -> 4742743.7
I61: BDI | J61: =PARAMETROS!$B$7 -> 0.196 | K61: =PARAMETROS!$C$7 -> 0.2097 | L61: =PARAMETROS!$D$7 -> 0.2423
I62: Contingência | J62: =PARAMETROS!$B$8 -> 0.05 | K62: =PARAMETROS!$C$8 -> 0.1 | L62: =PARAMETROS!$D$8 -> 0.15
I63: Fator regional | J63: =PARAMETROS!$B$9 -> 1 | K63: =PARAMETROS!$C$9 -> 1 | L63: =PARAMETROS!$D$9 -> 1.1
I64: TOTAL ESTIMADO (R$) | J64: =J60*(1+J61)*(1+J62)*J63 -> 1348883.2 | K64: =K60*(1+K61)*(1+K62)*K63 -> 2846250.3 | L64: =L60*(1+L61)*(1+L62)*L63 -> 7453266.7
A66: Estimativa preliminar paramétrica, não vinculante, para planejamento orçamentário. Não substitui o orçamento detalhado do projeto. PROVISORIO - aguarda aprovacao

Sheet 24_TJBA_8007670-17.2023
A1: 24 - Estabilização de encosta da Ladeira Júlio Bagana / Rua Rio Almada (Tapera)
A2: PROVISORIO - aguarda aprovacao
A4: Grupo-objeto | B4: JUSTICA_8007670-17.2023.8.05.0103
A5: Levantamento | B5: Justiça
A6: Origem | B6: Justiça
A7: Categoria | B7: encosta/contenção
A8: Local | B8: Ladeira Júlio Bagana (Rua Rio Almada), bairro Tapera
A9: Fonte das quantidades | B9: demanda-tipo (área da encosta a confirmar)
A10: Preços | B10: SINAPI/CAIXA ref. 08/2026, BA, não desonerado (código de cada item na coluna B)
A11: BDI aplicado | B11: edificações (Acórdão 2.622/2013, construção de edifícios)
A12: Premissas | B12: Estabilização de encosta da Ladeira Júlio Bagana / Rua Rio Almada (Tapera); obra paralisada e contrato anterior extinto.
B13: Face de 600/1.000/1.400 m² (premissa). O levantamento técnico em curso deve indicar o remanescente: parte da obra pode já ter sido executada.
B14: Solução-tipo: solo grampeado com concreto projetado e drenagem; grampos 2,0/1,5/1,25 m com 6/8/12 m; concreto 10/10/15 cm.
B15: Recuperação do pavimento da ladeira não está incluída.
A17: Macroetapa | B17: Código SINAPI | C17: Tipo | D17: Descrição | E17: Unid. | F17: Preço unit. (R$) | G17: Qtd. mínimo | H17: Qtd. provável | I17: Qtd. máximo | J17: Total mínimo (R$) | K17: Total provável (R$) | L17: Total máximo (R$) | M17: Memória de cálculo
A18: 1. Serviços preliminares | B18: 103689 | C18: SINAPI composição | D18: FORNECIMENTO E INSTALAÇÃO DE PLACA DE OBRA COM CHAPA GALVANIZADA E ESTRUTURA DE MADEIRA. AF_03/2022_PS | E18: M2 | F18: 454.97 | G18: 6 | H18: 6 | I18: 6 | J18: =F18*G18 -> 2729.82 | K18: =F18*H18 -> 2729.82 | L18: =F18*I18 -> 2729.82 | M18: placa de obra
A19: 1. Serviços preliminares | B19: 98525 | C19: SINAPI composição | D19: LIMPEZA MECANIZADA DE CAMADA VEGETAL, VEGETAÇÃO E PEQUENAS ÁRVORES (DIÂMETRO DE TRONCO MENOR QUE 0,20 M), COM TRATOR DE ESTEIRAS. AF_03/2024 | E19: M2 | F19: 0.76 | G19: 780 | H19: 1300 | I19: 1820 | J19: =F19*G19 -> 592.8 | K19: =F19*H19 -> 988 | L19: =F19*I19 -> 1383.2 | M19: limpeza e supressão vegetal: face + 30% de entorno
A20: 2. Contenção | B20: 93957 | C20: SINAPI composição | D20: EXECUÇÃO DE GRAMPO PARA SOLO GRAMPEADO COM COMPRIMENTO MENOR OU IGUAL A 6 M, DIÂMETRO DE 10 CM, PERFURAÇÃO COM EQUIPAMENTO MANUAL E ARMADURA COM DIÂMETRO DE 20 MM. AF_07/2024 | E20: M | F20: 351.86 | G20: 900 | H20: 0 | I20: 0 | J20: =F20*G20 -> 316674 | K20: =F20*H20 -> 0 | L20: =F20*I20 -> 0 | M20: grampos em malha 2.0 m x 2.0 m, comprimento 6 m
A21: 2. Contenção | B21: 107269 | C21: SINAPI composição | D21: EXECUÇÃO DE CORTINA DE CONCRETO PROJETADO COM ESPESSURA DE 10 CM, FCK MAIOR OU IGUAL A 30 MPA. AF_07/2026 | E21: M2 | F21: 185.2 | G21: 600 | H21: 1000 | I21: 0 | J21: =F21*G21 -> 111120 | K21: =F21*H21 -> 185200 | L21: =F21*I21 -> 0 | M21: cortina de concreto projetado 10 cm na face
A22: 3. Drenagem da encosta | B22: 106545 | C22: SINAPI composição | D22: ASSENTAMENTO DE TUBO DRENO DE PEAD CORRUGADO EM GEOCOMPOSTO, DN 100 MM - FORNECIMENTO E INSTALAÇÃO. AF_01/2026 | E22: M | F22: 10.8 | G22: 360 | H22: 600 | I22: 840 | J22: =F22*G22 -> 3888 | K22: =F22*H22 -> 6480 | L22: =F22*I22 -> 9072 | M22: drenos sub-horizontais/barbacãs, 0,6 m por m² de face
A23: 3. Drenagem da encosta | B23: 102991 | C23: SINAPI composição | D23: CANALETA MEIA CANA PRÉ-MOLDADA DE CONCRETO (D = 40 CM) - FORNECIMENTO E INSTALAÇÃO. AF_05/2025 | E23: M | F23: 74.22 | G23: 150 | H23: 250 | I23: 350 | J23: =F23*G23 -> 11133 | K23: =F23*H23 -> 18555 | L23: =F23*I23 -> 25977 | M23: canaletas de crista e de pé (A / altura média 8 m, 2 linhas)
A24: 3. Drenagem da encosta | B24: 103933 | C24: SINAPI composição | D24: DESCIDA D'ÁGUA RÁPIDA (DAR 03), EM CONCRETO USINADO, FCK = 20 MPA, LANÇADO COM BOMBA, INCLUINDO ARMAÇÃO, MATERIAIS E FÔRMAS (2 UTILIZAÇÕES). AF_08/2022 | E24: M3 | F24: 1827.4 | G24: 7.5 | H24: 12.5 | I24: 17.5 | J24: =F24*G24 -> 13705.5 | K24: =F24*H24 -> 22842.5 | L24: =F24*I24 -> 31979.5 | M24: descidas d'água em concreto (0,0125 m³ por m² de face)
A25: 4. Proteção superficial | B25: 98504 | C25: SINAPI composição | D25: PLANTIO DE GRAMA BATATAIS EM PLACAS. AF_07/2024 | E25: M2 | F25: 15.04 | G25: 180 | H25: 300 | I25: 420 | J25: =F25*G25 -> 2707.2 | K25: =F25*H25 -> 4512 | L25: =F25*I25 -> 6316.8 | M25: grama em placas em 30% da área (bermas/entorno)
A26: 2. Contenção | B26: 93959 | C26: SINAPI composição | D26: EXECUÇÃO DE GRAMPO PARA SOLO GRAMPEADO COM COMPRIMENTO MAIOR QUE 6 M E MENOR OU IGUAL A 10 M, DIÂMETRO DE 10 CM, PERFURAÇÃO COM EQUIPAMENTO MANUAL E ARMADURA COM DIÂMETRO DE 20 MM. AF_07/2024 | E26: M | F26: 283.12 | G26: 0 | H26: 3555.56 | I26: 0 | J26: =F26*G26 -> 0 | K26: =F26*H26 -> 1006650.1 | L26: =F26*I26 -> 0 | M26: grampos em malha 1.5 m x 1.5 m, comprimento 8 m
A27: 2. Contenção | B27: 93961 | C27: SINAPI composição | D27: EXECUÇÃO DE GRAMPO PARA SOLO GRAMPEADO COM COMPRIMENTO MAIOR QUE 10 M, DIÂMETRO DE 10 CM, PERFURAÇÃO COM EQUIPAMENTO MANUAL E ARMADURA COM DIÂMETRO DE 20 MM. AF_07/2024 | E27: M | F27: 254.2 | G27: 0 | H27: 0 | I27: 10752 | J27: =F27*G27 -> 0 | K27: =F27*H27 -> 0 | L27: =F27*I27 -> 2733158.4 | M27: grampos em malha 1.25 m x 1.25 m, comprimento 12 m
A28: 2. Contenção | B28: 107270 | C28: SINAPI composição | D28: EXECUÇÃO DE CORTINA DE CONCRETO PROJETADO COM ESPESSURA DE 15 CM, FCK MAIOR OU IGUAL A 30 MPA. AF_07/2026 | E28: M2 | F28: 225.64 | G28: 0 | H28: 0 | I28: 1400 | J28: =F28*G28 -> 0 | K28: =F28*H28 -> 0 | L28: =F28*I28 -> 315896 | M28: cortina de concreto projetado 15 cm na face
I29: Custo direto | J29: =SUM(J18:J28) -> 462550.32 | K29: =SUM(K18:K28) -> 1247957.5 | L29: =SUM(L18:L28) -> 3126512.7
I30: BDI | J30: =PARAMETROS!$B$6 -> 0.2034 | K30: =PARAMETROS!$C$6 -> 0.2212 | L30: =PARAMETROS!$D$6 -> 0.25
I31: Contingência | J31: =PARAMETROS!$B$8 -> 0.05 | K31: =PARAMETROS!$C$8 -> 0.1 | L31: =PARAMETROS!$D$8 -> 0.15
I32: Fator regional | J32: =PARAMETROS!$B$9 -> 1 | K32: =PARAMETROS!$C$9 -> 1 | L32: =PARAMETROS!$D$9 -> 1.1
I33: TOTAL ESTIMADO (R$) | J33: =J29*(1+J30)*(1+J31)*J32 -> 584464.71 | K33: =K29*(1+K30)*(1+K31)*K32 -> 1676406.2 | L33: =L29*(1+L30)*(1+L31)*L32 -> 4943798.2
A35: Estimativa preliminar paramétrica, não vinculante, para planejamento orçamentário. Não substitui o orçamento detalhado do projeto. PROVISORIO - aguarda aprovacao

Sheet 25_TJBA_8008589-69.2024
A1: 25 - Unidade de Acolhimento Renascer: projeto de incêndio e reforma (Conquista)
A2: PROVISORIO - aguarda aprovacao
A4: Grupo-objeto | B4: JUSTICA_8008589-69.2024.8.05.0103
A5: Levantamento | B5: Justiça
A6: Origem | B6: Justiça
A7: Categoria | B7: outro
A8: Local | B8: Unidade de Acolhimento Renascer, Av. Princesa Isabel, nº 1554, bairro Conquista
A9: Fonte das quantidades | B9: demanda-tipo (área a confirmar)
A10: Preços | B10: SINAPI/CAIXA ref. 08/2026, BA, não desonerado (código de cada item na coluna B)
A11: BDI aplicado | B11: edificações (Acórdão 2.622/2013, construção de edifícios)
A12: Premissas | B12: Acordo homologado: reforma da Unidade de Acolhimento Renascer, projeto de segurança contra incêndio, saída de emergência e armários.
B13: Imóvel de 200/300/450 m² (premissa); 1/1/2 portas corta-fogo na rota de saída.
B14: Reforma-tipo por m²: fração refeita de cobertura/forro/piso/reboco/esquadrias/instalações = 20/20/10/10/10/20% (mín), 50/50/30/30/30/50% (prov) e 100/100/60/60/60/100% (máx); pintura integral; extintores, emergência e sinalização de rota de fuga.
B15: Projeto de segurança contra incêndio na contingência (projetos). Armários de alvenaria não estão incluídos.
A17: Macroetapa | B17: Código SINAPI | C17: Tipo | D17: Descrição | E17: Unid. | F17: Preço unit. (R$) | G17: Qtd. mínimo | H17: Qtd. provável | I17: Qtd. máximo | J17: Total mínimo (R$) | K17: Total provável (R$) | L17: Total máximo (R$) | M17: Memória de cálculo
A18: 1. Serviços preliminares | B18: 103689 | C18: SINAPI composição | D18: FORNECIMENTO E INSTALAÇÃO DE PLACA DE OBRA COM CHAPA GALVANIZADA E ESTRUTURA DE MADEIRA. AF_03/2022_PS | E18: M2 | F18: 454.97 | G18: 6 | H18: 6 | I18: 6 | J18: =F18*G18 -> 2729.82 | K18: =F18*H18 -> 2729.82 | L18: =F18*I18 -> 2729.82 | M18: placa de obra
A19: 2. Demolições e retiradas | B19: 97647 | C19: SINAPI composição | D19: REMOÇÃO DE TELHAS DE FIBROCIMENTO METÁLICA E CERÂMICA, DE FORMA MANUAL, SEM REAPROVEITAMENTO. AF_09/2023 | E19: M2 | F19: 4.43 | G19: 50 | H19: 187.5 | I19: 562.5 | J19: =F19*G19 -> 221.5 | K19: =F19*H19 -> 830.625 | L19: =F19*I19 -> 2491.875 | M19: remoção de telhas
A20: 2. Demolições e retiradas | B20: 97650 | C20: SINAPI composição | D20: REMOÇÃO DE TRAMA DE MADEIRA PARA COBERTURA, DE FORMA MANUAL, SEM REAPROVEITAMENTO. AF_09/2023 | E20: M2 | F20: 9.56 | G20: 25 | H20: 93.75 | I20: 281.25 | J20: =F20*G20 -> 239 | K20: =F20*H20 -> 896.25 | L20: =F20*I20 -> 2688.75 | M20: remoção de trama de madeira (metade da área refeita)
A21: 2. Demolições e retiradas | B21: 97640 | C21: SINAPI composição | D21: REMOÇÃO DE FORROS DE DRYWALL, PVC E FIBROMINERAL, DE FORMA MANUAL, SEM REAPROVEITAMENTO. AF_09/2023 | E21: M2 | F21: 2.58 | G21: 40 | H21: 150 | I21: 450 | J21: =F21*G21 -> 103.2 | K21: =F21*H21 -> 387 | L21: =F21*I21 -> 1161 | M21: remoção de forro
A22: 2. Demolições e retiradas | B22: 97634 | C22: SINAPI composição | D22: DEMOLIÇÃO DE REVESTIMENTO CERÂMICO, DE FORMA MECANIZADA COM MARTELETE, SEM REAPROVEITAMENTO. AF_09/2023 | E22: M2 | F22: 10.04 | G22: 20 | H22: 90 | I22: 270 | J22: =F22*G22 -> 200.8 | K22: =F22*H22 -> 903.6 | L22: =F22*I22 -> 2710.8 | M22: demolição de piso cerâmico
A23: 2. Demolições e retiradas | B23: 97633 | C23: SINAPI composição | D23: DEMOLIÇÃO DE REVESTIMENTO CERÂMICO, DE FORMA MANUAL, SEM REAPROVEITAMENTO. AF_09/2023 | E23: M2 | F23: 28.42 | G23: 6 | H23: 27 | I23: 81 | J23: =F23*G23 -> 170.52 | K23: =F23*H23 -> 767.34 | L23: =F23*I23 -> 2302.02 | M23: demolição de revestimento de parede
A24: 2. Demolições e retiradas | B24: 97645 | C24: SINAPI composição | D24: REMOÇÃO DE JANELAS, DE FORMA MANUAL, SEM REAPROVEITAMENTO. AF_09/2023 | E24: M2 | F24: 30.78 | G24: 3 | H24: 13.5 | I24: 40.5 | J24: =F24*G24 -> 92.34 | K24: =F24*H24 -> 415.53 | L24: =F24*I24 -> 1246.59 | M24: remoção de janelas
A25: 3. Cobertura e forro | B25: 92539 | C25: SINAPI composição | D25: TRAMA DE MADEIRA COMPOSTA POR RIPAS, CAIBROS E TERÇAS PARA TELHADOS DE ATÉ 2 ÁGUAS PARA TELHA CERÂMICA OU DE CONCRETO, INCLUSO TRANSPORTE VERTICAL. AF_10/2025 | E25: M2 | F25: 101.54 | G25: 25 | H25: 93.75 | I25: 281.25 | J25: =F25*G25 -> 2538.5 | K25: =F25*H25 -> 9519.375 | L25: =F25*I25 -> 28558.125 | M25: trama de madeira nova
A26: 3. Cobertura e forro | B26: 94440 | C26: SINAPI composição | D26: TELHAMENTO COM TELHA CERÂMICA DE ENCAIXE, TIPO FRANCESA, COM ATÉ 2 ÁGUAS, INCLUSO TRANSPORTE VERTICAL. AF_06/2026 | E26: M2 | F26: 42.42 | G26: 50 | H26: 187.5 | I26: 562.5 | J26: =F26*G26 -> 2121 | K26: =F26*H26 -> 7953.75 | L26: =F26*I26 -> 23861.25 | M26: telha cerâmica nova
A27: 3. Cobertura e forro | B27: 96116 | C27: SINAPI composição | D27: FORRO EM RÉGUAS DE PVC, FRISADO, PARA AMBIENTES COMERCIAIS, INCLUSIVE ESTRUTURA BIDIRECIONAL DE FIXAÇÃO. AF_08/2023_PS | E27: M2 | F27: 73.2 | G27: 40 | H27: 150 | I27: 450 | J27: =F27*G27 -> 2928 | K27: =F27*H27 -> 10980 | L27: =F27*I27 -> 32940 | M27: forro de PVC novo
A28: 4. Revestimentos e pisos | B28: 87879 | C28: SINAPI composição | D28: CHAPISCO APLICADO EM ALVENARIAS E ESTRUTURAS DE CONCRETO INTERNAS, COM COLHER DE PEDREIRO. ARGAMASSA TRAÇO 1:3 COM PREPARO EM BETONEIRA 400L. AF_10/2022 | E28: M2 | F28: 6.03 | G28: 48 | H28: 216 | I28: 648 | J28: =F28*G28 -> 289.44 | K28: =F28*H28 -> 1302.48 | L28: =F28*I28 -> 3907.44 | M28: chapisco em paredes recuperadas
A29: 4. Revestimentos e pisos | B29: 104958 | C29: SINAPI composição | D29: MASSA ÚNICA, EM ARGAMASSA TRAÇO 1:2:8 PREPARO MECÂNICO, APLICADA MANUALMENTE EM PAREDES INTERNAS DE AMBIENTES COM ÁREA MAIOR QUE 10M², E = 10MM, COM TALISCAS. AF_03/2024 | E29: M2 | F29: 31.79 | G29: 48 | H29: 216 | I29: 648 | J29: =F29*G29 -> 1525.92 | K29: =F29*H29 -> 6866.64 | L29: =F29*I29 -> 20599.92 | M29: massa única em paredes recuperadas
... A50: 8. Prevenção contra incêndio | B50: 90838 | C50: SINAPI composição | D50: PORTA CORTA-FOGO 90X210X5CM - FORNECIMENTO E INSTALAÇÃO. AF_10/2025 | E50: UN | F50: 1253.09 | G50: 1 | H50: 1 | I50: 2 | J50: =F50*G50 -> 1253.09 | K50: =F50*H50 -> 1253.09 | L50: =F50*I50 -> 2506.18 | M50: porta corta-fogo 90x210 na rota de saída de emergência
I51: Custo direto | J51: =SUM(J18:J50) -> 35480.811 | K51: =SUM(K18:K50) -> 104912.74 | L51: =SUM(L18:L50) -> 287252.02
I52: BDI | J52: =PARAMETROS!$B$6 -> 0.2034 | K52: =PARAMETROS!$C$6 -> 0.2212 | L52: =PARAMETROS!$D$6 -> 0.25
I53: Contingência | J53: =PARAMETROS!$B$8 -> 0.05 | K53: =PARAMETROS!$C$8 -> 0.1 | L53: =PARAMETROS!$D$8 -> 0.15
I54: Fator regional | J54: =PARAMETROS!$B$9 -> 1 | K54: =PARAMETROS!$C$9 -> 1 | L54: =PARAMETROS!$D$9 -> 1.1
I55: TOTAL ESTIMADO (R$) | J55: =J51*(1+J52)*(1+J53)*J54 -> 44832.489 | K55: =K51*(1+K52)*(1+K53)*K54 -> 140931.38 | L55: =L51*(1+L52)*(1+L53)*L54 -> 454217.26
A57: Estimativa preliminar paramétrica, não vinculante, para planejamento orçamentário. Não substitui o orçamento detalhado do projeto. PROVISORIO - aguarda aprovacao

Sheet DEMANDAS-TIPO
A1: Demandas-tipo (premissas a aprovar uma vez por engenheiro revisor)
A2: PROVISORIO - aguarda aprovacao
A4: Demanda-tipo | B4: Unidade-chave | C4: Premissas e coeficientes (mín/prov/máx)
A5: Via urbana com drenagem e pavimentação | B5: metro de via | C5: Pista 5/6/7 m; passeios 1,2/1,5/2,0 m; base+sub-base 15/20/30 cm; CBUQ 4/5/5 cm; rede DN 600/600/800; PV a cada 40 m; 2 BL a cada 40 m; meio-fio, sarjeta, passeio, rampas e faixas.
A6: Microdrenagem em via existente | B6: metro de rede | C6: Vala DN+0,6 x DN+1,0 m; tubo de concreto; PV a cada 40 m; 2 BL a cada 40 m com ligação DN 400; recomposição de base 20 cm e CBUQ 5 cm na faixa da vala; bota-fora a 10 km.
A7: Contenção de encosta (solo grampeado + concreto projetado) | B7: m² de face | C7: Grampos em malha 2,0/1,5/1,25 m, comprimento 6/8/12 m; concreto projetado 10/10/15 cm; drenos 0,6 m/m²; canaletas de crista e pé; descidas d'água; grama em 30% da área. Calibrada com a média do Novo PAC Encostas citada nos documentos (R$ 1.692/m²).
A8: Edificação térrea nova | B8: m² construído | C8: Concreto 0,12 m³/m²; aço 10 kg/m²; fôrma 1,1 m²/m²; alvenaria 1,5 m²/m²; cobertura cerâmica 1,25 m²/m²; forro PVC; piso cerâmico; portas 1/15 m²; janelas 0,15 m²/m²; elétrica e hidrossanitária simplificadas; prevenção contra incêndio básica. Remanescente de obra = fração da área.
A9: Reforma predial | B9: m² reformado | C9: Fração refeita de cobertura/forro/piso/reboco/esquadrias/instalações: 20/20/10/10/10/20% (leve), 50/50/30/30/30/50% (média), 100/100/60/60/60/100% (pesada); pintura integral; extintores, emergência e rota de fuga.
A10: Quadra poliesportiva coberta | B10: unidade | C10: Piso 32 x 20 m em concreto armado 8 cm; cobertura metálica 748 m² (18/25/32 kg/m² de aço); alambrado 104 x 2 m; tabelas; refletores; vestiário 0/40/60 m².
A11: Campo de futebol | B11: unidade | C11: Campo 70x45 / 90x60 / 100x64 m; regularização; drenos a cada 5 m; grama em placas; alambrado; calçadas; vestiário 60/80/120 m².
A12: Abrigo de passageiros | B12: unidade | C12: Abrigo 4 x 3 m: fundação, estrutura de aço 300 kg, telha termoacústica 12 m², piso 12 m², banco e piso podotátil.
A13: Adequação de cozinha escolar | B13: unidade | C13: Abrigo de GLP, janela de ventilação, 15 m² de revestimento de parede e de piso, caixa de gordura, bancada, pontos elétricos, luminárias e extintor (sem exaustor: sem preço no SINAPI-BA).
A14: Banheiro com chuveiro + grade | B14: unidade | C14: Banheiro de cerca de 4 m² com louças, chuveiro, instalações e porta; grade de aço de 2,1 m² na porta de entrada.
A15: Proteção emergencial de fachada | B15: verba por quantidades | C15: Tapume, estroncas de eucalipto com mão de obra, montagem de andaime fachadeiro, tela de proteção e lona na cobertura.
... A19: Reforma de unidade de acolhimento (Justiça) | B19: m² reformado | C19: Reforma predial-tipo + porta corta-fogo na rota de saída (1/1/2 unidades); projeto de segurança contra incêndio na contingência.

Sheet FONTES
A1: Fontes e limitações
A2: PROVISORIO - aguarda aprovacao
A4: SINAPI/CAIXA - Relatórios mensais, ref. 08/2026 (publicado em 11/09/2026), recorte BA, regime sem desoneração: composições (aba CSD) e insumos (aba ISD). Arquivo: _PRECOS/SINAPI_BA_NAO_DESONERADO_2026_08.zip.
A5: Acórdão n. 2.622/2013-TCU-Plenário - faixas referenciais de BDI (construção de edifícios; construção de rodovias e ferrovias). Conferido em reproduções públicas do texto.
A6: IBRAOP - OT-IBR 004/2012 (precisão do orçamento de obras públicas): ±30% para estudos preliminares em edificações. Conferido em documentos que reproduzem a OT.
A7: CAIXA - SINAPI: metodologias e conceitos (coleta de preços nas capitais, sem frete). Conferido em reprodução pública.
A8: Base legal: nos termos da Lei n. 14.133/2021 e do Decreto Municipal n. 269/2025 (citados sem artigo).
A9: Quantidades: documentos dos pacotes MP_FILTRADO de 12/10/2026 (mp_objetos.json) e JUSTICA_FILTRADO de 13/10/2026 (justica_objetos.json) e demandas-tipo desta planilha.
A10: Limitação: composições sem preço na BA (ex.: imprimação, pintura de ligação, exaustores, central de alarme, locação de andaime) não estão incluídas; quantidades da maioria dos objetos são premissas a confirmar.
A11: Limitação: OpenStreetMap e sites oficiais não puderam ser acessados neste ambiente; comprimentos de ruas não foram medidos.
A12: Contratos da SEINFRA e editais de outras prefeituras não foram usados como base de preço.
